Workbook
Name Producto: 'Costo Materia Prima'!$D$3:$D$181

Sheet Precios Mayoreo
J1: Precio Sugerido Venta al Público | Q1: Precio Sugerido Venta a Mayoreo
C2: Presentación de Sub-producto | J2: 0.45 | Q2: 0.05
A3: Producto | B3: Sub-producto | C3: Individual | D3: Mini | E3: Chico | F3: Mediano | G3: Grande | H3: Rebanada | J3: Individual | K3: Mini | L3: Chico | M3: Mediano | N3: Grande | O3: Rebanada | Q3: Individual | R3: Mini | S3: Chico | T3: Mediano | U3: Grande | V3: Rebanada
A4: Pay | B4: Fresa | C4: =Pay!C53 -> 18.916121 | D4: 0 | E4: 0 | F4: =Pay!D53 -> 140.58423 | G4: =Pay!E53 -> 240.03393 | H4: =Pay!F53 -> 32.704881 | J4: =C4/$J$2 -> 42.035824 | K4: =D4/$J$2 -> 0 | L4: =E4/$J$2 -> 0 | M4: =F4/$J$2 -> 312.4094 | N4: =G4/$J$2 -> 533.40873 | O4: =H4/$J$2 -> 72.677513 | Q4: =J4*(1-$Q$2) -> 39.934033 | R4: =K4*(1-$Q$2) -> 0 | S4: =L4*(1-$Q$2) -> 0 | T4: =M4*(1-$Q$2) -> 296.78893 | U4: =N4*(1-$Q$2) -> 506.73829 | V4: =O4*(1-$Q$2) -> 69.043637
B5: Guayaba | C5: =Pay!C54 -> 19.055935 | D5: 0 | E5: 0 | F5: =Pay!D54 -> 148.26907 | G5: =Pay!E54 -> 240.58042 | H5: =Pay!F54 -> 32.773193 | J5: =C5/$J$2 -> 42.346523 | K5: =D5/$J$2 -> 0 | L5: =E5/$J$2 -> 0 | M5: =F5/$J$2 -> 329.48683 | N5: =G5/$J$2 -> 534.62316 | O5: =H5/$J$2 -> 72.829317 | Q5: =J5*(1-$Q$2) -> 40.229197 | R5: =K5*(1-$Q$2) -> 0 | S5: =L5*(1-$Q$2) -> 0 | T5: =M5*(1-$Q$2) -> 313.01249 | U5: =N5*(1-$Q$2) -> 507.892 | V5: =O5*(1-$Q$2) -> 69.187851
B6: Galleta con cajeta | C6: =Pay!C55 -> 20.11006 | D6: 0 | E6: 0 | F6: =Pay!D55 -> 135.33744 | G6: =Pay!E55 -> 229.02898 | H6: =Pay!F55 -> 31.329262 | J6: =C6/$J$2 -> 44.689022 | K6: =D6/$J$2 -> 0 | L6: =E6/$J$2 -> 0 | M6: =F6/$J$2 -> 300.74987 | N6: =G6/$J$2 -> 508.95328 | O6: =H6/$J$2 -> 69.620583 | Q6: =J6*(1-$Q$2) -> 42.454571 | R6: =K6*(1-$Q$2) -> 0 | S6: =L6*(1-$Q$2) -> 0 | T6: =M6*(1-$Q$2) -> 285.71238 | U6: =N6*(1-$Q$2) -> 483.50562 | V6: =O6*(1-$Q$2) -> 66.139553
B7: Oreo | C7: =Pay!C57 -> 18.623235 | D7: 0 | E7: 0 | F7: =Pay!D57 -> 139.81162 | G7: =Pay!E57 -> 238.53794 | H7: =Pay!F57 -> 32.517883 | J7: =C7/$J$2 -> 41.384968 | K7: =D7/$J$2 -> 0 | L7: =E7/$J$2 -> 0 | M7: =F7/$J$2 -> 310.69249 | N7: =G7/$J$2 -> 530.08432 | O7: =H7/$J$2 -> 72.261962 | Q7: =J7*(1-$Q$2) -> 39.315719 | R7: =K7*(1-$Q$2) -> 0 | S7: =L7*(1-$Q$2) -> 0 | T7: =M7*(1-$Q$2) -> 295.15787 | U7: =N7*(1-$Q$2) -> 503.5801 | V7: =O7*(1-$Q$2) -> 68.648864
B8: Pay horneado | C8: =Pay!C58 -> 0 | D8: 0 | E8: 0 | F8: =Pay!D58 -> 86.851881 | G8: =Pay!E58 -> 148.87704 | H8: =Pay!F58 -> 21.310271 | J8: =C8/$J$2 -> 0 | K8: =D8/$J$2 -> 0 | L8: =E8/$J$2 -> 0 | M8: =F8/$J$2 -> 193.00418 | N8: =G8/$J$2 -> 330.83788 | O8: =H8/$J$2 -> 47.356157 | Q8: =J8*(1-$Q$2) -> 0 | R8: =K8*(1-$Q$2) -> 0 | S8: =L8*(1-$Q$2) -> 0 | T8: =M8*(1-$Q$2) -> 183.35397 | U8: =N8*(1-$Q$2) -> 314.29598 | V8: =O8*(1-$Q$2) -> 44.988349
B9: Pay de queso | C9: =Pay!C59 -> 0 | D9: 0 | E9: 0 | F9: =Pay!D59 -> 115.18762 | G9: =Pay!E59 -> 195.44594 | H9: =Pay!F59 -> 27.131383 | J9: =C9/$J$2 -> 0 | K9: =D9/$J$2 -> 0 | L9: =E9/$J$2 -> 0 | M9: =F9/$J$2 -> 255.97249 | N9: =G9/$J$2 -> 434.32432 | O9: =H9/$J$2 -> 60.291962 | Q9: =J9*(1-$Q$2) -> 0 | R9: =K9*(1-$Q$2) -> 0 | S9: =L9*(1-$Q$2) -> 0 | T9: =M9*(1-$Q$2) -> 243.17387 | U9: =N9*(1-$Q$2) -> 412.6081 | V9: =O9*(1-$Q$2) -> 57.277364
A10: Pastel | B10: Fresas con Crema | C10: ='Pastel Fresas Con Crema'!D12 -> 0 | D10: ='Pastel Fresas Con Crema'!E12 -> 77.965623 | E10: ='Pastel Fresas Con Crema'!F12 -> 149.6192 | F10: ='Pastel Fresas Con Crema'!G12 -> 210.11335 | G10: ='Pastel Fresas Con Crema'!H12 -> 338.61711 | H10: ='Pastel Fresas Con Crema'!C12 -> 23.818475 | J10: =C10/$J$2 -> 0 | K10: =D10/$J$2 -> 173.25694 | L10: =E10/$J$2 -> 332.48712 | M10: =F10/$J$2 -> 466.91855 | N10: =G10/$J$2 -> 752.48247 | O10: =H10/$J$2 -> 52.929944 | Q10: =J10*(1-$Q$2) -> 0 | R10: =K10*(1-$Q$2) -> 164.59409 | S10: =L10*(1-$Q$2) -> 315.86276 | T10: =M10*(1-$Q$2) -> 443.57263 | U10: =N10*(1-$Q$2) -> 714.85835 | V10: =O10*(1-$Q$2) -> 50.283447
B11: 3 Pecados | C11: 0 | D11: ='Pastel 3 Pecados'!E18 -> 64.125646 | E11: ='Pastel 3 Pecados'!F18 -> 163.26597 | F11: ='Pastel 3 Pecados'!G18 -> 234.88562 | G11: ='Pastel 3 Pecados'!H18 -> 350.57494 | H11: ='Pastel 3 Pecados'!C18 -> 26.295702 | J11: =C11/$J$2 -> 0 | K11: =D11/$J$2 -> 142.50144 | L11: =E11/$J$2 -> 362.81327 | M11: =F11/$J$2 -> 521.96804 | N11: =G11/$J$2 -> 779.05543 | O11: =H11/$J$2 -> 58.434893 | Q11: =J11*(1-$Q$2) -> 0 | R11: =K11*(1-$Q$2) -> 135.37636 | S11: =L11*(1-$Q$2) -> 344.67261 | T11: =M11*(1-$Q$2) -> 495.86964 | U11: =N11*(1-$Q$2) -> 740.10266 | V11: =O11*(1-$Q$2) -> 55.513149
B12: Zanahoria | C12: 0 | D12: 0 | E12: ='Pastel Zanahoria'!F12 -> 151.95679 | F12: ='Pastel Zanahoria'!G12 -> 207.49008 | G12: ='Pastel Zanahoria'!H12 -> 317.43002 | H12: ='Pastel Zanahoria'!C12 -> 23.556148 | J12: =C12/$J$2 -> 0 | K12: =D12/$J$2 -> 0 | L12: =E12/$J$2 -> 337.68175 | M12: =F12/$J$2 -> 461.08908 | N12: =G12/$J$2 -> 705.40005 | O12: =H12/$J$2 -> 52.346997 | Q12: =J12*(1-$Q$2) -> 0 | R12: =K12*(1-$Q$2) -> 0 | S12: =L12*(1-$Q$2) -> 320.79766 | T12: =M12*(1-$Q$2) -> 438.03462 | U12: =N12*(1-$Q$2) -> 670.13005 | V12: =O12*(1-$Q$2) -> 49.729647
B13: Chocolate | C13: 0 | D13: ='Pastel Chocolate'!E12 -> 59.756374 | E13: 0 | F13: 0 | G13: 0 | H13: 0 | J13: =C13/$J$2 -> 0 | K13: =D13/$J$2 -> 132.79194 | L13: =E13/$J$2 -> 0 | M13: =F13/$J$2 -> 0 | N13: =G13/$J$2 -> 0 | O13: =H13/$J$2 -> 0 | Q13: =J13*(1-$Q$2) -> 0 | R13: =K13*(1-$Q$2) -> 126.15235 | S13: =L13*(1-$Q$2) -> 0 | T13: =M13*(1-$Q$2) -> 0 | U13: =N13*(1-$Q$2) -> 0 | V13: =O13*(1-$Q$2) -> 0
B14: Crunch | C14: 0 | D14: ='Pastel Crunch'!E14 -> 80.227256 | E14: ='Pastel Crunch'!F14 -> 166.4893 | F14: ='Pastel Crunch'!G14 -> 242.04424 | G14: ='Pastel Crunch'!H14 -> 338.62657 | H14: ='Pastel Crunch'!C14 -> 27.011564 | J14: =C14/$J$2 -> 0 | K14: =D14/$J$2 -> 178.28279 | L14: =E14/$J$2 -> 369.97623 | M14: =F14/$J$2 -> 537.87609 | N14: =G14/$J$2 -> 752.50349 | O14: =H14/$J$2 -> 60.025697 | Q14: =J14*(1-$Q$2) -> 0 | R14: =K14*(1-$Q$2) -> 169.36865 | S14: =L14*(1-$Q$2) -> 351.47742 | T14: =M14*(1-$Q$2) -> 510.98228 | U14: =N14*(1-$Q$2) -> 714.87832 | V14: =O14*(1-$Q$2) -> 57.024413
B15: Snicker's | C15: 0 | D15: ='Pastel Snicker''s'!E14 -> 33.131041 | E15: ='Pastel Snicker''s'!F14 -> 201.96184 | F15: ='Pastel Snicker''s'!G14 -> 281.62809 | G15: ='Pastel Snicker''s'!H14 -> 392.15336 | H15: ='Pastel Snicker''s'!C14 -> 30.969949 | J15: =C15/$J$2 -> 0 | K15: =D15/$J$2 -> 73.624534 | L15: =E15/$J$2 -> 448.8041 | M15: =F15/$J$2 -> 625.84019 | N15: =G15/$J$2 -> 871.45192 | O15: =H15/$J$2 -> 68.822108 | Q15: =J15*(1-$Q$2) -> 0 | R15: =K15*(1-$Q$2) -> 69.943308 | S15: =L15*(1-$Q$2) -> 426.36389 | T15: =M15*(1-$Q$2) -> 594.54818 | U15: =N15*(1-$Q$2) -> 827.87932 | V15: =O15*(1-$Q$2) -> 65.381003
B16: Dulce de Leche | C16: 0 | D16: ='Pastel Vainilla'!E12 -> 0 | E16: ='Pastel Vainilla'!F12 -> 146.8559 | F16: ='Pastel Vainilla'!G12 -> 205.71168 | G16: ='Pastel Vainilla'!H12 -> 330.05251 | H16: ='Pastel Vainilla'!C12 -> 17.49273 | J16: =C16/$J$2 -> 0 | K16: =D16/$J$2 -> 0 | L16: =E16/$J$2 -> 326.34644 | M16: =F16/$J$2 -> 457.13706 | N16: =G16/$J$2 -> 733.45002 | O16: =H16/$J$2 -> 38.872733 | Q16: =J16*(1-$Q$2) -> 0 | R16: =K16*(1-$Q$2) -> 0 | S16: =L16*(1-$Q$2) -> 310.02912 | T16: =M16*(1-$Q$2) -> 434.2802 | U16: =N16*(1-$Q$2) -> 696.77752 | V16: =O16*(1-$Q$2) -> 36.929097
B17: 3 Leches | C17: 0 | D17: 0 | E17: 0 | F17: ='Pastel 3 Leches'!D13 -> 176.71615 | G17: ='Pastel 3 Leches'!E13 -> 401.53172 | H17: ='Pastel 3 Leches'!C13 -> 32.259831 | J17: =C17/$J$2 -> 0 | K17: =D17/$J$2 -> 0 | L17: =E17/$J$2 -> 0 | M17: =F17/$J$2 -> 392.70255 | N17: =G17/$J$2 -> 892.29271 | O17: =H17/$J$2 -> 71.688514 | Q17: =J17*(1-$Q$2) -> 0 | R17: =K17*(1-$Q$2) -> 0 | S17: =L17*(1-$Q$2) -> 0 | T17: =M17*(1-$Q$2) -> 373.06742 | U17: =N17*(1-$Q$2) -> 847.67808 | V17: =O17*(1-$Q$2) -> 68.104089
B18: 3 Leches Lotus | C18: ='Pastel 3 Leches Lotus'!F14 -> 41.38822 | F18: ='Pastel 3 Leches Lotus'!D14 -> 188.12781 | G18: ='Pastel 3 Leches Lotus'!E14 -> 504.65497 | H18: ='Pastel 3 Leches Lotus'!C14 -> 34.161774 | J18: =C18/$J$2 -> 91.973822 | K18: =D18/$J$2 -> 0 | L18: =E18/$J$2 -> 0 | M18: =F18/$J$2 -> 418.06179 | N18: =G18/$J$2 -> 1121.4555 | O18: =H18/$J$2 -> 75.915054 | Q18: =J18*(1-$Q$2) -> 87.375131 | R18: =K18*(1-$Q$2) -> 0 | S18: =L18*(1-$Q$2) -> 0 | T18: =M18*(1-$Q$2) -> 397.1587 | U18: =N18*(1-$Q$2) -> 1065.3827 | V18: =O18*(1-$Q$2) -> 72.119301
B19: Flan | C19: =Flan!D9 -> 22.94585 | D19: 0 | E19: 0 | F19: =Flan!G9 -> 241.70639 | G19: 0 | H19: =Flan!I9 -> 0 | J19: =C19/$J$2 -> 50.990777 | K19: =D19/$J$2 -> 0 | L19: =E19/$J$2 -> 0 | M19: =F19/$J$2 -> 537.1253 | N19: =G19/$J$2 -> 0 | O19: =H19/$J$2 -> 0 | Q19: =J19*(1-$Q$2) -> 48.441238 | R19: =K19*(1-$Q$2) -> 0 | S19: =L19*(1-$Q$2) -> 0 | T19: =M19*(1-$Q$2) -> 510.26904 | U19: =N19*(1-$Q$2) -> 0 | V19: =O19*(1-$Q$2) -> 0
A20: Vasos | B20: Fresas con crema | D20: =Vasos!D24 -> 17.018195 | G20: =Vasos!C24 -> 32.405495 | J20: =C20/$J$2 -> 0 | K20: =D20/$J$2 -> 37.818211 | L20: =E20/$J$2 -> 0 | M20: =F20/$J$2 -> 0 | N20: =G20/$J$2 -> 72.012211 | O20: =H20/$J$2 -> 0 | Q20: =J20*(1-$Q$2) -> 0 | R20: =K20*(1-$Q$2) -> 35.9273 | S20: =L20*(1-$Q$2) -> 0 | T20: =M20*(1-$Q$2) -> 0 | U20: =N20*(1-$Q$2) -> 68.411601 | V20: =O20*(1-$Q$2) -> 0
B21: Fresas con pay | D21: =Vasos!D25 -> 29.233566 | G21: =Vasos!C25 -> 44.620867 | J21: =C21/$J$2 -> 0 | K21: =D21/$J$2 -> 64.963481 | L21: =E21/$J$2 -> 0 | M21: =F21/$J$2 -> 0 | N21: =G21/$J$2 -> 99.157481 | O21: =H21/$J$2 -> 0 | Q21: =J21*(1-$Q$2) -> 0 | R21: =K21*(1-$Q$2) -> 61.715307 | S21: =L21*(1-$Q$2) -> 0 | T21: =M21*(1-$Q$2) -> 0 | U21: =N21*(1-$Q$2) -> 94.199607 | V21: =O21*(1-$Q$2) -> 0
B22: Crema | D22: =Vasos!D26 -> 9.8099053 | G22: =Vasos!C26 -> 17.08788 | J22: =C22/$J$2 -> 0 | K22: =D22/$J$2 -> 21.79979 | L22: =E22/$J$2 -> 0 | M22: =F22/$J$2 -> 0 | N22: =G22/$J$2 -> 37.973066 | O22: =H22/$J$2 -> 0 | Q22: =J22*(1-$Q$2) -> 0 | R22: =K22*(1-$Q$2) -> 20.7098 | S22: =L22*(1-$Q$2) -> 0 | T22: =M22*(1-$Q$2) -> 0 | U22: =N22*(1-$Q$2) -> 36.074413 | V22: =O22*(1-$Q$2) -> 0
A23: Bollos | B23: Chocolate | C23: =Bollos!D14 -> 14.435269 | D23: ='Pastel Fresas Con Crema'!E24 -> 0 | E23: ='Pastel Fresas Con Crema'!F24 -> 0 | F23: ='Pastel Fresas Con Crema'!G24 -> 0 | G23: ='Pastel Fresas Con Crema'!H24 -> 0 | H23: ='Pastel Fresas Con Crema'!C24 -> 0 | J23: =C23/$J$2 -> 32.078376 | K23: =D23/$J$2 -> 0 | L23: =E23/$J$2 -> 0 | M23: =F23/$J$2 -> 0 | N23: =G23/$J$2 -> 0 | O23: =H23/$J$2 -> 0 | Q23: =J23*(1-$Q$2) -> 30.474457 | R23: =K23*(1-$Q$2) -> 0 | S23: =L23*(1-$Q$2) -> 0 | T23: =M23*(1-$Q$2) -> 0 | U23: =N23*(1-$Q$2) -> 0 | V23: =O23*(1-$Q$2) -> 0
B24: Vainilla | C24: =Bollos!C14 -> 12.485675 | J24: =C24/$J$2 -> 27.745944 | K24: =D24/$J$2 -> 0 | L24: =E24/$J$2 -> 0 | M24: =F24/$J$2 -> 0 | N24: =G24/$J$2 -> 0 | O24: =H24/$J$2 -> 0 | Q24: =J24*(1-$Q$2) -> 26.358647 | R24: =K24*(1-$Q$2) -> 0 | S24: =L24*(1-$Q$2) -> 0 | T24: =M24*(1-$Q$2) -> 0 | U24: =N24*(1-$Q$2) -> 0 | V24: =O24*(1-$Q$2) -> 0
B25: Zanahoria | C25: =Bollos!F14 -> 12.928453 | D25: 0 | E25: ='Pastel Zanahoria'!F21 -> 0 | F25: ='Pastel Zanahoria'!G21 -> 0 | G25: ='Pastel Zanahoria'!H21 -> 0 | H25: ='Pastel Zanahoria'!C21 -> 0 | J25: =C25/$J$2 -> 28.729896 | K25: =D25/$J$2 -> 0 | L25: =E25/$J$2 -> 0 | M25: =F25/$J$2 -> 0 | N25: =G25/$J$2 -> 0 | O25: =H25/$J$2 -> 0 | Q25: =J25*(1-$Q$2) -> 27.293401 | R25: =K25*(1-$Q$2) -> 0 | S25: =L25*(1-$Q$2) -> 0 | T25: =M25*(1-$Q$2) -> 0 | U25: =N25*(1-$Q$2) -> 0 | V25: =O25*(1-$Q$2) -> 0
B26: Red Velvet | C26: =Bollos!E14 -> 13.970433 | D26: ='Pastel Chocolate'!E24 -> 0 | E26: ='Pastel Chocolate'!F24 -> 0 | F26: ='Pastel Chocolate'!G24 -> 0 | G26: ='Pastel Chocolate'!H24 -> 0 | H26: ='Pastel Chocolate'!C24 -> 0 | J26: =C26/$J$2 -> 31.045406 | K26: =D26/$J$2 -> 0 | L26: =E26/$J$2 -> 0 | M26: =F26/$J$2 -> 0 | N26: =G26/$J$2 -> 0 | O26: =H26/$J$2 -> 0 | Q26: =J26*(1-$Q$2) -> 29.493136 | R26: =K26*(1-$Q$2) -> 0 | S26: =L26*(1-$Q$2) -> 0 | T26: =M26*(1-$Q$2) -> 0 | U26: =N26*(1-$Q$2) -> 0 | V26: =O26*(1-$Q$2) -> 0
B27: Lotus | C27: =Bollos!G14 -> 20.155525 | D27: 0 | E27: 0 | F27: 0 | G27: 0 | H27: 0 | J27: =C27/$J$2 -> 44.790056 | K27: =D27/$J$2 -> 0 | L27: =E27/$J$2 -> 0 | M27: =F27/$J$2 -> 0 | N27: =G27/$J$2 -> 0 | O27: =H27/$J$2 -> 0 | Q27: =J27*(1-$Q$2) -> 42.550553 | R27: =K27*(1-$Q$2) -> 0 | S27: =L27*(1-$Q$2) -> 0 | T27: =M27*(1-$Q$2) -> 0 | U27: =N27*(1-$Q$2) -> 0 | V27: =O27*(1-$Q$2) -> 0
A28: Cheesecake | B28: Lotus | C28: =Cheesecake!J29 -> 60.99483 | D28: 0 | E28: =Cheesecake!G29 -> 205.30523 | F28: =Cheesecake!D29 -> 319.64719 | G28: 0 | H28: ='Pastel Fresas Con Crema'!C29 -> 0 | J28: =C28/$J$2 -> 135.54407 | K28: =D28/$J$2 -> 0 | L28: =E28/$J$2 -> 456.23384 | M28: =F28/$J$2 -> 710.32709 | N28: =G28/$J$2 -> 0 | O28: =H28/$J$2 -> 0 | Q28: =J28*(1-$Q$2) -> 128.76686 | R28: =K28*(1-$Q$2) -> 0 | S28: =L28*(1-$Q$2) -> 433.42214 | T28: =M28*(1-$Q$2) -> 674.81073 | U28: =N28*(1-$Q$2) -> 0 | V28: =O28*(1-$Q$2) -> 0
B29: Tortuga | C29: =Cheesecake!U29 -> 52.683417 | D29: ='Pastel 3 Pecados'!E31 -> 0 | E29: =Cheesecake!R29 -> 182.33088 | F29: =Cheesecake!O29 -> 254.16219 | G29: ='Pastel 3 Pecados'!H31 -> 0 | H29: ='Pastel 3 Pecados'!C31 -> 0 | J29: =C29/$J$2 -> 117.07426 | K29: =D29/$J$2 -> 0 | L29: =E29/$J$2 -> 405.17974 | M29: =F29/$J$2 -> 564.80487 | N29: =G29/$J$2 -> 0 | O29: =H29/$J$2 -> 0 | Q29: =J29*(1-$Q$2) -> 111.22055 | R29: =K29*(1-$Q$2) -> 0 | S29: =L29*(1-$Q$2) -> 384.92075 | T29: =M29*(1-$Q$2) -> 536.56463 | U29: =N29*(1-$Q$2) -> 0 | V29: =O29*(1-$Q$2) -> 0
B30: Brownie | C30: =Cheesecake!AF29 -> 45.518018 | D30: 0 | E30: =Cheesecake!AC29 -> 179.67515 | F30: =Cheesecake!Z29 -> 250.2993 | G30: 0 | H30: 0 | J30: =C30/$J$2 -> 101.15115 | K30: =D30/$J$2 -> 0 | L30: =E30/$J$2 -> 399.2781 | M30: =F30/$J$2 -> 556.22067 | N30: =G30/$J$2 -> 0 | O30: =H30/$J$2 -> 0 | Q30: =J30*(1-$Q$2) -> 96.093595 | R30: =K30*(1-$Q$2) -> 0 | S30: =L30*(1-$Q$2) -> 379.3142 | T30: =M30*(1-$Q$2) -> 528.40964 | U30: =N30*(1-$Q$2) -> 0 | V30: =O30*(1-$Q$2) -> 0
B31: Zarzamora | C31: =Cheesecake!AQ29 -> 52.866543 | D31: 0 | E31: =Cheesecake!AN29 -> 198.97726 | F31: =Cheesecake!AK29 -> 286.3147 | G31: 0 | H31: 0 | J31: =C31/$J$2 -> 117.48121 | K31: =D31/$J$2 -> 0 | L31: =E31/$J$2 -> 442.1717 | M31: =F31/$J$2 -> 636.25488 | N31: =G31/$J$2 -> 0 | O31: =H31/$J$2 -> 0 | Q31: =J31*(1-$Q$2) -> 111.60715 | R31: =K31*(1-$Q$2) -> 0 | S31: =L31*(1-$Q$2) -> 420.06311 | T31: =M31*(1-$Q$2) -> 604.44214 | U31: =N31*(1-$Q$2) -> 0 | V31: =O31*(1-$Q$2) -> 0
B32: Zanahoria | C32: 0 | D32: 0 | E32: 0 | F32: 0 | G32: 0 | H32: 0 | J32: =C32/$J$2 -> 0 | K32: =D32/$J$2 -> 0 | L32: =E32/$J$2 -> 0 | M32: =F32/$J$2 -> 0 | N32: =G32/$J$2 -> 0 | O32: =H32/$J$2 -> 0 | Q32: =J32*(1-$Q$2) -> 0 | R32: =K32*(1-$Q$2) -> 0 | S32: =L32*(1-$Q$2) -> 0 | T32: =M32*(1-$Q$2) -> 0 | U32: =N32*(1-$Q$2) -> 0 | V32: =O32*(1-$Q$2) -> 0
B33: Cinnamon | C33: 0 | D33: 0 | E33: 0 | F33: 0 | G33: 0 | H33: 0 | J33: =C33/$J$2 -> 0 | K33: =D33/$J$2 -> 0 | L33: =E33/$J$2 -> 0 | M33: =F33/$J$2 -> 0 | N33: =G33/$J$2 -> 0 | O33: =H33/$J$2 -> 0 | Q33: =J33*(1-$Q$2) -> 0 | R33: =K33*(1-$Q$2) -> 0 | S33: =L33*(1-$Q$2) -> 0 | T33: =M33*(1-$Q$2) -> 0 | U33: =N33*(1-$Q$2) -> 0 | V33: =O33*(1-$Q$2) -> 0
B34: Manzana | C34: 0 | D34: 0 | E34: 0 | F34: 0 | G34: 0 | H34: 0 | J34: =C34/$J$2 -> 0 | K34: =D34/$J$2 -> 0 | L34: =E34/$J$2 -> 0 | M34: =F34/$J$2 -> 0 | N34: =G34/$J$2 -> 0 | O34: =H34/$J$2 -> 0 | Q34: =J34*(1-$Q$2) -> 0 | R34: =K34*(1-$Q$2) -> 0 | S34: =L34*(1-$Q$2) -> 0 | T34: =M34*(1-$Q$2) -> 0 | U34: =N34*(1-$Q$2) -> 0 | V34: =O34*(1-$Q$2) -> 0
B35: Limón | C35: =Cheesecake!BB29 -> 51.531339 | D35: 0 | E35: =Cheesecake!AY29 -> 168.3096 | F35: =Cheesecake!AV29 -> 244.24056 | G35: 0 | H35: 0 | J35: =C35/$J$2 -> 114.51409 | K35: =D35/$J$2 -> 0 | L35: =E35/$J$2 -> 374.02133 | M35: =F35/$J$2 -> 542.7568 | N35: =G35/$J$2 -> 0 | O35: =H35/$J$2 -> 0 | Q35: =J35*(1-$Q$2) -> 108.78838 | R35: =K35*(1-$Q$2) -> 0 | S35: =L35*(1-$Q$2) -> 355.32027 | T35: =M35*(1-$Q$2) -> 515.61896 | U35: =N35*(1-$Q$2) -> 0 | V35: =O35*(1-$Q$2) -> 0
B36: Rol Canela | C36: =Cheesecake!BM29 -> 56.522501 | D36: 0 | E36: =Cheesecake!BJ29 -> 194.38114 | F36: =Cheesecake!BG29 -> 280.56721 | G36: 0 | H36: 0 | J36: =C36/$J$2 -> 125.60556 | K36: =D36/$J$2 -> 0 | L36: =E36/$J$2 -> 431.95809 | M36: =F36/$J$2 -> 623.4827 | N36: =G36/$J$2 -> 0 | O36: =H36/$J$2 -> 0 | Q36: =J36*(1-$Q$2) -> 119.32528 | R36: =K36*(1-$Q$2) -> 0 | S36: =L36*(1-$Q$2) -> 410.36019 | T36: =M36*(1-$Q$2) -> 592.30856 | U36: =N36*(1-$Q$2) -> 0 | V36: =O36*(1-$Q$2) -> 0
B37: Manzana | C37: =Cheesecake!BX29 -> 47.115889 | D37: 0 | E37: =Cheesecake!BU29 -> 159.56781 | F37: =Cheesecake!BR29 -> 260.52072 | G37: 0 | H37: 0 | J37: =C37/$J$2 -> 104.70198 | K37: =D37/$J$2 -> 0 | L37: =E37/$J$2 -> 354.59513 | M37: =F37/$J$2 -> 578.93494 | N37: =G37/$J$2 -> 0 | O37: =H37/$J$2 -> 0 | Q37: =J37*(1-$Q$2) -> 99.466877 | R37: =K37*(1-$Q$2) -> 0 | S37: =L37*(1-$Q$2) -> 336.86537 | T37: =M37*(1-$Q$2) -> 549.9882 | U37: =N37*(1-$Q$2) -> 0 | V37: =O37*(1-$Q$2) -> 0
C39: Individual | D39: Mini | E39: Chico | F39: Mediano | G39: Grande | H39: Rebanada | J39: Individual | K39: Mini | L39: Chico | M39: Mediano | N39: Grande | O39: Rebanada | Q39: Individual | R39: Mini | S39: Chico | T39: Mediano | U39: Grande | V39: Rebanada
A40: Promedio | B40: Pastel | C40: 0 | D40: =AVERAGE(D10,D11,D13,D14) -> 70.518725 | E40: =AVERAGE(E10:E12,E14:E15) -> 166.65862 | F40: =AVERAGE(F10:F12,F14:F17) -> 222.6556 | G40: =AVERAGE(G10:G12,G14:G17) -> 352.71232 | H40: =AVERAGE(H10:H12,H14:H17) -> 25.914914 | J40: =C40/$J$2 -> 0 | K40: =D40/$J$2 -> 156.70828 | L40: =E40/$J$2 -> 370.35249 | M40: =F40/$J$2 -> 494.79022 | N40: =G40/$J$2 -> 783.80516 | O40: =H40/$J$2 -> 57.588698 | Q40: =J40*(1-$Q$2) -> 0 | R40: =K40*(1-$Q$2) -> 148.87286 | S40: =L40*(1-$Q$2) -> 351.83487 | T40: =M40*(1-$Q$2) -> 470.05071 | U40: =N40*(1-$Q$2) -> 744.6149 | V40: =O40*(1-$Q$2) -> 54.709263
B41: Pay | C41: =AVERAGE(C4:C7) -> 19.176338 | D41: =AVERAGE(D4:D9) -> 0 | E41: =AVERAGE(E4:E9) -> 0 | F41: =AVERAGE(F4:F6) -> 141.39691 | G41: =AVERAGE(G4:G6) -> 236.54777 | H41: =AVERAGE(H4:H6) -> 32.269112 | J41: =C41/$J$2 -> 42.614084 | K41: =D41/$J$2 -> 0 | L41: =E41/$J$2 -> 0 | M41: =F41/$J$2 -> 314.21537 | N41: =G41/$J$2 -> 525.66172 | O41: =H41/$J$2 -> 71.709137 | Q41: =J41*(1-$Q$2) -> 40.48338 | R41: =K41*(1-$Q$2) -> 0 | S41: =L41*(1-$Q$2) -> 0 | T41: =M41*(1-$Q$2) -> 298.5046 | U41: =N41*(1-$Q$2) -> 499.37864 | V41: =O41*(1-$Q$2) -> 68.123681
B42: Cheesecake | C42: =AVERAGE(C28:C31,C35) -> 52.718829 | D42: =AVERAGE(D28:D31,D35) -> 0 | E42: =AVERAGE(E28:E31,E35) -> 186.91962 | F42: =AVERAGE(F28:F31,F35) -> 270.93279 | G42: =AVERAGE(G28:G31,G35) -> 0 | H42: =AVERAGE(H28:H31,H35) -> 0 | J42: =C42/$J$2 -> 117.15295 | K42: =D42/$J$2 -> 0 | L42: =E42/$J$2 -> 415.37694 | M42: =F42/$J$2 -> 602.07286 | N42: =G42/$J$2 -> 0 | O42: =H42/$J$2 -> 0 | Q42: =J42*(1-$Q$2) -> 111.29531 | R42: =K42*(1-$Q$2) -> 0 | S42: =L42*(1-$Q$2) -> 394.60809 | T42: =M42*(1-$Q$2) -> 571.96922 | U42: =N42*(1-$Q$2) -> 0 | V42: =O42*(1-$Q$2) -> 0
B43: Vasos | C43: =IFERROR(AVERAGE(C20:C22),0) -> 0 | D43: =IFERROR(AVERAGE(D20:D21),0) -> 23.125881 | E43: =IFERROR(AVERAGE(E20:E22),0) -> 0 | F43: =IFERROR(AVERAGE(F20:F22),0) -> 0 | G43: =IFERROR(AVERAGE(G20:G21),0) -> 38.513181 | H43: =IFERROR(AVERAGE(H20:H22),0) -> 0 | J43: =C43/$J$2 -> 0 | K43: =D43/$J$2 -> 51.390846 | L43: =E43/$J$2 -> 0 | M43: =F43/$J$2 -> 0 | N43: =G43/$J$2 -> 85.584846 | O43: =H43/$J$2 -> 0 | Q43: =J43*(1-$Q$2) -> 0 | R43: =K43*(1-$Q$2) -> 48.821304 | S43: =L43*(1-$Q$2) -> 0 | T43: =M43*(1-$Q$2) -> 0 | U43: =N43*(1-$Q$2) -> 81.305604 | V43: =O43*(1-$Q$2) -> 0
B44: Bollos | C44: =AVERAGE(C23:C27) -> 14.795071 | D44: =AVERAGE(D23:D27) -> 0 | E44: =AVERAGE(E23:E27) -> 0 | F44: =AVERAGE(F23:F27) -> 0 | G44: =AVERAGE(G23:G27) -> 0 | H44: =AVERAGE(H23:H27) -> 0 | J44: =C44/$J$2 -> 32.877936 | K44: =D44/$J$2 -> 0 | L44: =E44/$J$2 -> 0 | M44: =F44/$J$2 -> 0 | N44: =G44/$J$2 -> 0 | O44: =H44/$J$2 -> 0 | Q44: =J44*(1-$Q$2) -> 31.234039 | R44: =K44*(1-$Q$2) -> 0 | S44: =L44*(1-$Q$2) -> 0 | T44: =M44*(1-$Q$2) -> 0 | U44: =N44*(1-$Q$2) -> 0 | V44: =O44*(1-$Q$2) -> 0
D51: Ticket Promedio
D52: 3.6-7 tickets | E52: 7-18 tickets | F52: 18-36 tickets | G52: 36+ tickets
D53: Consumo
D54: $1,000-$1,999 | E54: $2,000-$4,999 | F54: $5,000-$9,999 | G54: $10,000 o más
D55: Descuento
D56: 0.05 | E56: 0.08 | F56: 0.1 | G56: 0.15
B57: Fresas con crema | C57: 490 | D57: =C57*(1-$D$56) -> 465.5 | E57: =C57*(1-$E$56) -> 450.8 | F57: =C57*(1-$F$56) -> 441 | G57: =C57*(1-$G$56) -> 416.5
B58: Snicker's | C58: 500 | D58: =C58*(1-$D$56) -> 475 | E58: =C58*(1-$E$56) -> 460 | F58: =C58*(1-$F$56) -> 450 | G58: =C58*(1-$G$56) -> 425
B59: 3 Pecados | C59: 490 | D59: =C59*(1-$D$56) -> 465.5 | E59: =C59*(1-$E$56) -> 450.8 | F59: =C59*(1-$F$56) -> 441 | G59: =C59*(1-$G$56) -> 416.5
B60: Crunch | C60: 490 | D60: =C60*(1-$D$56) -> 465.5 | E60: =C60*(1-$E$56) -> 450.8 | F60: =C60*(1-$F$56) -> 441 | G60: =C60*(1-$G$56) -> 416.5
B61: Zanahoria | C61: 440 | D61: =C61*(1-$D$56) -> 418 | E61: =C61*(1-$E$56) -> 404.8 | F61: =C61*(1-$F$56) -> 396 | G61: =C61*(1-$G$56) -> 374
B62: Pay de Queso | C62: 495 | D62: =C62*(1-$D$56) -> 470.25 | E62: =C62*(1-$E$56) -> 455.4 | F62: =C62*(1-$F$56) -> 445.5 | G62: =C62*(1-$G$56) -> 420.75
B63: Lotus | C63: 600 | D63: =C63*(1-$D$56) -> 570 | E63: =C63*(1-$E$56) -> 552 | F63: =C63*(1-$F$56) -> 540 | G63: =C63*(1-$G$56) -> 510
B64: Tortuga | C64: 600 | D64: =C64*(1-$D$56) -> 570 | E64: =C64*(1-$E$56) -> 552 | F64: =C64*(1-$F$56) -> 540 | G64: =C64*(1-$G$56) -> 510
B65: Brownie | C65: 600 | D65: =C65*(1-$D$56) -> 570 | E65: =C65*(1-$E$56) -> 552 | F65: =C65*(1-$F$56) -> 540 | G65: =C65*(1-$G$56) -> 510
B66: Zarzamora | C66: 600 | D66: =C66*(1-$D$56) -> 570 | E66: =C66*(1-$E$56) -> 552 | F66: =C66*(1-$F$56) -> 540 | G66: =C66*(1-$G$56) -> 510
B67: Limón | C67: 550 | D67: =C67*(1-$D$56) -> 522.5 | E67: =C67*(1-$E$56) -> 506 | F67: =C67*(1-$F$56) -> 495 | G67: =C67*(1-$G$56) -> 467.5
B68: Galleta Chipas de Chocolate | C68: 35 | D68: =C68*(1-$D$56) -> 33.25 | E68: =C68*(1-$E$56) -> 32.2 | F68: =C68*(1-$F$56) -> 31.5 | G68: =C68*(1-$G$56) -> 29.75
... B77: Bollo Lotus | C77: 35 | D77: =C77*(1-$D$56) -> 33.25 | E77: =C77*(1-$E$56) -> 32.2 | F77: =C77*(1-$F$56) -> 31.5 | G77: =C77*(1-$G$56) -> 29.75

Sheet Lista de Costo Produccion
I1: Precio Ajustado | J1: 0.45 | O1: Mínimo de margen | P1: 0.4 | U1: Buen margen | V1: 0.35 | AA1: Mejor margen | AB1: 0.3 | AG1: Precio Propuesto | AM1: Precio Ajustado | AN1: 0.45
C2: Individual | D2: Mini | E2: Chico | F2: Mediano | G2: Grande | H2: Rebanada | I2: Individual | J2: Mini | K2: Chico | L2: Mediano | M2: Grande | N2: Rebanada | O2: Individual | P2: Mini | Q2: Chico | R2: Mediano | S2: Grande | T2: Rebanada | U2: Individual | V2: Mini | W2: Chico | X2: Mediano | Y2: Grande | Z2: Rebanada | AA2: Individual | AB2: Mini | AC2: Chico | AD2: Mediano | AE2: Grande | AF2: Rebanada | AG2: Individual | AH2: Mini | AI2: Chico | AJ2: Mediano | AK2: Grande | AL2: Rebanada | AM2: Individual | AN2: Mini | AO2: Chico | AP2: Mediano | AQ2: Grande | AR2: Rebanada
A3: Pay | B3: Fresa | C3: =Pay!C53 -> 18.916121 | D3: 0 | E3: 0 | F3: =Pay!D53 -> 140.58423 | G3: =Pay!E53 -> 240.03393 | H3: =Pay!F53 -> 32.704881 | I3: =_xlfn.IFNA(C3/$J$1,0) -> 42.035824 | J3: =_xlfn.IFNA(D3/$J$1,0) -> 0 | K3: =_xlfn.IFNA(E3/$J$1,0) -> 0 | L3: =_xlfn.IFNA(F3/$J$1,0) -> 312.4094 | M3: =_xlfn.IFNA(G3/$J$1,0) -> 533.40873 | N3: =_xlfn.IFNA(H3/$J$1,0) -> 72.677513 | O3: =_xlfn.IFNA(C3/$P$1,0) -> 47.290302 | P3: =_xlfn.IFNA(D3/$P$1,0) -> 0 | Q3: =_xlfn.IFNA(E3/$P$1,0) -> 0 | R3: =_xlfn.IFNA(F3/$P$1,0) -> 351.46057 | S3: =_xlfn.IFNA(G3/$P$1,0) -> 600.08482 | T3: =_xlfn.IFNA(H3/$P$1,0) -> 81.762202 | U3: =_xlfn.IFNA(C3/$V$1,0) -> 54.04606 | V3: =_xlfn.IFNA(D3/$V$1,0) -> 0 | W3: =_xlfn.IFNA(E3/$V$1,0) -> 0 | X3: =_xlfn.IFNA(F3/$V$1,0) -> 401.66922 | Y3: =_xlfn.IFNA(G3/$V$1,0) -> 685.81122 | Z3: =_xlfn.IFNA(H3/$V$1,0) -> 93.442517 | AA3: =_xlfn.IFNA(C3/$AB$1,0) -> 63.053737 | AB3: =_xlfn.IFNA(D3/$AB$1,0) -> 0 | AC3: =_xlfn.IFNA(E3/$AB$1,0) -> 0 | AD3: =_xlfn.IFNA(F3/$AB$1,0) -> 468.61409 | AE3: =_xlfn.IFNA(G3/$AB$1,0) -> 800.11309 | AF3: =_xlfn.IFNA(H3/$AB$1,0) -> 109.01627 | AG3: 55 | AJ3: 395 | AK3: 495 | AL3: 70 | AM3: =_xlfn.IFNA(C3/$AN$1,0) -> 42.035824 | AN3: =_xlfn.IFNA(D3/$AN$1,0) -> 0 | AO3: =_xlfn.IFNA(E3/$AN$1,0) -> 0 | AP3: =_xlfn.IFNA(F3/$AN$1,0) -> 312.4094 | AQ3: =_xlfn.IFNA(G3/$AN$1,0) -> 533.40873 | AR3: =_xlfn.IFNA(H3/$AN$1,0) -> 72.677513
B4: Guayaba | C4: =Pay!C54 -> 19.055935 | D4: 0 | E4: 0 | F4: =Pay!D54 -> 148.26907 | G4: =Pay!E54 -> 240.58042 | H4: =Pay!F54 -> 32.773193 | I4: =_xlfn.IFNA(C4/$J$1,0) -> 42.346523 | J4: =_xlfn.IFNA(D4/$J$1,0) -> 0 | K4: =_xlfn.IFNA(E4/$J$1,0) -> 0 | L4: =_xlfn.IFNA(F4/$J$1,0) -> 329.48683 | M4: =_xlfn.IFNA(G4/$J$1,0) -> 534.62316 | N4: =_xlfn.IFNA(H4/$J$1,0) -> 72.829317 | O4: =_xlfn.IFNA(C4/$P$1,0) -> 47.639839 | P4: =_xlfn.IFNA(D4/$P$1,0) -> 0 | Q4: =_xlfn.IFNA(E4/$P$1,0) -> 0 | R4: =_xlfn.IFNA(F4/$P$1,0) -> 370.67269 | S4: =_xlfn.IFNA(G4/$P$1,0) -> 601.45105 | T4: =_xlfn.IFNA(H4/$P$1,0) -> 81.932982 | U4: =_xlfn.IFNA(C4/$V$1,0) -> 54.44553 | V4: =_xlfn.IFNA(D4/$V$1,0) -> 0 | W4: =_xlfn.IFNA(E4/$V$1,0) -> 0 | X4: =_xlfn.IFNA(F4/$V$1,0) -> 423.62593 | Y4: =_xlfn.IFNA(G4/$V$1,0) -> 687.37263 | Z4: =_xlfn.IFNA(H4/$V$1,0) -> 93.637693 | AA4: =_xlfn.IFNA(C4/$AB$1,0) -> 63.519785 | AB4: =_xlfn.IFNA(D4/$AB$1,0) -> 0 | AC4: =_xlfn.IFNA(E4/$AB$1,0) -> 0 | AD4: =_xlfn.IFNA(F4/$AB$1,0) -> 494.23025 | AE4: =_xlfn.IFNA(G4/$AB$1,0) -> 801.93474 | AF4: =_xlfn.IFNA(H4/$AB$1,0) -> 109.24398 | AG4: 55 | AJ4: 380 | AK4: 475 | AL4: 70 | AM4: =_xlfn.IFNA(C4/$AN$1,0) -> 42.346523 | AN4: =_xlfn.IFNA(D4/$AN$1,0) -> 0 | AO4: =_xlfn.IFNA(E4/$AN$1,0) -> 0 | AP4: =_xlfn.IFNA(F4/$AN$1,0) -> 329.48683 | AQ4: =_xlfn.IFNA(G4/$AN$1,0) -> 534.62316 | AR4: =_xlfn.IFNA(H4/$AN$1,0) -> 72.829317
B5: Galleta con cajeta | C5: =Pay!C55 -> 20.11006 | D5: 0 | E5: 0 | F5: =Pay!D55 -> 135.33744 | G5: =Pay!E55 -> 229.02898 | H5: =Pay!F55 -> 31.329262 | I5: =_xlfn.IFNA(C5/$J$1,0) -> 44.689022 | J5: =_xlfn.IFNA(D5/$J$1,0) -> 0 | K5: =_xlfn.IFNA(E5/$J$1,0) -> 0 | L5: =_xlfn.IFNA(F5/$J$1,0) -> 300.74987 | M5: =_xlfn.IFNA(G5/$J$1,0) -> 508.95328 | N5: =_xlfn.IFNA(H5/$J$1,0) -> 69.620583 | O5: =_xlfn.IFNA(C5/$P$1,0) -> 50.27515 | P5: =_xlfn.IFNA(D5/$P$1,0) -> 0 | Q5: =_xlfn.IFNA(E5/$P$1,0) -> 0 | R5: =_xlfn.IFNA(F5/$P$1,0) -> 338.3436 | S5: =_xlfn.IFNA(G5/$P$1,0) -> 572.57244 | T5: =_xlfn.IFNA(H5/$P$1,0) -> 78.323155 | U5: =_xlfn.IFNA(C5/$V$1,0) -> 57.457314 | V5: =_xlfn.IFNA(D5/$V$1,0) -> 0 | W5: =_xlfn.IFNA(E5/$V$1,0) -> 0 | X5: =_xlfn.IFNA(F5/$V$1,0) -> 386.6784 | Y5: =_xlfn.IFNA(G5/$V$1,0) -> 654.36851 | Z5: =_xlfn.IFNA(H5/$V$1,0) -> 89.512178 | AA5: =_xlfn.IFNA(C5/$AB$1,0) -> 67.033534 | AB5: =_xlfn.IFNA(D5/$AB$1,0) -> 0 | AC5: =_xlfn.IFNA(E5/$AB$1,0) -> 0 | AD5: =_xlfn.IFNA(F5/$AB$1,0) -> 451.1248 | AE5: =_xlfn.IFNA(G5/$AB$1,0) -> 763.42992 | AF5: =_xlfn.IFNA(H5/$AB$1,0) -> 104.43087 | AG5: 55 | AJ5: 370 | AK5: 475 | AL5: 70 | AM5: =_xlfn.IFNA(C5/$AN$1,0) -> 44.689022 | AN5: =_xlfn.IFNA(D5/$AN$1,0) -> 0 | AO5: =_xlfn.IFNA(E5/$AN$1,0) -> 0 | AP5: =_xlfn.IFNA(F5/$AN$1,0) -> 300.74987 | AQ5: =_xlfn.IFNA(G5/$AN$1,0) -> 508.95328 | AR5: =_xlfn.IFNA(H5/$AN$1,0) -> 69.620583
B6: Oreo | C6: =Pay!C57 -> 18.623235 | D6: 0 | E6: 0 | F6: =Pay!D57 -> 139.81162 | G6: =Pay!E57 -> 238.53794 | H6: =Pay!F57 -> 32.517883 | I6: =_xlfn.IFNA(C6/$J$1,0) -> 41.384968 | J6: =_xlfn.IFNA(D6/$J$1,0) -> 0 | K6: =_xlfn.IFNA(E6/$J$1,0) -> 0 | L6: =_xlfn.IFNA(F6/$J$1,0) -> 310.69249 | M6: =_xlfn.IFNA(G6/$J$1,0) -> 530.08432 | N6: =_xlfn.IFNA(H6/$J$1,0) -> 72.261962 | O6: =_xlfn.IFNA(C6/$P$1,0) -> 46.558089 | P6: =_xlfn.IFNA(D6/$P$1,0) -> 0 | Q6: =_xlfn.IFNA(E6/$P$1,0) -> 0 | R6: =_xlfn.IFNA(F6/$P$1,0) -> 349.52905 | S6: =_xlfn.IFNA(G6/$P$1,0) -> 596.34486 | T6: =_xlfn.IFNA(H6/$P$1,0) -> 81.294708 | U6: =_xlfn.IFNA(C6/$V$1,0) -> 53.209244 | V6: =_xlfn.IFNA(D6/$V$1,0) -> 0 | W6: =_xlfn.IFNA(E6/$V$1,0) -> 0 | X6: =_xlfn.IFNA(F6/$V$1,0) -> 399.46178 | Y6: =_xlfn.IFNA(G6/$V$1,0) -> 681.53698 | Z6: =_xlfn.IFNA(H6/$V$1,0) -> 92.908237 | AA6: =_xlfn.IFNA(C6/$AB$1,0) -> 62.077452 | AB6: =_xlfn.IFNA(D6/$AB$1,0) -> 0 | AC6: =_xlfn.IFNA(E6/$AB$1,0) -> 0 | AD6: =_xlfn.IFNA(F6/$AB$1,0) -> 466.03874 | AE6: =_xlfn.IFNA(G6/$AB$1,0) -> 795.12648 | AF6: =_xlfn.IFNA(H6/$AB$1,0) -> 108.39294 | AG6: 55 | AJ6: 395 | AK6: 495 | AL6: 70 | AM6: =_xlfn.IFNA(C6/$AN$1,0) -> 41.384968 | AN6: =_xlfn.IFNA(D6/$AN$1,0) -> 0 | AO6: =_xlfn.IFNA(E6/$AN$1,0) -> 0 | AP6: =_xlfn.IFNA(F6/$AN$1,0) -> 310.69249 | AQ6: =_xlfn.IFNA(G6/$AN$1,0) -> 530.08432 | AR6: =_xlfn.IFNA(H6/$AN$1,0) -> 72.261962
B7: Plátano
B8: Pay horneado | C8: =Pay!C58 -> 0 | D8: 0 | E8: 0 | F8: =Pay!D58 -> 86.851881 | G8: =Pay!E58 -> 148.87704 | H8: =Pay!F58 -> 21.310271 | I8: =_xlfn.IFNA(C8/$J$1,0) -> 0 | J8: =_xlfn.IFNA(D8/$J$1,0) -> 0 | K8: =_xlfn.IFNA(E8/$J$1,0) -> 0 | L8: =_xlfn.IFNA(F8/$J$1,0) -> 193.00418 | M8: =_xlfn.IFNA(G8/$J$1,0) -> 330.83788 | N8: =_xlfn.IFNA(H8/$J$1,0) -> 47.356157 | O8: =_xlfn.IFNA(C8/$P$1,0) -> 0 | P8: =_xlfn.IFNA(D8/$P$1,0) -> 0 | Q8: =_xlfn.IFNA(E8/$P$1,0) -> 0 | R8: =_xlfn.IFNA(F8/$P$1,0) -> 217.1297 | S8: =_xlfn.IFNA(G8/$P$1,0) -> 372.19261 | T8: =_xlfn.IFNA(H8/$P$1,0) -> 53.275676 | U8: =_xlfn.IFNA(C8/$V$1,0) -> 0 | V8: =_xlfn.IFNA(D8/$V$1,0) -> 0 | W8: =_xlfn.IFNA(E8/$V$1,0) -> 0 | X8: =_xlfn.IFNA(F8/$V$1,0) -> 248.14823 | Y8: =_xlfn.IFNA(G8/$V$1,0) -> 425.36298 | Z8: =_xlfn.IFNA(H8/$V$1,0) -> 60.886487 | AA8: =_xlfn.IFNA(C8/$AB$1,0) -> 0 | AB8: =_xlfn.IFNA(D8/$AB$1,0) -> 0 | AC8: =_xlfn.IFNA(E8/$AB$1,0) -> 0 | AD8: =_xlfn.IFNA(F8/$AB$1,0) -> 289.50627 | AE8: =_xlfn.IFNA(G8/$AB$1,0) -> 496.25681 | AF8: =_xlfn.IFNA(H8/$AB$1,0) -> 71.034235 | AG8: 45 | AL8: 60 | AM8: =_xlfn.IFNA(C8/$AN$1,0) -> 0 | AN8: =_xlfn.IFNA(D8/$AN$1,0) -> 0 | AO8: =_xlfn.IFNA(E8/$AN$1,0) -> 0 | AP8: =_xlfn.IFNA(F8/$AN$1,0) -> 193.00418 | AQ8: =_xlfn.IFNA(G8/$AN$1,0) -> 330.83788 | AR8: =_xlfn.IFNA(H8/$AN$1,0) -> 47.356157
B9: Pay de queso | C9: =Pay!C59 -> 0 | D9: 0 | E9: 0 | F9: =Pay!D59 -> 115.18762 | G9: =Pay!E59 -> 195.44594 | H9: =Pay!F59 -> 27.131383 | I9: =_xlfn.IFNA(C9/$J$1,0) -> 0 | J9: =_xlfn.IFNA(D9/$J$1,0) -> 0 | K9: =_xlfn.IFNA(E9/$J$1,0) -> 0 | L9: =_xlfn.IFNA(F9/$J$1,0) -> 255.97249 | M9: =_xlfn.IFNA(G9/$J$1,0) -> 434.32432 | N9: =_xlfn.IFNA(H9/$J$1,0) -> 60.291962 | O9: =_xlfn.IFNA(C9/$P$1,0) -> 0 | P9: =_xlfn.IFNA(D9/$P$1,0) -> 0 | Q9: =_xlfn.IFNA(E9/$P$1,0) -> 0 | R9: =_xlfn.IFNA(F9/$P$1,0) -> 287.96905 | S9: =_xlfn.IFNA(G9/$P$1,0) -> 488.61486 | T9: =_xlfn.IFNA(H9/$P$1,0) -> 67.828458 | U9: =_xlfn.IFNA(C9/$V$1,0) -> 0 | V9: =_xlfn.IFNA(D9/$V$1,0) -> 0 | W9: =_xlfn.IFNA(E9/$V$1,0) -> 0 | X9: =_xlfn.IFNA(F9/$V$1,0) -> 329.10749 | Y9: =_xlfn.IFNA(G9/$V$1,0) -> 558.41698 | Z9: =_xlfn.IFNA(H9/$V$1,0) -> 77.518237 | AA9: =_xlfn.IFNA(C9/$AB$1,0) -> 0 | AB9: =_xlfn.IFNA(D9/$AB$1,0) -> 0 | AC9: =_xlfn.IFNA(E9/$AB$1,0) -> 0 | AD9: =_xlfn.IFNA(F9/$AB$1,0) -> 383.95874 | AE9: =_xlfn.IFNA(G9/$AB$1,0) -> 651.48648 | AF9: =_xlfn.IFNA(H9/$AB$1,0) -> 90.437944 | AG9: 50 | AL9: 65 | AM9: =_xlfn.IFNA(C9/$AN$1,0) -> 0 | AN9: =_xlfn.IFNA(D9/$AN$1,0) -> 0 | AO9: =_xlfn.IFNA(E9/$AN$1,0) -> 0 | AP9: =_xlfn.IFNA(F9/$AN$1,0) -> 255.97249 | AQ9: =_xlfn.IFNA(G9/$AN$1,0) -> 434.32432 | AR9: =_xlfn.IFNA(H9/$AN$1,0) -> 60.291962
A10: Pastel | B10: Fresas con Crema | C10: ='Pastel Fresas Con Crema'!D12 -> 0 | D10: ='Pastel Fresas Con Crema'!E13 -> 70.789681 | E10: ='Pastel Fresas Con Crema'!F13 -> 139.62928 | F10: ='Pastel Fresas Con Crema'!G13 -> 197.69975 | G10: ='Pastel Fresas Con Crema'!H13 -> 323.02917 | H10: ='Pastel Fresas Con Crema'!C13 -> 22.577115 | I10: =_xlfn.IFNA(C10/$J$1,0) -> 0 | J10: =_xlfn.IFNA(D10/$J$1,0) -> 157.3104 | K10: =_xlfn.IFNA(E10/$J$1,0) -> 310.28729 | L10: =_xlfn.IFNA(F10/$J$1,0) -> 439.33279 | M10: =_xlfn.IFNA(G10/$J$1,0) -> 717.8426 | N10: =_xlfn.IFNA(H10/$J$1,0) -> 50.171367 | O10: =_xlfn.IFNA(C10/$P$1,0) -> 0 | P10: =_xlfn.IFNA(D10/$P$1,0) -> 176.9742 | Q10: =_xlfn.IFNA(E10/$P$1,0) -> 349.07321 | R10: =_xlfn.IFNA(F10/$P$1,0) -> 494.24938 | S10: =_xlfn.IFNA(G10/$P$1,0) -> 807.57292 | T10: =_xlfn.IFNA(H10/$P$1,0) -> 56.442788 | U10: =_xlfn.IFNA(C10/$V$1,0) -> 0 | V10: =_xlfn.IFNA(D10/$V$1,0) -> 202.25623 | W10: =_xlfn.IFNA(E10/$V$1,0) -> 398.94081 | X10: =_xlfn.IFNA(F10/$V$1,0) -> 564.85644 | Y10: =_xlfn.IFNA(G10/$V$1,0) -> 922.94048 | Z10: =_xlfn.IFNA(H10/$V$1,0) -> 64.506044 | AA10: =_xlfn.IFNA(C10/$AB$1,0) -> 0 | AB10: =_xlfn.IFNA(D10/$AB$1,0) -> 235.9656 | AC10: =_xlfn.IFNA(E10/$AB$1,0) -> 465.43094 | AD10: =_xlfn.IFNA(F10/$AB$1,0) -> 658.99918 | AE10: =_xlfn.IFNA(G10/$AB$1,0) -> 1076.7639 | AF10: =_xlfn.IFNA(H10/$AB$1,0) -> 75.257051 | AH10: 185 | AI10: 335 | AJ10: 490 | AK10: 700 | AL10: 70 | AM10: =_xlfn.IFNA(C10/$AN$1,0) -> 0 | AN10: =_xlfn.IFNA(D10/$AN$1,0) -> 157.3104 | AO10: =_xlfn.IFNA(E10/$AN$1,0) -> 310.28729 | AP10: =_xlfn.IFNA(F10/$AN$1,0) -> 439.33279 | AQ10: =_xlfn.IFNA(G10/$AN$1,0) -> 717.8426 | AR10: =_xlfn.IFNA(H10/$AN$1,0) -> 50.171367
B11: 3 Pecados | C11: 0 | D11: ='Pastel 3 Pecados'!E18 -> 64.125646 | E11: ='Pastel 3 Pecados'!F18 -> 163.26597 | F11: ='Pastel 3 Pecados'!G18 -> 234.88562 | G11: ='Pastel 3 Pecados'!H18 -> 350.57494 | H11: ='Pastel 3 Pecados'!C18 -> 26.295702 | I11: =_xlfn.IFNA(C11/$J$1,0) -> 0 | J11: =_xlfn.IFNA(D11/$J$1,0) -> 142.50144 | K11: =_xlfn.IFNA(E11/$J$1,0) -> 362.81327 | L11: =_xlfn.IFNA(F11/$J$1,0) -> 521.96804 | M11: =_xlfn.IFNA(G11/$J$1,0) -> 779.05543 | N11: =_xlfn.IFNA(H11/$J$1,0) -> 58.434893 | O11: =_xlfn.IFNA(C11/$P$1,0) -> 0 | P11: =_xlfn.IFNA(D11/$P$1,0) -> 160.31412 | Q11: =_xlfn.IFNA(E11/$P$1,0) -> 408.16493 | R11: =_xlfn.IFNA(F11/$P$1,0) -> 587.21405 | S11: =_xlfn.IFNA(G11/$P$1,0) -> 876.43736 | T11: =_xlfn.IFNA(H11/$P$1,0) -> 65.739255 | U11: =_xlfn.IFNA(C11/$V$1,0) -> 0 | V11: =_xlfn.IFNA(D11/$V$1,0) -> 183.21613 | W11: =_xlfn.IFNA(E11/$V$1,0) -> 466.4742 | X11: =_xlfn.IFNA(F11/$V$1,0) -> 671.10177 | Y11: =_xlfn.IFNA(G11/$V$1,0) -> 1001.6427 | Z11: =_xlfn.IFNA(H11/$V$1,0) -> 75.130577 | AA11: =_xlfn.IFNA(C11/$AB$1,0) -> 0 | AB11: =_xlfn.IFNA(D11/$AB$1,0) -> 213.75215 | AC11: =_xlfn.IFNA(E11/$AB$1,0) -> 544.2199 | AD11: =_xlfn.IFNA(F11/$AB$1,0) -> 782.95207 | AE11: =_xlfn.IFNA(G11/$AB$1,0) -> 1168.5831 | AF11: =_xlfn.IFNA(H11/$AB$1,0) -> 87.65234 | AH11: 185 | AI11: 340 | AJ11: 490 | AK11: 700 | AL11: 70 | AM11: =_xlfn.IFNA(C11/$AN$1,0) -> 0 | AN11: =_xlfn.IFNA(D11/$AN$1,0) -> 142.50144 | AO11: =_xlfn.IFNA(E11/$AN$1,0) -> 362.81327 | AP11: =_xlfn.IFNA(F11/$AN$1,0) -> 521.96804 | AQ11: =_xlfn.IFNA(G11/$AN$1,0) -> 779.05543 | AR11: =_xlfn.IFNA(H11/$AN$1,0) -> 58.434893
B12: Zanahoria | C12: 0 | D12: 0 | E12: ='Pastel Zanahoria'!F12 -> 151.95679 | F12: ='Pastel Zanahoria'!G12 -> 207.49008 | G12: ='Pastel Zanahoria'!H12 -> 317.43002 | H12: ='Pastel Zanahoria'!C12 -> 23.556148 | I12: =_xlfn.IFNA(C12/$J$1,0) -> 0 | J12: =_xlfn.IFNA(D12/$J$1,0) -> 0 | K12: =_xlfn.IFNA(E12/$J$1,0) -> 337.68175 | L12: =_xlfn.IFNA(F12/$J$1,0) -> 461.08908 | M12: =_xlfn.IFNA(G12/$J$1,0) -> 705.40005 | N12: =_xlfn.IFNA(H12/$J$1,0) -> 52.346997 | O12: =_xlfn.IFNA(C12/$P$1,0) -> 0 | P12: =_xlfn.IFNA(D12/$P$1,0) -> 0 | Q12: =_xlfn.IFNA(E12/$P$1,0) -> 379.89196 | R12: =_xlfn.IFNA(F12/$P$1,0) -> 518.72521 | S12: =_xlfn.IFNA(G12/$P$1,0) -> 793.57506 | T12: =_xlfn.IFNA(H12/$P$1,0) -> 58.890371 | U12: =_xlfn.IFNA(C12/$V$1,0) -> 0 | V12: =_xlfn.IFNA(D12/$V$1,0) -> 0 | W12: =_xlfn.IFNA(E12/$V$1,0) -> 434.16225 | X12: =_xlfn.IFNA(F12/$V$1,0) -> 592.82881 | Y12: =_xlfn.IFNA(G12/$V$1,0) -> 906.94293 | Z12: =_xlfn.IFNA(H12/$V$1,0) -> 67.303281 | AA12: =_xlfn.IFNA(C12/$AB$1,0) -> 0 | AB12: =_xlfn.IFNA(D12/$AB$1,0) -> 0 | AC12: =_xlfn.IFNA(E12/$AB$1,0) -> 506.52262 | AD12: =_xlfn.IFNA(F12/$AB$1,0) -> 691.63362 | AE12: =_xlfn.IFNA(G12/$AB$1,0) -> 1058.1001 | AF12: =_xlfn.IFNA(H12/$AB$1,0) -> 78.520495 | AI12: 330 | AJ12: 440 | AK12: 700 | AL12: 70 | AM12: =_xlfn.IFNA(C12/$AN$1,0) -> 0 | AN12: =_xlfn.IFNA(D12/$AN$1,0) -> 0 | AO12: =_xlfn.IFNA(E12/$AN$1,0) -> 337.68175 | AP12: =_xlfn.IFNA(F12/$AN$1,0) -> 461.08908 | AQ12: =_xlfn.IFNA(G12/$AN$1,0) -> 705.40005 | AR12: =_xlfn.IFNA(H12/$AN$1,0) -> 52.346997
B13: Chocolate | C13: 0 | D13: ='Pastel Chocolate'!E12 -> 59.756374 | E13: 0 | F13: 0 | G13: 0 | H13: 0 | I13: =_xlfn.IFNA(C13/$J$1,0) -> 0 | J13: =_xlfn.IFNA(D13/$J$1,0) -> 132.79194 | K13: =_xlfn.IFNA(E13/$J$1,0) -> 0 | L13: =_xlfn.IFNA(F13/$J$1,0) -> 0 | M13: =_xlfn.IFNA(G13/$J$1,0) -> 0 | N13: =_xlfn.IFNA(H13/$J$1,0) -> 0 | O13: =_xlfn.IFNA(C13/$P$1,0) -> 0 | P13: =_xlfn.IFNA(D13/$P$1,0) -> 149.39094 | Q13: =_xlfn.IFNA(E13/$P$1,0) -> 0 | R13: =_xlfn.IFNA(F13/$P$1,0) -> 0 | S13: =_xlfn.IFNA(G13/$P$1,0) -> 0 | T13: =_xlfn.IFNA(H13/$P$1,0) -> 0 | U13: =_xlfn.IFNA(C13/$V$1,0) -> 0 | V13: =_xlfn.IFNA(D13/$V$1,0) -> 170.7325 | W13: =_xlfn.IFNA(E13/$V$1,0) -> 0 | X13: =_xlfn.IFNA(F13/$V$1,0) -> 0 | Y13: =_xlfn.IFNA(G13/$V$1,0) -> 0 | Z13: =_xlfn.IFNA(H13/$V$1,0) -> 0 | AA13: =_xlfn.IFNA(C13/$AB$1,0) -> 0 | AB13: =_xlfn.IFNA(D13/$AB$1,0) -> 199.18791 | AC13: =_xlfn.IFNA(E13/$AB$1,0) -> 0 | AD13: =_xlfn.IFNA(F13/$AB$1,0) -> 0 | AE13: =_xlfn.IFNA(G13/$AB$1,0) -> 0 | AF13: =_xlfn.IFNA(H13/$AB$1,0) -> 0 | AL13: 70 | AM13: =_xlfn.IFNA(C13/$AN$1,0) -> 0 | AN13: =_xlfn.IFNA(D13/$AN$1,0) -> 132.79194 | AO13: =_xlfn.IFNA(E13/$AN$1,0) -> 0 | AP13: =_xlfn.IFNA(F13/$AN$1,0) -> 0 | AQ13: =_xlfn.IFNA(G13/$AN$1,0) -> 0 | AR13: =_xlfn.IFNA(H13/$AN$1,0) -> 0
B14: Crunch | C14: 0 | D14: ='Pastel Crunch'!E14 -> 80.227256 | E14: ='Pastel Crunch'!F14 -> 166.4893 | F14: ='Pastel Crunch'!G14 -> 242.04424 | G14: ='Pastel Crunch'!H14 -> 338.62657 | H14: ='Pastel Crunch'!C14 -> 27.011564 | I14: =_xlfn.IFNA(C14/$J$1,0) -> 0 | J14: =_xlfn.IFNA(D14/$J$1,0) -> 178.28279 | K14: =_xlfn.IFNA(E14/$J$1,0) -> 369.97623 | L14: =_xlfn.IFNA(F14/$J$1,0) -> 537.87609 | M14: =_xlfn.IFNA(G14/$J$1,0) -> 752.50349 | N14: =_xlfn.IFNA(H14/$J$1,0) -> 60.025697 | O14: =_xlfn.IFNA(C14/$P$1,0) -> 0 | P14: =_xlfn.IFNA(D14/$P$1,0) -> 200.56814 | Q14: =_xlfn.IFNA(E14/$P$1,0) -> 416.22325 | R14: =_xlfn.IFNA(F14/$P$1,0) -> 605.1106 | S14: =_xlfn.IFNA(G14/$P$1,0) -> 846.56643 | T14: =_xlfn.IFNA(H14/$P$1,0) -> 67.52891 | U14: =_xlfn.IFNA(C14/$V$1,0) -> 0 | V14: =_xlfn.IFNA(D14/$V$1,0) -> 229.22073 | W14: =_xlfn.IFNA(E14/$V$1,0) -> 475.68372 | X14: =_xlfn.IFNA(F14/$V$1,0) -> 691.55497 | Y14: =_xlfn.IFNA(G14/$V$1,0) -> 967.50449 | Z14: =_xlfn.IFNA(H14/$V$1,0) -> 77.175897 | AA14: =_xlfn.IFNA(C14/$AB$1,0) -> 0 | AB14: =_xlfn.IFNA(D14/$AB$1,0) -> 267.42419 | AC14: =_xlfn.IFNA(E14/$AB$1,0) -> 554.96434 | AD14: =_xlfn.IFNA(F14/$AB$1,0) -> 806.81413 | AE14: =_xlfn.IFNA(G14/$AB$1,0) -> 1128.7552 | AF14: =_xlfn.IFNA(H14/$AB$1,0) -> 90.038546 | AH14: 185 | AI14: 360 | AJ14: 490 | AK14: 720 | AL14: 70 | AM14: =_xlfn.IFNA(C14/$AN$1,0) -> 0 | AN14: =_xlfn.IFNA(D14/$AN$1,0) -> 178.28279 | AO14: =_xlfn.IFNA(E14/$AN$1,0) -> 369.97623 | AP14: =_xlfn.IFNA(F14/$AN$1,0) -> 537.87609 | AQ14: =_xlfn.IFNA(G14/$AN$1,0) -> 752.50349 | AR14: =_xlfn.IFNA(H14/$AN$1,0) -> 60.025697
B15: Snicker's | C15: 0 | D15: ='Pastel Snicker''s'!E14 -> 33.131041 | E15: ='Pastel Snicker''s'!F14 -> 201.96184 | F15: ='Pastel Snicker''s'!G14 -> 281.62809 | G15: ='Pastel Snicker''s'!H14 -> 392.15336 | H15: ='Pastel Snicker''s'!C14 -> 30.969949 | I15: =_xlfn.IFNA(C15/$J$1,0) -> 0 | J15: =_xlfn.IFNA(D15/$J$1,0) -> 73.624534 | K15: =_xlfn.IFNA(E15/$J$1,0) -> 448.8041 | L15: =_xlfn.IFNA(F15/$J$1,0) -> 625.84019 | M15: =_xlfn.IFNA(G15/$J$1,0) -> 871.45192 | N15: =_xlfn.IFNA(H15/$J$1,0) -> 68.822108 | O15: =_xlfn.IFNA(C15/$P$1,0) -> 0 | P15: =_xlfn.IFNA(D15/$P$1,0) -> 82.827601 | Q15: =_xlfn.IFNA(E15/$P$1,0) -> 504.90461 | R15: =_xlfn.IFNA(F15/$P$1,0) -> 704.07022 | S15: =_xlfn.IFNA(G15/$P$1,0) -> 980.38341 | T15: =_xlfn.IFNA(H15/$P$1,0) -> 77.424872 | U15: =_xlfn.IFNA(C15/$V$1,0) -> 0 | V15: =_xlfn.IFNA(D15/$V$1,0) -> 94.660116 | W15: =_xlfn.IFNA(E15/$V$1,0) -> 577.03384 | X15: =_xlfn.IFNA(F15/$V$1,0) -> 804.65168 | Y15: =_xlfn.IFNA(G15/$V$1,0) -> 1120.4382 | Z15: =_xlfn.IFNA(H15/$V$1,0) -> 88.485568 | AA15: =_xlfn.IFNA(C15/$AB$1,0) -> 0 | AB15: =_xlfn.IFNA(D15/$AB$1,0) -> 110.4368 | AC15: =_xlfn.IFNA(E15/$AB$1,0) -> 673.20614 | AD15: =_xlfn.IFNA(F15/$AB$1,0) -> 938.76029 | AE15: =_xlfn.IFNA(G15/$AB$1,0) -> 1307.1779 | AF15: =_xlfn.IFNA(H15/$AB$1,0) -> 103.23316 | AI15: 400 | AJ15: 500 | AK15: 750 | AL15: 70 | AM15: =_xlfn.IFNA(C15/$AN$1,0) -> 0 | AN15: =_xlfn.IFNA(D15/$AN$1,0) -> 73.624534 | AO15: =_xlfn.IFNA(E15/$AN$1,0) -> 448.8041 | AP15: =_xlfn.IFNA(F15/$AN$1,0) -> 625.84019 | AQ15: =_xlfn.IFNA(G15/$AN$1,0) -> 871.45192 | AR15: =_xlfn.IFNA(H15/$AN$1,0) -> 68.822108
B16: Dulce de Leche | C16: 0 | D16: ='Pastel Vainilla'!E12 -> 0 | E16: ='Pastel Vainilla'!F12 -> 146.8559 | F16: ='Pastel Vainilla'!G12 -> 205.71168 | G16: ='Pastel Vainilla'!H12 -> 330.05251 | H16: ='Pastel Vainilla'!C12 -> 17.49273 | I16: =_xlfn.IFNA(C16/$J$1,0) -> 0 | J16: =_xlfn.IFNA(D16/$J$1,0) -> 0 | K16: =_xlfn.IFNA(E16/$J$1,0) -> 326.34644 | L16: =_xlfn.IFNA(F16/$J$1,0) -> 457.13706 | M16: =_xlfn.IFNA(G16/$J$1,0) -> 733.45002 | N16: =_xlfn.IFNA(H16/$J$1,0) -> 38.872733 | O16: =_xlfn.IFNA(C16/$P$1,0) -> 0 | P16: =_xlfn.IFNA(D16/$P$1,0) -> 0 | Q16: =_xlfn.IFNA(E16/$P$1,0) -> 367.13975 | R16: =_xlfn.IFNA(F16/$P$1,0) -> 514.27919 | S16: =_xlfn.IFNA(G16/$P$1,0) -> 825.13128 | T16: =_xlfn.IFNA(H16/$P$1,0) -> 43.731825 | U16: =_xlfn.IFNA(C16/$V$1,0) -> 0 | V16: =_xlfn.IFNA(D16/$V$1,0) -> 0 | W16: =_xlfn.IFNA(E16/$V$1,0) -> 419.58828 | X16: =_xlfn.IFNA(F16/$V$1,0) -> 587.74764 | Y16: =_xlfn.IFNA(G16/$V$1,0) -> 943.00717 | Z16: =_xlfn.IFNA(H16/$V$1,0) -> 49.979228 | AA16: =_xlfn.IFNA(C16/$AB$1,0) -> 0 | AB16: =_xlfn.IFNA(D16/$AB$1,0) -> 0 | AC16: =_xlfn.IFNA(E16/$AB$1,0) -> 489.51966 | AD16: =_xlfn.IFNA(F16/$AB$1,0) -> 685.70559 | AE16: =_xlfn.IFNA(G16/$AB$1,0) -> 1100.175 | AF16: =_xlfn.IFNA(H16/$AB$1,0) -> 58.3091 | AI16: 340 | AJ16: 450 | AK16: 710 | AL16: 70 | AM16: =_xlfn.IFNA(C16/$AN$1,0) -> 0 | AN16: =_xlfn.IFNA(D16/$AN$1,0) -> 0 | AO16: =_xlfn.IFNA(E16/$AN$1,0) -> 326.34644 | AP16: =_xlfn.IFNA(F16/$AN$1,0) -> 457.13706 | AQ16: =_xlfn.IFNA(G16/$AN$1,0) -> 733.45002 | AR16: =_xlfn.IFNA(H16/$AN$1,0) -> 38.872733
B17: 3 Leches | C17: ='Pastel 3 Leches'!F13 -> 31.019912 | D17: 0 | E17: 0 | F17: ='Pastel 3 Leches'!D13 -> 176.71615 | G17: ='Pastel 3 Leches'!E13 -> 401.53172 | H17: ='Pastel 3 Leches'!C13 -> 32.259831 | I17: =_xlfn.IFNA(C17/$J$1,0) -> 68.933139 | J17: =_xlfn.IFNA(D17/$J$1,0) -> 0 | K17: =_xlfn.IFNA(E17/$J$1,0) -> 0 | L17: =_xlfn.IFNA(F17/$J$1,0) -> 392.70255 | M17: =_xlfn.IFNA(G17/$J$1,0) -> 892.29271 | N17: =_xlfn.IFNA(H17/$J$1,0) -> 71.688514 | O17: =_xlfn.IFNA(C17/$P$1,0) -> 77.549781 | P17: =_xlfn.IFNA(D17/$P$1,0) -> 0 | Q17: =_xlfn.IFNA(E17/$P$1,0) -> 0 | R17: =_xlfn.IFNA(F17/$P$1,0) -> 441.79037 | S17: =_xlfn.IFNA(G17/$P$1,0) -> 1003.8293 | T17: =_xlfn.IFNA(H17/$P$1,0) -> 80.649579 | U17: =_xlfn.IFNA(C17/$V$1,0) -> 88.628321 | V17: =_xlfn.IFNA(D17/$V$1,0) -> 0 | W17: =_xlfn.IFNA(E17/$V$1,0) -> 0 | X17: =_xlfn.IFNA(F17/$V$1,0) -> 504.90328 | Y17: =_xlfn.IFNA(G17/$V$1,0) -> 1147.2335 | Z17: =_xlfn.IFNA(H17/$V$1,0) -> 92.170947 | AA17: =_xlfn.IFNA(C17/$AB$1,0) -> 103.39971 | AB17: =_xlfn.IFNA(D17/$AB$1,0) -> 0 | AC17: =_xlfn.IFNA(E17/$AB$1,0) -> 0 | AD17: =_xlfn.IFNA(F17/$AB$1,0) -> 589.05383 | AE17: =_xlfn.IFNA(G17/$AB$1,0) -> 1338.4391 | AF17: =_xlfn.IFNA(H17/$AB$1,0) -> 107.53277 | AI17: =-AI17 -> 0 | AJ17: 435 | AK17: =-AK17 -> 0 | AL17: 75 | AM17: =_xlfn.IFNA(C17/$AN$1,0) -> 68.933139 | AN17: =_xlfn.IFNA(D17/$AN$1,0) -> 0 | AO17: =_xlfn.IFNA(E17/$AN$1,0) -> 0 | AP17: =_xlfn.IFNA(F17/$AN$1,0) -> 392.70255 | AQ17: =_xlfn.IFNA(G17/$AN$1,0) -> 892.29271 | AR17: =_xlfn.IFNA(H17/$AN$1,0) -> 71.688514
B18: 3 Leches Lotus | C18: ='Pastel 3 Leches Lotus'!F14 -> 41.38822 | F18: ='Pastel 3 Leches Lotus'!D14 -> 188.12781 | G18: ='Pastel 3 Leches Lotus'!E14 -> 504.65497 | H18: ='Pastel 3 Leches Lotus'!C14 -> 34.161774 | I18: =_xlfn.IFNA(C18/$J$1,0) -> 91.973822 | J18: =_xlfn.IFNA(D18/$J$1,0) -> 0 | K18: =_xlfn.IFNA(E18/$J$1,0) -> 0 | L18: =_xlfn.IFNA(F18/$J$1,0) -> 418.06179 | M18: =_xlfn.IFNA(G18/$J$1,0) -> 1121.4555 | N18: =_xlfn.IFNA(H18/$J$1,0) -> 75.915054 | O18: =_xlfn.IFNA(C18/$P$1,0) -> 103.47055 | P18: =_xlfn.IFNA(D18/$P$1,0) -> 0 | Q18: =_xlfn.IFNA(E18/$P$1,0) -> 0 | R18: =_xlfn.IFNA(F18/$P$1,0) -> 470.31951 | S18: =_xlfn.IFNA(G18/$P$1,0) -> 1261.6374 | T18: =_xlfn.IFNA(H18/$P$1,0) -> 85.404436 | U18: =_xlfn.IFNA(C18/$V$1,0) -> 118.25206 | V18: =_xlfn.IFNA(D18/$V$1,0) -> 0 | W18: =_xlfn.IFNA(E18/$V$1,0) -> 0 | X18: =_xlfn.IFNA(F18/$V$1,0) -> 537.50802 | Y18: =_xlfn.IFNA(G18/$V$1,0) -> 1441.8713 | Z18: =_xlfn.IFNA(H18/$V$1,0) -> 97.605069 | AA18: =_xlfn.IFNA(C18/$AB$1,0) -> 137.96073 | AB18: =_xlfn.IFNA(D18/$AB$1,0) -> 0 | AC18: =_xlfn.IFNA(E18/$AB$1,0) -> 0 | AD18: =_xlfn.IFNA(F18/$AB$1,0) -> 627.09269 | AE18: =_xlfn.IFNA(G18/$AB$1,0) -> 1682.1832 | AF18: =_xlfn.IFNA(H18/$AB$1,0) -> 113.87258 | AI18: =-AI18 -> 0 | AJ18: 480 | AK18: =-AK18 -> 0 | AL18: 80 | AM18: =_xlfn.IFNA(C18/$AN$1,0) -> 91.973822 | AN18: =_xlfn.IFNA(D18/$AN$1,0) -> 0 | AO18: =_xlfn.IFNA(E18/$AN$1,0) -> 0 | AP18: =_xlfn.IFNA(F18/$AN$1,0) -> 418.06179 | AQ18: =_xlfn.IFNA(G18/$AN$1,0) -> 1121.4555 | AR18: =_xlfn.IFNA(H18/$AN$1,0) -> 75.915054
B19: Flan | C19: ='Resumen Costos'!C19 -> 22.94585 | D19: ='Resumen Costos'!D19 -> 0 | E19: ='Resumen Costos'!E19 -> 0 | F19: ='Resumen Costos'!F19 -> 241.70639 | G19: ='Resumen Costos'!G19 -> 0 | H19: ='Resumen Costos'!H19 -> 0 | I19: =_xlfn.IFNA(C19/$J$1,0) -> 50.990777 | J19: =_xlfn.IFNA(D19/$J$1,0) -> 0 | K19: =_xlfn.IFNA(E19/$J$1,0) -> 0 | L19: =_xlfn.IFNA(F19/$J$1,0) -> 537.1253 | M19: =_xlfn.IFNA(G19/$J$1,0) -> 0 | N19: =_xlfn.IFNA(H19/$J$1,0) -> 0 | O19: =_xlfn.IFNA(C19/$P$1,0) -> 57.364624 | P19: =_xlfn.IFNA(D19/$P$1,0) -> 0 | Q19: =_xlfn.IFNA(E19/$P$1,0) -> 0 | R19: =_xlfn.IFNA(F19/$P$1,0) -> 604.26596 | S19: =_xlfn.IFNA(G19/$P$1,0) -> 0 | T19: =_xlfn.IFNA(H19/$P$1,0) -> 0 | U19: =_xlfn.IFNA(C19/$V$1,0) -> 65.55957 | V19: =_xlfn.IFNA(D19/$V$1,0) -> 0 | W19: =_xlfn.IFNA(E19/$V$1,0) -> 0 | X19: =_xlfn.IFNA(F19/$V$1,0) -> 690.58967 | Y19: =_xlfn.IFNA(G19/$V$1,0) -> 0 | Z19: =_xlfn.IFNA(H19/$V$1,0) -> 0 | AA19: =_xlfn.IFNA(C19/$AB$1,0) -> 76.486165 | AB19: =_xlfn.IFNA(D19/$AB$1,0) -> 0 | AC19: =_xlfn.IFNA(E19/$AB$1,0) -> 0 | AD19: =_xlfn.IFNA(F19/$AB$1,0) -> 805.68795 | AE19: =_xlfn.IFNA(G19/$AB$1,0) -> 0 | AF19: =_xlfn.IFNA(H19/$AB$1,0) -> 0 | AG19: 55 | AM19: =_xlfn.IFNA(C19/$AN$1,0) -> 50.990777 | AN19: =_xlfn.IFNA(D19/$AN$1,0) -> 0 | AO19: =_xlfn.IFNA(E19/$AN$1,0) -> 0 | AP19: =_xlfn.IFNA(F19/$AN$1,0) -> 537.1253 | AQ19: =_xlfn.IFNA(G19/$AN$1,0) -> 0 | AR19: =_xlfn.IFNA(H19/$AN$1,0) -> 0
A20: Vasos | B20: Fresas con crema | D20: =Vasos!D24 -> 17.018195 | E20: =Vasos!C24 -> 32.405495 | F20: =Vasos!E24 -> 39.465763 | G20: =Vasos!F24 -> 43.147207 | I20: =_xlfn.IFNA(C20/$J$1,0) -> 0 | J20: =_xlfn.IFNA(D20/$J$1,0) -> 37.818211 | K20: =_xlfn.IFNA(E20/$J$1,0) -> 72.012211 | L20: =_xlfn.IFNA(F20/$J$1,0) -> 87.701696 | M20: =_xlfn.IFNA(G20/$J$1,0) -> 95.882681 | N20: =_xlfn.IFNA(H20/$J$1,0) -> 0 | O20: =_xlfn.IFNA(C20/$P$1,0) -> 0 | P20: =_xlfn.IFNA(D20/$P$1,0) -> 42.545487 | Q20: =_xlfn.IFNA(E20/$P$1,0) -> 81.013738 | R20: =_xlfn.IFNA(F20/$P$1,0) -> 98.664408 | S20: =_xlfn.IFNA(G20/$P$1,0) -> 107.86802 | T20: =_xlfn.IFNA(H20/$P$1,0) -> 0 | U20: =_xlfn.IFNA(C20/$V$1,0) -> 0 | V20: =_xlfn.IFNA(D20/$V$1,0) -> 48.623414 | W20: =_xlfn.IFNA(E20/$V$1,0) -> 92.587129 | X20: =_xlfn.IFNA(F20/$V$1,0) -> 112.75932 | Y20: =_xlfn.IFNA(G20/$V$1,0) -> 123.27773 | Z20: =_xlfn.IFNA(H20/$V$1,0) -> 0 | AA20: =_xlfn.IFNA(C20/$AB$1,0) -> 0 | AB20: =_xlfn.IFNA(D20/$AB$1,0) -> 56.727316 | AC20: =_xlfn.IFNA(E20/$AB$1,0) -> 108.01832 | AD20: =_xlfn.IFNA(F20/$AB$1,0) -> 131.55254 | AE20: =_xlfn.IFNA(G20/$AB$1,0) -> 143.82402 | AF20: =_xlfn.IFNA(H20/$AB$1,0) -> 0 | AH20: 60 | AI20: 90 | AJ20: 105 | AK20: 115 | AM20: =_xlfn.IFNA(C20/$AN$1,0) -> 0 | AN20: =_xlfn.IFNA(D20/$AN$1,0) -> 37.818211 | AO20: =_xlfn.IFNA(E20/$AN$1,0) -> 72.012211 | AP20: =_xlfn.IFNA(F20/$AN$1,0) -> 87.701696 | AQ20: =_xlfn.IFNA(G20/$AN$1,0) -> 95.882681 | AR20: =_xlfn.IFNA(H20/$AN$1,0) -> 0
B21: Fresas con pay | D21: =Vasos!D25 -> 29.233566 | G21: =Vasos!C25 -> 44.620867 | I21: =_xlfn.IFNA(C21/$J$1,0) -> 0 | J21: =_xlfn.IFNA(D21/$J$1,0) -> 64.963481 | K21: =_xlfn.IFNA(E21/$J$1,0) -> 0 | L21: =_xlfn.IFNA(F21/$J$1,0) -> 0 | M21: =_xlfn.IFNA(G21/$J$1,0) -> 99.157481 | N21: =_xlfn.IFNA(H21/$J$1,0) -> 0 | O21: =_xlfn.IFNA(C21/$P$1,0) -> 0 | P21: =_xlfn.IFNA(D21/$P$1,0) -> 73.083916 | Q21: =_xlfn.IFNA(E21/$P$1,0) -> 0 | R21: =_xlfn.IFNA(F21/$P$1,0) -> 0 | S21: =_xlfn.IFNA(G21/$P$1,0) -> 111.55217 | T21: =_xlfn.IFNA(H21/$P$1,0) -> 0 | U21: =_xlfn.IFNA(C21/$V$1,0) -> 0 | V21: =_xlfn.IFNA(D21/$V$1,0) -> 83.524475 | W21: =_xlfn.IFNA(E21/$V$1,0) -> 0 | X21: =_xlfn.IFNA(F21/$V$1,0) -> 0 | Y21: =_xlfn.IFNA(G21/$V$1,0) -> 127.48819 | Z21: =_xlfn.IFNA(H21/$V$1,0) -> 0 | AA21: =_xlfn.IFNA(C21/$AB$1,0) -> 0 | AB21: =_xlfn.IFNA(D21/$AB$1,0) -> 97.445221 | AC21: =_xlfn.IFNA(E21/$AB$1,0) -> 0 | AD21: =_xlfn.IFNA(F21/$AB$1,0) -> 0 | AE21: =_xlfn.IFNA(G21/$AB$1,0) -> 148.73622 | AF21: =_xlfn.IFNA(H21/$AB$1,0) -> 0 | AM21: =_xlfn.IFNA(C21/$AN$1,0) -> 0 | AN21: =_xlfn.IFNA(D21/$AN$1,0) -> 64.963481 | AO21: =_xlfn.IFNA(E21/$AN$1,0) -> 0 | AP21: =_xlfn.IFNA(F21/$AN$1,0) -> 0 | AQ21: =_xlfn.IFNA(G21/$AN$1,0) -> 99.157481 | AR21: =_xlfn.IFNA(H21/$AN$1,0) -> 0
B22: Crema | D22: =Vasos!D26 -> 9.8099053 | G22: =Vasos!C26 -> 17.08788 | I22: =_xlfn.IFNA(C22/$J$1,0) -> 0 | J22: =_xlfn.IFNA(D22/$J$1,0) -> 21.79979 | K22: =_xlfn.IFNA(E22/$J$1,0) -> 0 | L22: =_xlfn.IFNA(F22/$J$1,0) -> 0 | M22: =_xlfn.IFNA(G22/$J$1,0) -> 37.973066 | N22: =_xlfn.IFNA(H22/$J$1,0) -> 0 | O22: =_xlfn.IFNA(C22/$P$1,0) -> 0 | P22: =_xlfn.IFNA(D22/$P$1,0) -> 24.524763 | Q22: =_xlfn.IFNA(E22/$P$1,0) -> 0 | R22: =_xlfn.IFNA(F22/$P$1,0) -> 0 | S22: =_xlfn.IFNA(G22/$P$1,0) -> 42.7197 | T22: =_xlfn.IFNA(H22/$P$1,0) -> 0 | U22: =_xlfn.IFNA(C22/$V$1,0) -> 0 | V22: =_xlfn.IFNA(D22/$V$1,0) -> 28.028301 | W22: =_xlfn.IFNA(E22/$V$1,0) -> 0 | X22: =_xlfn.IFNA(F22/$V$1,0) -> 0 | Y22: =_xlfn.IFNA(G22/$V$1,0) -> 48.822514 | Z22: =_xlfn.IFNA(H22/$V$1,0) -> 0 | AA22: =_xlfn.IFNA(C22/$AB$1,0) -> 0 | AB22: =_xlfn.IFNA(D22/$AB$1,0) -> 32.699684 | AC22: =_xlfn.IFNA(E22/$AB$1,0) -> 0 | AD22: =_xlfn.IFNA(F22/$AB$1,0) -> 0 | AE22: =_xlfn.IFNA(G22/$AB$1,0) -> 56.9596 | AF22: =_xlfn.IFNA(H22/$AB$1,0) -> 0 | AM22: =_xlfn.IFNA(C22/$AN$1,0) -> 0 | AN22: =_xlfn.IFNA(D22/$AN$1,0) -> 21.79979 | AO22: =_xlfn.IFNA(E22/$AN$1,0) -> 0 | AP22: =_xlfn.IFNA(F22/$AN$1,0) -> 0 | AQ22: =_xlfn.IFNA(G22/$AN$1,0) -> 37.973066 | AR22: =_xlfn.IFNA(H22/$AN$1,0) -> 0
A23: Bollos | B23: Chocolate | C23: =Bollos!D14 -> 14.435269 | D23: ='Pastel Fresas Con Crema'!E24 -> 0 | E23: ='Pastel Fresas Con Crema'!F24 -> 0 | F23: ='Pastel Fresas Con Crema'!G24 -> 0 | G23: ='Pastel Fresas Con Crema'!H24 -> 0 | H23: ='Pastel Fresas Con Crema'!C24 -> 0 | I23: =_xlfn.IFNA(C23/$J$1,0) -> 32.078376 | J23: =_xlfn.IFNA(D23/$J$1,0) -> 0 | K23: =_xlfn.IFNA(E23/$J$1,0) -> 0 | L23: =_xlfn.IFNA(F23/$J$1,0) -> 0 | M23: =_xlfn.IFNA(G23/$J$1,0) -> 0 | N23: =_xlfn.IFNA(H23/$J$1,0) -> 0 | O23: =_xlfn.IFNA(C23/$P$1,0) -> 36.088173 | P23: =_xlfn.IFNA(D23/$P$1,0) -> 0 | Q23: =_xlfn.IFNA(E23/$P$1,0) -> 0 | R23: =_xlfn.IFNA(F23/$P$1,0) -> 0 | S23: =_xlfn.IFNA(G23/$P$1,0) -> 0 | T23: =_xlfn.IFNA(H23/$P$1,0) -> 0 | U23: =_xlfn.IFNA(C23/$V$1,0) -> 41.243626 | V23: =_xlfn.IFNA(D23/$V$1,0) -> 0 | W23: =_xlfn.IFNA(E23/$V$1,0) -> 0 | X23: =_xlfn.IFNA(F23/$V$1,0) -> 0 | Y23: =_xlfn.IFNA(G23/$V$1,0) -> 0 | Z23: =_xlfn.IFNA(H23/$V$1,0) -> 0 | AA23: =_xlfn.IFNA(C23/$AB$1,0) -> 48.117564 | AB23: =_xlfn.IFNA(D23/$AB$1,0) -> 0 | AC23: =_xlfn.IFNA(E23/$AB$1,0) -> 0 | AD23: =_xlfn.IFNA(F23/$AB$1,0) -> 0 | AE23: =_xlfn.IFNA(G23/$AB$1,0) -> 0 | AF23: =_xlfn.IFNA(H23/$AB$1,0) -> 0 | AG23: 36 | AM23: =_xlfn.IFNA(C23/$AN$1,0) -> 32.078376 | AN23: =_xlfn.IFNA(D23/$AN$1,0) -> 0 | AO23: =_xlfn.IFNA(E23/$AN$1,0) -> 0 | AP23: =_xlfn.IFNA(F23/$AN$1,0) -> 0 | AQ23: =_xlfn.IFNA(G23/$AN$1,0) -> 0 | AR23: =_xlfn.IFNA(H23/$AN$1,0) -> 0
B24: Vainilla | C24: =Bollos!C14 -> 12.485675 | I24: =_xlfn.IFNA(C24/$J$1,0) -> 27.745944 | J24: =_xlfn.IFNA(D24/$J$1,0) -> 0 | K24: =_xlfn.IFNA(E24/$J$1,0) -> 0 | L24: =_xlfn.IFNA(F24/$J$1,0) -> 0 | M24: =_xlfn.IFNA(G24/$J$1,0) -> 0 | N24: =_xlfn.IFNA(H24/$J$1,0) -> 0 | O24: =_xlfn.IFNA(C24/$P$1,0) -> 31.214187 | P24: =_xlfn.IFNA(D24/$P$1,0) -> 0 | Q24: =_xlfn.IFNA(E24/$P$1,0) -> 0 | R24: =_xlfn.IFNA(F24/$P$1,0) -> 0 | S24: =_xlfn.IFNA(G24/$P$1,0) -> 0 | T24: =_xlfn.IFNA(H24/$P$1,0) -> 0 | U24: =_xlfn.IFNA(C24/$V$1,0) -> 35.673357 | V24: =_xlfn.IFNA(D24/$V$1,0) -> 0 | W24: =_xlfn.IFNA(E24/$V$1,0) -> 0 | X24: =_xlfn.IFNA(F24/$V$1,0) -> 0 | Y24: =_xlfn.IFNA(G24/$V$1,0) -> 0 | Z24: =_xlfn.IFNA(H24/$V$1,0) -> 0 | AA24: =_xlfn.IFNA(C24/$AB$1,0) -> 41.618916 | AB24: =_xlfn.IFNA(D24/$AB$1,0) -> 0 | AC24: =_xlfn.IFNA(E24/$AB$1,0) -> 0 | AD24: =_xlfn.IFNA(F24/$AB$1,0) -> 0 | AE24: =_xlfn.IFNA(G24/$AB$1,0) -> 0 | AF24: =_xlfn.IFNA(H24/$AB$1,0) -> 0 | AG24: 34 | AM24: =_xlfn.IFNA(C24/$AN$1,0) -> 27.745944 | AN24: =_xlfn.IFNA(D24/$AN$1,0) -> 0 | AO24: =_xlfn.IFNA(E24/$AN$1,0) -> 0 | AP24: =_xlfn.IFNA(F24/$AN$1,0) -> 0 | AQ24: =_xlfn.IFNA(G24/$AN$1,0) -> 0 | AR24: =_xlfn.IFNA(H24/$AN$1,0) -> 0
B25: Zanahoria | C25: =Bollos!F14 -> 12.928453 | D25: 0 | E25: ='Pastel Zanahoria'!F21 -> 0 | F25: ='Pastel Zanahoria'!G21 -> 0 | G25: ='Pastel Zanahoria'!H21 -> 0 | H25: ='Pastel Zanahoria'!C21 -> 0 | I25: =_xlfn.IFNA(C25/$J$1,0) -> 28.729896 | J25: =_xlfn.IFNA(D25/$J$1,0) -> 0 | K25: =_xlfn.IFNA(E25/$J$1,0) -> 0 | L25: =_xlfn.IFNA(F25/$J$1,0) -> 0 | M25: =_xlfn.IFNA(G25/$J$1,0) -> 0 | N25: =_xlfn.IFNA(H25/$J$1,0) -> 0 | O25: =_xlfn.IFNA(C25/$P$1,0) -> 32.321133 | P25: =_xlfn.IFNA(D25/$P$1,0) -> 0 | Q25: =_xlfn.IFNA(E25/$P$1,0) -> 0 | R25: =_xlfn.IFNA(F25/$P$1,0) -> 0 | S25: =_xlfn.IFNA(G25/$P$1,0) -> 0 | T25: =_xlfn.IFNA(H25/$P$1,0) -> 0 | U25: =_xlfn.IFNA(C25/$V$1,0) -> 36.938438 | V25: =_xlfn.IFNA(D25/$V$1,0) -> 0 | W25: =_xlfn.IFNA(E25/$V$1,0) -> 0 | X25: =_xlfn.IFNA(F25/$V$1,0) -> 0 | Y25: =_xlfn.IFNA(G25/$V$1,0) -> 0 | Z25: =_xlfn.IFNA(H25/$V$1,0) -> 0 | AA25: =_xlfn.IFNA(C25/$AB$1,0) -> 43.094844 | AB25: =_xlfn.IFNA(D25/$AB$1,0) -> 0 | AC25: =_xlfn.IFNA(E25/$AB$1,0) -> 0 | AD25: =_xlfn.IFNA(F25/$AB$1,0) -> 0 | AE25: =_xlfn.IFNA(G25/$AB$1,0) -> 0 | AF25: =_xlfn.IFNA(H25/$AB$1,0) -> 0 | AG25: 27 | AM25: =_xlfn.IFNA(C25/$AN$1,0) -> 28.729896 | AN25: =_xlfn.IFNA(D25/$AN$1,0) -> 0 | AO25: =_xlfn.IFNA(E25/$AN$1,0) -> 0 | AP25: =_xlfn.IFNA(F25/$AN$1,0) -> 0 | AQ25: =_xlfn.IFNA(G25/$AN$1,0) -> 0 | AR25: =_xlfn.IFNA(H25/$AN$1,0) -> 0
B26: Red Velvet | C26: =Bollos!E14 -> 13.970433 | D26: ='Pastel Chocolate'!E24 -> 0 | E26: ='Pastel Chocolate'!F24 -> 0 | F26: ='Pastel Chocolate'!G24 -> 0 | G26: ='Pastel Chocolate'!H24 -> 0 | H26: ='Pastel Chocolate'!C24 -> 0 | I26: =_xlfn.IFNA(C26/$J$1,0) -> 31.045406 | J26: =_xlfn.IFNA(D26/$J$1,0) -> 0 | K26: =_xlfn.IFNA(E26/$J$1,0) -> 0 | L26: =_xlfn.IFNA(F26/$J$1,0) -> 0 | M26: =_xlfn.IFNA(G26/$J$1,0) -> 0 | N26: =_xlfn.IFNA(H26/$J$1,0) -> 0 | O26: =_xlfn.IFNA(C26/$P$1,0) -> 34.926082 | P26: =_xlfn.IFNA(D26/$P$1,0) -> 0 | Q26: =_xlfn.IFNA(E26/$P$1,0) -> 0 | R26: =_xlfn.IFNA(F26/$P$1,0) -> 0 | S26: =_xlfn.IFNA(G26/$P$1,0) -> 0 | T26: =_xlfn.IFNA(H26/$P$1,0) -> 0 | U26: =_xlfn.IFNA(C26/$V$1,0) -> 39.915522 | V26: =_xlfn.IFNA(D26/$V$1,0) -> 0 | W26: =_xlfn.IFNA(E26/$V$1,0) -> 0 | X26: =_xlfn.IFNA(F26/$V$1,0) -> 0 | Y26: =_xlfn.IFNA(G26/$V$1,0) -> 0 | Z26: =_xlfn.IFNA(H26/$V$1,0) -> 0 | AA26: =_xlfn.IFNA(C26/$AB$1,0) -> 46.568109 | AB26: =_xlfn.IFNA(D26/$AB$1,0) -> 0 | AC26: =_xlfn.IFNA(E26/$AB$1,0) -> 0 | AD26: =_xlfn.IFNA(F26/$AB$1,0) -> 0 | AE26: =_xlfn.IFNA(G26/$AB$1,0) -> 0 | AF26: =_xlfn.IFNA(H26/$AB$1,0) -> 0 | AG26: 30 | AM26: =_xlfn.IFNA(C26/$AN$1,0) -> 31.045406 | AN26: =_xlfn.IFNA(D26/$AN$1,0) -> 0 | AO26: =_xlfn.IFNA(E26/$AN$1,0) -> 0 | AP26: =_xlfn.IFNA(F26/$AN$1,0) -> 0 | AQ26: =_xlfn.IFNA(G26/$AN$1,0) -> 0 | AR26: =_xlfn.IFNA(H26/$AN$1,0) -> 0
B27: Lotus | C27: =Bollos!G14 -> 20.155525 | D27: 0 | E27: 0 | F27: 0 | G27: 0 | H27: 0 | I27: =_xlfn.IFNA(C27/$J$1,0) -> 44.790056 | J27: =_xlfn.IFNA(D27/$J$1,0) -> 0 | K27: =_xlfn.IFNA(E27/$J$1,0) -> 0 | L27: =_xlfn.IFNA(F27/$J$1,0) -> 0 | M27: =_xlfn.IFNA(G27/$J$1,0) -> 0 | N27: =_xlfn.IFNA(H27/$J$1,0) -> 0 | O27: =_xlfn.IFNA(C27/$P$1,0) -> 50.388813 | P27: =_xlfn.IFNA(D27/$P$1,0) -> 0 | Q27: =_xlfn.IFNA(E27/$P$1,0) -> 0 | R27: =_xlfn.IFNA(F27/$P$1,0) -> 0 | S27: =_xlfn.IFNA(G27/$P$1,0) -> 0 | T27: =_xlfn.IFNA(H27/$P$1,0) -> 0 | U27: =_xlfn.IFNA(C27/$V$1,0) -> 57.587215 | V27: =_xlfn.IFNA(D27/$V$1,0) -> 0 | W27: =_xlfn.IFNA(E27/$V$1,0) -> 0 | X27: =_xlfn.IFNA(F27/$V$1,0) -> 0 | Y27: =_xlfn.IFNA(G27/$V$1,0) -> 0 | Z27: =_xlfn.IFNA(H27/$V$1,0) -> 0 | AA27: =_xlfn.IFNA(C27/$AB$1,0) -> 67.185084 | AB27: =_xlfn.IFNA(D27/$AB$1,0) -> 0 | AC27: =_xlfn.IFNA(E27/$AB$1,0) -> 0 | AD27: =_xlfn.IFNA(F27/$AB$1,0) -> 0 | AE27: =_xlfn.IFNA(G27/$AB$1,0) -> 0 | AF27: =_xlfn.IFNA(H27/$AB$1,0) -> 0 | AG27: 39 | AM27: =_xlfn.IFNA(C27/$AN$1,0) -> 44.790056 | AN27: =_xlfn.IFNA(D27/$AN$1,0) -> 0 | AO27: =_xlfn.IFNA(E27/$AN$1,0) -> 0 | AP27: =_xlfn.IFNA(F27/$AN$1,0) -> 0 | AQ27: =_xlfn.IFNA(G27/$AN$1,0) -> 0 | AR27: =_xlfn.IFNA(H27/$AN$1,0) -> 0
A28: Cheesecake | B28: Lotus | C28: ='Resumen Costos'!C28 -> 60.99483 | D28: ='Resumen Costos'!D28 -> 0 | E28: ='Resumen Costos'!E28 -> 205.30523 | F28: ='Resumen Costos'!F28 -> 319.64719 | G28: ='Resumen Costos'!G28 -> 0 | H28: ='Resumen Costos'!H28 -> 0 | I28: =_xlfn.IFNA(C28/$J$1,0) -> 135.54407 | J28: =_xlfn.IFNA(D28/$J$1,0) -> 0 | K28: =_xlfn.IFNA(E28/$J$1,0) -> 456.23384 | L28: =_xlfn.IFNA(F28/$J$1,0) -> 710.32709 | M28: =_xlfn.IFNA(G28/$J$1,0) -> 0 | N28: =_xlfn.IFNA(H28/$J$1,0) -> 0 | O28: =_xlfn.IFNA(C28/$P$1,0) -> 152.48707 | P28: =_xlfn.IFNA(D28/$P$1,0) -> 0 | Q28: =_xlfn.IFNA(E28/$P$1,0) -> 513.26306 | R28: =_xlfn.IFNA(F28/$P$1,0) -> 799.11797 | S28: =_xlfn.IFNA(G28/$P$1,0) -> 0 | T28: =_xlfn.IFNA(H28/$P$1,0) -> 0 | U28: =_xlfn.IFNA(C28/$V$1,0) -> 174.27094 | V28: =_xlfn.IFNA(D28/$V$1,0) -> 0 | W28: =_xlfn.IFNA(E28/$V$1,0) -> 586.58636 | X28: =_xlfn.IFNA(F28/$V$1,0) -> 913.27768 | Y28: =_xlfn.IFNA(G28/$V$1,0) -> 0 | Z28: =_xlfn.IFNA(H28/$V$1,0) -> 0 | AA28: =_xlfn.IFNA(C28/$AB$1,0) -> 203.3161 | AB28: =_xlfn.IFNA(D28/$AB$1,0) -> 0 | AC28: =_xlfn.IFNA(E28/$AB$1,0) -> 684.35075 | AD28: =_xlfn.IFNA(F28/$AB$1,0) -> 1065.4906 | AE28: =_xlfn.IFNA(G28/$AB$1,0) -> 0 | AF28: =_xlfn.IFNA(H28/$AB$1,0) -> 0 | AG28: 135 | AJ28: 650 | AM28: =_xlfn.IFNA(C28/$AN$1,0) -> 135.54407 | AN28: =_xlfn.IFNA(D28/$AN$1,0) -> 0 | AO28: =_xlfn.IFNA(E28/$AN$1,0) -> 456.23384 | AP28: =_xlfn.IFNA(F28/$AN$1,0) -> 710.32709 | AQ28: =_xlfn.IFNA(G28/$AN$1,0) -> 0 | AR28: =_xlfn.IFNA(H28/$AN$1,0) -> 0
B29: Tortuga | C29: ='Resumen Costos'!C29 -> 52.683417 | D29: ='Resumen Costos'!D29 -> 0 | E29: ='Resumen Costos'!E29 -> 182.33088 | F29: ='Resumen Costos'!F29 -> 254.16219 | G29: ='Resumen Costos'!G29 -> 0 | H29: ='Resumen Costos'!H29 -> 0 | I29: =_xlfn.IFNA(C29/$J$1,0) -> 117.07426 | J29: =_xlfn.IFNA(D29/$J$1,0) -> 0 | K29: =_xlfn.IFNA(E29/$J$1,0) -> 405.17974 | L29: =_xlfn.IFNA(F29/$J$1,0) -> 564.80487 | M29: =_xlfn.IFNA(G29/$J$1,0) -> 0 | N29: =_xlfn.IFNA(H29/$J$1,0) -> 0 | O29: =_xlfn.IFNA(C29/$P$1,0) -> 131.70854 | P29: =_xlfn.IFNA(D29/$P$1,0) -> 0 | Q29: =_xlfn.IFNA(E29/$P$1,0) -> 455.82721 | R29: =_xlfn.IFNA(F29/$P$1,0) -> 635.40548 | S29: =_xlfn.IFNA(G29/$P$1,0) -> 0 | T29: =_xlfn.IFNA(H29/$P$1,0) -> 0 | U29: =_xlfn.IFNA(C29/$V$1,0) -> 150.52405 | V29: =_xlfn.IFNA(D29/$V$1,0) -> 0 | W29: =_xlfn.IFNA(E29/$V$1,0) -> 520.94538 | X29: =_xlfn.IFNA(F29/$V$1,0) -> 726.17769 | Y29: =_xlfn.IFNA(G29/$V$1,0) -> 0 | Z29: =_xlfn.IFNA(H29/$V$1,0) -> 0 | AA29: =_xlfn.IFNA(C29/$AB$1,0) -> 175.61139 | AB29: =_xlfn.IFNA(D29/$AB$1,0) -> 0 | AC29: =_xlfn.IFNA(E29/$AB$1,0) -> 607.76961 | AD29: =_xlfn.IFNA(F29/$AB$1,0) -> 847.20731 | AE29: =_xlfn.IFNA(G29/$AB$1,0) -> 0 | AF29: =_xlfn.IFNA(H29/$AB$1,0) -> 0 | AG29: 125 | AJ29: 590 | AM29: =_xlfn.IFNA(C29/$AN$1,0) -> 117.07426 | AN29: =_xlfn.IFNA(D29/$AN$1,0) -> 0 | AO29: =_xlfn.IFNA(E29/$AN$1,0) -> 405.17974 | AP29: =_xlfn.IFNA(F29/$AN$1,0) -> 564.80487 | AQ29: =_xlfn.IFNA(G29/$AN$1,0) -> 0 | AR29: =_xlfn.IFNA(H29/$AN$1,0) -> 0
B30: Brownie | C30: ='Resumen Costos'!C30 -> 45.518018 | D30: ='Resumen Costos'!D30 -> 0 | E30: ='Resumen Costos'!E30 -> 179.67515 | F30: ='Resumen Costos'!F30 -> 250.2993 | G30: ='Resumen Costos'!G30 -> 0 | H30: ='Resumen Costos'!H30 -> 0 | I30: =_xlfn.IFNA(C30/$J$1,0) -> 101.15115 | J30: =_xlfn.IFNA(D30/$J$1,0) -> 0 | K30: =_xlfn.IFNA(E30/$J$1,0) -> 399.2781 | L30: =_xlfn.IFNA(F30/$J$1,0) -> 556.22067 | M30: =_xlfn.IFNA(G30/$J$1,0) -> 0 | N30: =_xlfn.IFNA(H30/$J$1,0) -> 0 | O30: =_xlfn.IFNA(C30/$P$1,0) -> 113.79505 | P30: =_xlfn.IFNA(D30/$P$1,0) -> 0 | Q30: =_xlfn.IFNA(E30/$P$1,0) -> 449.18786 | R30: =_xlfn.IFNA(F30/$P$1,0) -> 625.74826 | S30: =_xlfn.IFNA(G30/$P$1,0) -> 0 | T30: =_xlfn.IFNA(H30/$P$1,0) -> 0 | U30: =_xlfn.IFNA(C30/$V$1,0) -> 130.05148 | V30: =_xlfn.IFNA(D30/$V$1,0) -> 0 | W30: =_xlfn.IFNA(E30/$V$1,0) -> 513.35756 | X30: =_xlfn.IFNA(F30/$V$1,0) -> 715.14087 | Y30: =_xlfn.IFNA(G30/$V$1,0) -> 0 | Z30: =_xlfn.IFNA(H30/$V$1,0) -> 0 | AA30: =_xlfn.IFNA(C30/$AB$1,0) -> 151.72673 | AB30: =_xlfn.IFNA(D30/$AB$1,0) -> 0 | AC30: =_xlfn.IFNA(E30/$AB$1,0) -> 598.91715 | AD30: =_xlfn.IFNA(F30/$AB$1,0) -> 834.33101 | AE30: =_xlfn.IFNA(G30/$AB$1,0) -> 0 | AF30: =_xlfn.IFNA(H30/$AB$1,0) -> 0 | AG30: 125 | AJ30: 560 | AM30: =_xlfn.IFNA(C30/$AN$1,0) -> 101.15115 | AN30: =_xlfn.IFNA(D30/$AN$1,0) -> 0 | AO30: =_xlfn.IFNA(E30/$AN$1,0) -> 399.2781 | AP30: =_xlfn.IFNA(F30/$AN$1,0) -> 556.22067 | AQ30: =_xlfn.IFNA(G30/$AN$1,0) -> 0 | AR30: =_xlfn.IFNA(H30/$AN$1,0) -> 0
B31: Zarzamora | C31: ='Resumen Costos'!C31 -> 52.866543 | D31: ='Resumen Costos'!D31 -> 0 | E31: ='Resumen Costos'!E31 -> 198.97726 | F31: ='Resumen Costos'!F31 -> 286.3147 | G31: ='Resumen Costos'!G31 -> 0 | H31: ='Resumen Costos'!H31 -> 0 | I31: =_xlfn.IFNA(C31/$J$1,0) -> 117.48121 | J31: =_xlfn.IFNA(D31/$J$1,0) -> 0 | K31: =_xlfn.IFNA(E31/$J$1,0) -> 442.1717 | L31: =_xlfn.IFNA(F31/$J$1,0) -> 636.25488 | M31: =_xlfn.IFNA(G31/$J$1,0) -> 0 | N31: =_xlfn.IFNA(H31/$J$1,0) -> 0 | O31: =_xlfn.IFNA(C31/$P$1,0) -> 132.16636 | P31: =_xlfn.IFNA(D31/$P$1,0) -> 0 | Q31: =_xlfn.IFNA(E31/$P$1,0) -> 497.44316 | R31: =_xlfn.IFNA(F31/$P$1,0) -> 715.78674 | S31: =_xlfn.IFNA(G31/$P$1,0) -> 0 | T31: =_xlfn.IFNA(H31/$P$1,0) -> 0 | U31: =_xlfn.IFNA(C31/$V$1,0) -> 151.04727 | V31: =_xlfn.IFNA(D31/$V$1,0) -> 0 | W31: =_xlfn.IFNA(E31/$V$1,0) -> 568.50647 | X31: =_xlfn.IFNA(F31/$V$1,0) -> 818.04199 | Y31: =_xlfn.IFNA(G31/$V$1,0) -> 0 | Z31: =_xlfn.IFNA(H31/$V$1,0) -> 0 | AA31: =_xlfn.IFNA(C31/$AB$1,0) -> 176.22181 | AB31: =_xlfn.IFNA(D31/$AB$1,0) -> 0 | AC31: =_xlfn.IFNA(E31/$AB$1,0) -> 663.25755 | AD31: =_xlfn.IFNA(F31/$AB$1,0) -> 954.38232 | AE31: =_xlfn.IFNA(G31/$AB$1,0) -> 0 | AF31: =_xlfn.IFNA(H31/$AB$1,0) -> 0 | AG31: 125 | AJ31: 650 | AM31: =_xlfn.IFNA(C31/$AN$1,0) -> 117.48121 | AN31: =_xlfn.IFNA(D31/$AN$1,0) -> 0 | AO31: =_xlfn.IFNA(E31/$AN$1,0) -> 442.1717 | AP31: =_xlfn.IFNA(F31/$AN$1,0) -> 636.25488 | AQ31: =_xlfn.IFNA(G31/$AN$1,0) -> 0 | AR31: =_xlfn.IFNA(H31/$AN$1,0) -> 0
B32: Zanahoria | C32: ='Resumen Costos'!C32 -> 0 | D32: ='Resumen Costos'!D32 -> 0 | E32: ='Resumen Costos'!E32 -> 0 | F32: ='Resumen Costos'!F32 -> 0 | G32: ='Resumen Costos'!G32 -> 0 | H32: ='Resumen Costos'!H32 -> 0 | I32: =_xlfn.IFNA(C32/$J$1,0) -> 0 | J32: =_xlfn.IFNA(D32/$J$1,0) -> 0 | K32: =_xlfn.IFNA(E32/$J$1,0) -> 0 | L32: =_xlfn.IFNA(F32/$J$1,0) -> 0 | M32: =_xlfn.IFNA(G32/$J$1,0) -> 0 | N32: =_xlfn.IFNA(H32/$J$1,0) -> 0 | O32: =_xlfn.IFNA(C32/$P$1,0) -> 0 | P32: =_xlfn.IFNA(D32/$P$1,0) -> 0 | Q32: =_xlfn.IFNA(E32/$P$1,0) -> 0 | R32: =_xlfn.IFNA(F32/$P$1,0) -> 0 | S32: =_xlfn.IFNA(G32/$P$1,0) -> 0 | T32: =_xlfn.IFNA(H32/$P$1,0) -> 0 | U32: =_xlfn.IFNA(C32/$V$1,0) -> 0 | V32: =_xlfn.IFNA(D32/$V$1,0) -> 0 | W32: =_xlfn.IFNA(E32/$V$1,0) -> 0 | X32: =_xlfn.IFNA(F32/$V$1,0) -> 0 | Y32: =_xlfn.IFNA(G32/$V$1,0) -> 0 | Z32: =_xlfn.IFNA(H32/$V$1,0) -> 0 | AA32: =_xlfn.IFNA(C32/$AB$1,0) -> 0 | AB32: =_xlfn.IFNA(D32/$AB$1,0) -> 0 | AC32: =_xlfn.IFNA(E32/$AB$1,0) -> 0 | AD32: =_xlfn.IFNA(F32/$AB$1,0) -> 0 | AE32: =_xlfn.IFNA(G32/$AB$1,0) -> 0 | AF32: =_xlfn.IFNA(H32/$AB$1,0) -> 0 | AG32: =-AG32 -> 0 | AM32: =_xlfn.IFNA(C32/$AN$1,0) -> 0 | AN32: =_xlfn.IFNA(D32/$AN$1,0) -> 0 | AO32: =_xlfn.IFNA(E32/$AN$1,0) -> 0 | AP32: =_xlfn.IFNA(F32/$AN$1,0) -> 0 | AQ32: =_xlfn.IFNA(G32/$AN$1,0) -> 0 | AR32: =_xlfn.IFNA(H32/$AN$1,0) -> 0
B33: Rol de Canela | C33: =Cheesecake!BM29 -> 56.522501 | D33: ='Resumen Costos'!D33 -> 0 | E33: =Cheesecake!BJ29 -> 194.38114 | F33: =Cheesecake!BG29 -> 280.56721 | G33: ='Resumen Costos'!G33 -> 0 | H33: ='Resumen Costos'!H33 -> 0 | I33: =_xlfn.IFNA(C33/$J$1,0) -> 125.60556 | J33: =_xlfn.IFNA(D33/$J$1,0) -> 0 | K33: =_xlfn.IFNA(E33/$J$1,0) -> 431.95809 | L33: =_xlfn.IFNA(F33/$J$1,0) -> 623.4827 | M33: =_xlfn.IFNA(G33/$J$1,0) -> 0 | N33: =_xlfn.IFNA(H33/$J$1,0) -> 0 | O33: =_xlfn.IFNA(C33/$P$1,0) -> 141.30625 | P33: =_xlfn.IFNA(D33/$P$1,0) -> 0 | Q33: =_xlfn.IFNA(E33/$P$1,0) -> 485.95286 | R33: =_xlfn.IFNA(F33/$P$1,0) -> 701.41803 | S33: =_xlfn.IFNA(G33/$P$1,0) -> 0 | T33: =_xlfn.IFNA(H33/$P$1,0) -> 0 | U33: =_xlfn.IFNA(C33/$V$1,0) -> 161.49286 | V33: =_xlfn.IFNA(D33/$V$1,0) -> 0 | W33: =_xlfn.IFNA(E33/$V$1,0) -> 555.37469 | X33: =_xlfn.IFNA(F33/$V$1,0) -> 801.62061 | Y33: =_xlfn.IFNA(G33/$V$1,0) -> 0 | Z33: =_xlfn.IFNA(H33/$V$1,0) -> 0 | AA33: =_xlfn.IFNA(C33/$AB$1,0) -> 188.40834 | AB33: =_xlfn.IFNA(D33/$AB$1,0) -> 0 | AC33: =_xlfn.IFNA(E33/$AB$1,0) -> 647.93714 | AD33: =_xlfn.IFNA(F33/$AB$1,0) -> 935.22404 | AE33: =_xlfn.IFNA(G33/$AB$1,0) -> 0 | AF33: =_xlfn.IFNA(H33/$AB$1,0) -> 0 | AG33: 130 | AJ33: 635 | AM33: =_xlfn.IFNA(C33/$AN$1,0) -> 125.60556 | AN33: =_xlfn.IFNA(D33/$AN$1,0) -> 0 | AO33: =_xlfn.IFNA(E33/$AN$1,0) -> 431.95809 | AP33: =_xlfn.IFNA(F33/$AN$1,0) -> 623.4827 | AQ33: =_xlfn.IFNA(G33/$AN$1,0) -> 0 | AR33: =_xlfn.IFNA(H33/$AN$1,0) -> 0
B34: Manzana | C34: ='Resumen Costos'!C34 -> 0 | D34: ='Resumen Costos'!D34 -> 0 | E34: ='Resumen Costos'!E34 -> 0 | F34: ='Resumen Costos'!F34 -> 0 | G34: ='Resumen Costos'!G34 -> 0 | H34: ='Resumen Costos'!H34 -> 0 | I34: =_xlfn.IFNA(C34/$J$1,0) -> 0 | J34: =_xlfn.IFNA(D34/$J$1,0) -> 0 | K34: =_xlfn.IFNA(E34/$J$1,0) -> 0 | L34: =_xlfn.IFNA(F34/$J$1,0) -> 0 | M34: =_xlfn.IFNA(G34/$J$1,0) -> 0 | N34: =_xlfn.IFNA(H34/$J$1,0) -> 0 | O34: =_xlfn.IFNA(C34/$P$1,0) -> 0 | P34: =_xlfn.IFNA(D34/$P$1,0) -> 0 | Q34: =_xlfn.IFNA(E34/$P$1,0) -> 0 | R34: =_xlfn.IFNA(F34/$P$1,0) -> 0 | S34: =_xlfn.IFNA(G34/$P$1,0) -> 0 | T34: =_xlfn.IFNA(H34/$P$1,0) -> 0 | U34: =_xlfn.IFNA(C34/$V$1,0) -> 0 | V34: =_xlfn.IFNA(D34/$V$1,0) -> 0 | W34: =_xlfn.IFNA(E34/$V$1,0) -> 0 | X34: =_xlfn.IFNA(F34/$V$1,0) -> 0 | Y34: =_xlfn.IFNA(G34/$V$1,0) -> 0 | Z34: =_xlfn.IFNA(H34/$V$1,0) -> 0 | AA34: =_xlfn.IFNA(C34/$AB$1,0) -> 0 | AB34: =_xlfn.IFNA(D34/$AB$1,0) -> 0 | AC34: =_xlfn.IFNA(E34/$AB$1,0) -> 0 | AD34: =_xlfn.IFNA(F34/$AB$1,0) -> 0 | AE34: =_xlfn.IFNA(G34/$AB$1,0) -> 0 | AF34: =_xlfn.IFNA(H34/$AB$1,0) -> 0 | AG34: 130 | AJ34: 600 | AM34: =_xlfn.IFNA(C34/$AN$1,0) -> 0 | AN34: =_xlfn.IFNA(D34/$AN$1,0) -> 0 | AO34: =_xlfn.IFNA(E34/$AN$1,0) -> 0 | AP34: =_xlfn.IFNA(F34/$AN$1,0) -> 0 | AQ34: =_xlfn.IFNA(G34/$AN$1,0) -> 0 | AR34: =_xlfn.IFNA(H34/$AN$1,0) -> 0
B35: Limón | C35: ='Resumen Costos'!C35 -> 51.531339 | D35: ='Resumen Costos'!D35 -> 0 | E35: ='Resumen Costos'!E35 -> 168.3096 | F35: ='Resumen Costos'!F35 -> 244.24056 | G35: ='Resumen Costos'!G35 -> 0 | H35: ='Resumen Costos'!H35 -> 0 | I35: =_xlfn.IFNA(C35/$J$1,0) -> 114.51409 | J35: =_xlfn.IFNA(D35/$J$1,0) -> 0 | K35: =_xlfn.IFNA(E35/$J$1,0) -> 374.02133 | L35: =_xlfn.IFNA(F35/$J$1,0) -> 542.7568 | M35: =_xlfn.IFNA(G35/$J$1,0) -> 0 | N35: =_xlfn.IFNA(H35/$J$1,0) -> 0 | O35: =_xlfn.IFNA(C35/$P$1,0) -> 128.82835 | P35: =_xlfn.IFNA(D35/$P$1,0) -> 0 | Q35: =_xlfn.IFNA(E35/$P$1,0) -> 420.774 | R35: =_xlfn.IFNA(F35/$P$1,0) -> 610.6014 | S35: =_xlfn.IFNA(G35/$P$1,0) -> 0 | T35: =_xlfn.IFNA(H35/$P$1,0) -> 0 | U35: =_xlfn.IFNA(C35/$V$1,0) -> 147.2324 | V35: =_xlfn.IFNA(D35/$V$1,0) -> 0 | W35: =_xlfn.IFNA(E35/$V$1,0) -> 480.88457 | X35: =_xlfn.IFNA(F35/$V$1,0) -> 697.83017 | Y35: =_xlfn.IFNA(G35/$V$1,0) -> 0 | Z35: =_xlfn.IFNA(H35/$V$1,0) -> 0 | AA35: =_xlfn.IFNA(C35/$AB$1,0) -> 171.77113 | AB35: =_xlfn.IFNA(D35/$AB$1,0) -> 0 | AC35: =_xlfn.IFNA(E35/$AB$1,0) -> 561.032 | AD35: =_xlfn.IFNA(F35/$AB$1,0) -> 814.1352 | AE35: =_xlfn.IFNA(G35/$AB$1,0) -> 0 | AF35: =_xlfn.IFNA(H35/$AB$1,0) -> 0 | AG35: 125 | AJ35: 555 | AM35: =_xlfn.IFNA(C35/$AN$1,0) -> 114.51409 | AN35: =_xlfn.IFNA(D35/$AN$1,0) -> 0 | AO35: =_xlfn.IFNA(E35/$AN$1,0) -> 374.02133 | AP35: =_xlfn.IFNA(F35/$AN$1,0) -> 542.7568 | AQ35: =_xlfn.IFNA(G35/$AN$1,0) -> 0 | AR35: =_xlfn.IFNA(H35/$AN$1,0) -> 0
A36: Galletas | B36: Chispas de Chocolate | C36: =Galletas!#REF! -> #REF! | D36: 0 | E36: 0 | F36: 0 | G36: 0 | H36: 0 | I36: =_xlfn.IFNA(C36/$J$1,0) -> #REF! | J36: =_xlfn.IFNA(D36/$J$1,0) -> 0 | K36: =_xlfn.IFNA(E36/$J$1,0) -> 0 | L36: =_xlfn.IFNA(F36/$J$1,0) -> 0 | M36: =_xlfn.IFNA(G36/$J$1,0) -> 0 | N36: =_xlfn.IFNA(H36/$J$1,0) -> 0 | O36: =_xlfn.IFNA(C36/$P$1,0) -> #REF! | P36: =_xlfn.IFNA(D36/$P$1,0) -> 0 | Q36: =_xlfn.IFNA(E36/$P$1,0) -> 0 | R36: =_xlfn.IFNA(F36/$P$1,0) -> 0 | S36: =_xlfn.IFNA(G36/$P$1,0) -> 0 | T36: =_xlfn.IFNA(H36/$P$1,0) -> 0 | U36: =_xlfn.IFNA(C36/$V$1,0) -> #REF! | V36: =_xlfn.IFNA(D36/$V$1,0) -> 0 | W36: =_xlfn.IFNA(E36/$V$1,0) -> 0 | X36: =_xlfn.IFNA(F36/$V$1,0) -> 0 | Y36: =_xlfn.IFNA(G36/$V$1,0) -> 0 | Z36: =_xlfn.IFNA(H36/$V$1,0) -> 0 | AA36: =_xlfn.IFNA(C36/$AB$1,0) -> #REF! | AB36: =_xlfn.IFNA(D36/$AB$1,0) -> 0 | AC36: =_xlfn.IFNA(E36/$AB$1,0) -> 0 | AD36: =_xlfn.IFNA(F36/$AB$1,0) -> 0 | AE36: =_xlfn.IFNA(G36/$AB$1,0) -> 0 | AF36: =_xlfn.IFNA(H36/$AB$1,0) -> 0 | AG36: 32 | AM36: =_xlfn.IFNA(C36/$AN$1,0) -> #REF! | AN36: =_xlfn.IFNA(D36/$AN$1,0) -> 0 | AO36: =_xlfn.IFNA(E36/$AN$1,0) -> 0 | AP36: =_xlfn.IFNA(F36/$AN$1,0) -> 0 | AQ36: =_xlfn.IFNA(G36/$AN$1,0) -> 0 | AR36: =_xlfn.IFNA(H36/$AN$1,0) -> 0
B37: Lotus | C37: =Galletas!D68 -> 18.026862 | I37: =_xlfn.IFNA(C37/$J$1,0) -> 40.059693 | J37: =_xlfn.IFNA(D37/$J$1,0) -> 0 | K37: =_xlfn.IFNA(E37/$J$1,0) -> 0 | L37: =_xlfn.IFNA(F37/$J$1,0) -> 0 | M37: =_xlfn.IFNA(G37/$J$1,0) -> 0 | N37: =_xlfn.IFNA(H37/$J$1,0) -> 0 | O37: =_xlfn.IFNA(C37/$P$1,0) -> 45.067154 | P37: =_xlfn.IFNA(D37/$P$1,0) -> 0 | Q37: =_xlfn.IFNA(E37/$P$1,0) -> 0 | R37: =_xlfn.IFNA(F37/$P$1,0) -> 0 | S37: =_xlfn.IFNA(G37/$P$1,0) -> 0 | T37: =_xlfn.IFNA(H37/$P$1,0) -> 0 | U37: =_xlfn.IFNA(C37/$V$1,0) -> 51.505319 | V37: =_xlfn.IFNA(D37/$V$1,0) -> 0 | W37: =_xlfn.IFNA(E37/$V$1,0) -> 0 | X37: =_xlfn.IFNA(F37/$V$1,0) -> 0 | Y37: =_xlfn.IFNA(G37/$V$1,0) -> 0 | Z37: =_xlfn.IFNA(H37/$V$1,0) -> 0 | AA37: =_xlfn.IFNA(C37/$AB$1,0) -> 60.089539 | AB37: =_xlfn.IFNA(D37/$AB$1,0) -> 0 | AC37: =_xlfn.IFNA(E37/$AB$1,0) -> 0 | AD37: =_xlfn.IFNA(F37/$AB$1,0) -> 0 | AE37: =_xlfn.IFNA(G37/$AB$1,0) -> 0 | AF37: =_xlfn.IFNA(H37/$AB$1,0) -> 0 | AG37: 48 | AM37: =_xlfn.IFNA(C37/$AN$1,0) -> 40.059693 | AN37: =_xlfn.IFNA(D37/$AN$1,0) -> 0 | AO37: =_xlfn.IFNA(E37/$AN$1,0) -> 0 | AP37: =_xlfn.IFNA(F37/$AN$1,0) -> 0 | AQ37: =_xlfn.IFNA(G37/$AN$1,0) -> 0 | AR37: =_xlfn.IFNA(H37/$AN$1,0) -> 0
B38: Red Velvet | C38: =Galletas!D225 -> 12.908 | I38: =_xlfn.IFNA(C38/$J$1,0) -> 28.684445 | J38: =_xlfn.IFNA(D38/$J$1,0) -> 0 | K38: =_xlfn.IFNA(E38/$J$1,0) -> 0 | L38: =_xlfn.IFNA(F38/$J$1,0) -> 0 | M38: =_xlfn.IFNA(G38/$J$1,0) -> 0 | N38: =_xlfn.IFNA(H38/$J$1,0) -> 0 | O38: =_xlfn.IFNA(C38/$P$1,0) -> 32.27 | P38: =_xlfn.IFNA(D38/$P$1,0) -> 0 | Q38: =_xlfn.IFNA(E38/$P$1,0) -> 0 | R38: =_xlfn.IFNA(F38/$P$1,0) -> 0 | S38: =_xlfn.IFNA(G38/$P$1,0) -> 0 | T38: =_xlfn.IFNA(H38/$P$1,0) -> 0 | U38: =_xlfn.IFNA(C38/$V$1,0) -> 36.880001 | V38: =_xlfn.IFNA(D38/$V$1,0) -> 0 | W38: =_xlfn.IFNA(E38/$V$1,0) -> 0 | X38: =_xlfn.IFNA(F38/$V$1,0) -> 0 | Y38: =_xlfn.IFNA(G38/$V$1,0) -> 0 | Z38: =_xlfn.IFNA(H38/$V$1,0) -> 0 | AA38: =_xlfn.IFNA(C38/$AB$1,0) -> 43.026667 | AB38: =_xlfn.IFNA(D38/$AB$1,0) -> 0 | AC38: =_xlfn.IFNA(E38/$AB$1,0) -> 0 | AD38: =_xlfn.IFNA(F38/$AB$1,0) -> 0 | AE38: =_xlfn.IFNA(G38/$AB$1,0) -> 0 | AF38: =_xlfn.IFNA(H38/$AB$1,0) -> 0 | AG38: 30 | AM38: =_xlfn.IFNA(C38/$AN$1,0) -> 28.684445 | AN38: =_xlfn.IFNA(D38/$AN$1,0) -> 0 | AO38: =_xlfn.IFNA(E38/$AN$1,0) -> 0 | AP38: =_xlfn.IFNA(F38/$AN$1,0) -> 0 | AQ38: =_xlfn.IFNA(G38/$AN$1,0) -> 0 | AR38: =_xlfn.IFNA(H38/$AN$1,0) -> 0
B39: Nutella | C39: =Galletas!D90 -> 15.731111 | I39: =_xlfn.IFNA(C39/$J$1,0) -> 34.958025 | J39: =_xlfn.IFNA(D39/$J$1,0) -> 0 | K39: =_xlfn.IFNA(E39/$J$1,0) -> 0 | L39: =_xlfn.IFNA(F39/$J$1,0) -> 0 | M39: =_xlfn.IFNA(G39/$J$1,0) -> 0 | N39: =_xlfn.IFNA(H39/$J$1,0) -> 0 | O39: =_xlfn.IFNA(C39/$P$1,0) -> 39.327779 | P39: =_xlfn.IFNA(D39/$P$1,0) -> 0 | Q39: =_xlfn.IFNA(E39/$P$1,0) -> 0 | R39: =_xlfn.IFNA(F39/$P$1,0) -> 0 | S39: =_xlfn.IFNA(G39/$P$1,0) -> 0 | T39: =_xlfn.IFNA(H39/$P$1,0) -> 0 | U39: =_xlfn.IFNA(C39/$V$1,0) -> 44.946033 | V39: =_xlfn.IFNA(D39/$V$1,0) -> 0 | W39: =_xlfn.IFNA(E39/$V$1,0) -> 0 | X39: =_xlfn.IFNA(F39/$V$1,0) -> 0 | Y39: =_xlfn.IFNA(G39/$V$1,0) -> 0 | Z39: =_xlfn.IFNA(H39/$V$1,0) -> 0 | AA39: =_xlfn.IFNA(C39/$AB$1,0) -> 52.437038 | AB39: =_xlfn.IFNA(D39/$AB$1,0) -> 0 | AC39: =_xlfn.IFNA(E39/$AB$1,0) -> 0 | AD39: =_xlfn.IFNA(F39/$AB$1,0) -> 0 | AE39: =_xlfn.IFNA(G39/$AB$1,0) -> 0 | AF39: =_xlfn.IFNA(H39/$AB$1,0) -> 0 | AG39: 30 | AM39: =_xlfn.IFNA(C39/$AN$1,0) -> 34.958025 | AN39: =_xlfn.IFNA(D39/$AN$1,0) -> 0 | AO39: =_xlfn.IFNA(E39/$AN$1,0) -> 0 | AP39: =_xlfn.IFNA(F39/$AN$1,0) -> 0 | AQ39: =_xlfn.IFNA(G39/$AN$1,0) -> 0 | AR39: =_xlfn.IFNA(H39/$AN$1,0) -> 0
B40: Dulce de Leche | C40: =Galletas!D122 -> 14.586311 | I40: =_xlfn.IFNA(C40/$J$1,0) -> 32.414025 | J40: =_xlfn.IFNA(D40/$J$1,0) -> 0 | K40: =_xlfn.IFNA(E40/$J$1,0) -> 0 | L40: =_xlfn.IFNA(F40/$J$1,0) -> 0 | M40: =_xlfn.IFNA(G40/$J$1,0) -> 0 | N40: =_xlfn.IFNA(H40/$J$1,0) -> 0 | O40: =_xlfn.IFNA(C40/$P$1,0) -> 36.465779 | P40: =_xlfn.IFNA(D40/$P$1,0) -> 0 | Q40: =_xlfn.IFNA(E40/$P$1,0) -> 0 | R40: =_xlfn.IFNA(F40/$P$1,0) -> 0 | S40: =_xlfn.IFNA(G40/$P$1,0) -> 0 | T40: =_xlfn.IFNA(H40/$P$1,0) -> 0 | U40: =_xlfn.IFNA(C40/$V$1,0) -> 41.675176 | V40: =_xlfn.IFNA(D40/$V$1,0) -> 0 | W40: =_xlfn.IFNA(E40/$V$1,0) -> 0 | X40: =_xlfn.IFNA(F40/$V$1,0) -> 0 | Y40: =_xlfn.IFNA(G40/$V$1,0) -> 0 | Z40: =_xlfn.IFNA(H40/$V$1,0) -> 0 | AA40: =_xlfn.IFNA(C40/$AB$1,0) -> 48.621038 | AB40: =_xlfn.IFNA(D40/$AB$1,0) -> 0 | AC40: =_xlfn.IFNA(E40/$AB$1,0) -> 0 | AD40: =_xlfn.IFNA(F40/$AB$1,0) -> 0 | AE40: =_xlfn.IFNA(G40/$AB$1,0) -> 0 | AF40: =_xlfn.IFNA(H40/$AB$1,0) -> 0 | AG40: 32 | AM40: =_xlfn.IFNA(C40/$AN$1,0) -> 32.414025 | AN40: =_xlfn.IFNA(D40/$AN$1,0) -> 0 | AO40: =_xlfn.IFNA(E40/$AN$1,0) -> 0 | AP40: =_xlfn.IFNA(F40/$AN$1,0) -> 0 | AQ40: =_xlfn.IFNA(G40/$AN$1,0) -> 0 | AR40: =_xlfn.IFNA(H40/$AN$1,0) -> 0
B41: Oreo | C41: =Galletas!D156 -> 8.9995665 | I41: =_xlfn.IFNA(C41/$J$1,0) -> 19.999037 | J41: =_xlfn.IFNA(D41/$J$1,0) -> 0 | K41: =_xlfn.IFNA(E41/$J$1,0) -> 0 | L41: =_xlfn.IFNA(F41/$J$1,0) -> 0 | M41: =_xlfn.IFNA(G41/$J$1,0) -> 0 | N41: =_xlfn.IFNA(H41/$J$1,0) -> 0 | O41: =_xlfn.IFNA(C41/$P$1,0) -> 22.498916 | P41: =_xlfn.IFNA(D41/$P$1,0) -> 0 | Q41: =_xlfn.IFNA(E41/$P$1,0) -> 0 | R41: =_xlfn.IFNA(F41/$P$1,0) -> 0 | S41: =_xlfn.IFNA(G41/$P$1,0) -> 0 | T41: =_xlfn.IFNA(H41/$P$1,0) -> 0 | U41: =_xlfn.IFNA(C41/$V$1,0) -> 25.713047 | V41: =_xlfn.IFNA(D41/$V$1,0) -> 0 | W41: =_xlfn.IFNA(E41/$V$1,0) -> 0 | X41: =_xlfn.IFNA(F41/$V$1,0) -> 0 | Y41: =_xlfn.IFNA(G41/$V$1,0) -> 0 | Z41: =_xlfn.IFNA(H41/$V$1,0) -> 0 | AA41: =_xlfn.IFNA(C41/$AB$1,0) -> 29.998555 | AB41: =_xlfn.IFNA(D41/$AB$1,0) -> 0 | AC41: =_xlfn.IFNA(E41/$AB$1,0) -> 0 | AD41: =_xlfn.IFNA(F41/$AB$1,0) -> 0 | AE41: =_xlfn.IFNA(G41/$AB$1,0) -> 0 | AF41: =_xlfn.IFNA(H41/$AB$1,0) -> 0 | AG41: 30 | AM41: =_xlfn.IFNA(C41/$AN$1,0) -> 19.999037 | AN41: =_xlfn.IFNA(D41/$AN$1,0) -> 0 | AO41: =_xlfn.IFNA(E41/$AN$1,0) -> 0 | AP41: =_xlfn.IFNA(F41/$AN$1,0) -> 0 | AQ41: =_xlfn.IFNA(G41/$AN$1,0) -> 0 | AR41: =_xlfn.IFNA(H41/$AN$1,0) -> 0
A42: Roscas | B42: Zanahoria | C42: =Roscas!K32 -> 164.17525 | D42: 0 | E42: 0 | F42: 0 | G42: 0 | H42: 0 | I42: =_xlfn.IFNA(C42/$J$1,0) -> 364.83388 | J42: =_xlfn.IFNA(D42/$J$1,0) -> 0 | K42: =_xlfn.IFNA(E42/$J$1,0) -> 0 | L42: =_xlfn.IFNA(F42/$J$1,0) -> 0 | M42: =_xlfn.IFNA(G42/$J$1,0) -> 0 | N42: =_xlfn.IFNA(H42/$J$1,0) -> 0 | O42: =_xlfn.IFNA(C42/$P$1,0) -> 410.43811 | P42: =_xlfn.IFNA(D42/$P$1,0) -> 0 | Q42: =_xlfn.IFNA(E42/$P$1,0) -> 0 | R42: =_xlfn.IFNA(F42/$P$1,0) -> 0 | S42: =_xlfn.IFNA(G42/$P$1,0) -> 0 | T42: =_xlfn.IFNA(H42/$P$1,0) -> 0 | U42: =_xlfn.IFNA(C42/$V$1,0) -> 469.07213 | V42: =_xlfn.IFNA(D42/$V$1,0) -> 0 | W42: =_xlfn.IFNA(E42/$V$1,0) -> 0 | X42: =_xlfn.IFNA(F42/$V$1,0) -> 0 | Y42: =_xlfn.IFNA(G42/$V$1,0) -> 0 | Z42: =_xlfn.IFNA(H42/$V$1,0) -> 0 | AA42: =_xlfn.IFNA(C42/$AB$1,0) -> 547.25082 | AB42: =_xlfn.IFNA(D42/$AB$1,0) -> 0 | AC42: =_xlfn.IFNA(E42/$AB$1,0) -> 0 | AD42: =_xlfn.IFNA(F42/$AB$1,0) -> 0 | AE42: =_xlfn.IFNA(G42/$AB$1,0) -> 0 | AF42: =_xlfn.IFNA(H42/$AB$1,0) -> 0 | AG42: 32 | AM42: =_xlfn.IFNA(C42/$AN$1,0) -> 364.83388 | AN42: =_xlfn.IFNA(D42/$AN$1,0) -> 0 | AO42: =_xlfn.IFNA(E42/$AN$1,0) -> 0 | AP42: =_xlfn.IFNA(F42/$AN$1,0) -> 0 | AQ42: =_xlfn.IFNA(G42/$AN$1,0) -> 0 | AR42: =_xlfn.IFNA(H42/$AN$1,0) -> 0
B43: Dulce de Leches | C43: =Roscas!O32 -> 143.30808 | I43: =_xlfn.IFNA(C43/$J$1,0) -> 318.4624 | J43: =_xlfn.IFNA(D43/$J$1,0) -> 0 | K43: =_xlfn.IFNA(E43/$J$1,0) -> 0 | L43: =_xlfn.IFNA(F43/$J$1,0) -> 0 | M43: =_xlfn.IFNA(G43/$J$1,0) -> 0 | N43: =_xlfn.IFNA(H43/$J$1,0) -> 0 | O43: =_xlfn.IFNA(C43/$P$1,0) -> 358.2702 | P43: =_xlfn.IFNA(D43/$P$1,0) -> 0 | Q43: =_xlfn.IFNA(E43/$P$1,0) -> 0 | R43: =_xlfn.IFNA(F43/$P$1,0) -> 0 | S43: =_xlfn.IFNA(G43/$P$1,0) -> 0 | T43: =_xlfn.IFNA(H43/$P$1,0) -> 0 | U43: =_xlfn.IFNA(C43/$V$1,0) -> 409.45165 | V43: =_xlfn.IFNA(D43/$V$1,0) -> 0 | W43: =_xlfn.IFNA(E43/$V$1,0) -> 0 | X43: =_xlfn.IFNA(F43/$V$1,0) -> 0 | Y43: =_xlfn.IFNA(G43/$V$1,0) -> 0 | Z43: =_xlfn.IFNA(H43/$V$1,0) -> 0 | AA43: =_xlfn.IFNA(C43/$AB$1,0) -> 477.69359 | AB43: =_xlfn.IFNA(D43/$AB$1,0) -> 0 | AC43: =_xlfn.IFNA(E43/$AB$1,0) -> 0 | AD43: =_xlfn.IFNA(F43/$AB$1,0) -> 0 | AE43: =_xlfn.IFNA(G43/$AB$1,0) -> 0 | AF43: =_xlfn.IFNA(H43/$AB$1,0) -> 0 | AG43: 48 | AM43: =_xlfn.IFNA(C43/$AN$1,0) -> 318.4624 | AN43: =_xlfn.IFNA(D43/$AN$1,0) -> 0 | AO43: =_xlfn.IFNA(E43/$AN$1,0) -> 0 | AP43: =_xlfn.IFNA(F43/$AN$1,0) -> 0 | AQ43: =_xlfn.IFNA(G43/$AN$1,0) -> 0 | AR43: =_xlfn.IFNA(H43/$AN$1,0) -> 0
B44: Chocolate | C44: =Roscas!G32 -> 130.60667 | I44: =_xlfn.IFNA(C44/$J$1,0) -> 290.23704 | J44: =_xlfn.IFNA(D44/$J$1,0) -> 0 | K44: =_xlfn.IFNA(E44/$J$1,0) -> 0 | L44: =_xlfn.IFNA(F44/$J$1,0) -> 0 | M44: =_xlfn.IFNA(G44/$J$1,0) -> 0 | N44: =_xlfn.IFNA(H44/$J$1,0) -> 0 | O44: =_xlfn.IFNA(C44/$P$1,0) -> 326.51667 | P44: =_xlfn.IFNA(D44/$P$1,0) -> 0 | Q44: =_xlfn.IFNA(E44/$P$1,0) -> 0 | R44: =_xlfn.IFNA(F44/$P$1,0) -> 0 | S44: =_xlfn.IFNA(G44/$P$1,0) -> 0 | T44: =_xlfn.IFNA(H44/$P$1,0) -> 0 | U44: =_xlfn.IFNA(C44/$V$1,0) -> 373.1619 | V44: =_xlfn.IFNA(D44/$V$1,0) -> 0 | W44: =_xlfn.IFNA(E44/$V$1,0) -> 0 | X44: =_xlfn.IFNA(F44/$V$1,0) -> 0 | Y44: =_xlfn.IFNA(G44/$V$1,0) -> 0 | Z44: =_xlfn.IFNA(H44/$V$1,0) -> 0 | AA44: =_xlfn.IFNA(C44/$AB$1,0) -> 435.35556 | AB44: =_xlfn.IFNA(D44/$AB$1,0) -> 0 | AC44: =_xlfn.IFNA(E44/$AB$1,0) -> 0 | AD44: =_xlfn.IFNA(F44/$AB$1,0) -> 0 | AE44: =_xlfn.IFNA(G44/$AB$1,0) -> 0 | AF44: =_xlfn.IFNA(H44/$AB$1,0) -> 0 | AG44: 30 | AM44: =_xlfn.IFNA(C44/$AN$1,0) -> 290.23704 | AN44: =_xlfn.IFNA(D44/$AN$1,0) -> 0 | AO44: =_xlfn.IFNA(E44/$AN$1,0) -> 0 | AP44: =_xlfn.IFNA(F44/$AN$1,0) -> 0 | AQ44: =_xlfn.IFNA(G44/$AN$1,0) -> 0 | AR44: =_xlfn.IFNA(H44/$AN$1,0) -> 0
B45: Fresas con Crema | C45: =Roscas!C32 -> 115.05403 | I45: =_xlfn.IFNA(C45/$J$1,0) -> 255.67563 | J45: =_xlfn.IFNA(D45/$J$1,0) -> 0 | K45: =_xlfn.IFNA(E45/$J$1,0) -> 0 | L45: =_xlfn.IFNA(F45/$J$1,0) -> 0 | M45: =_xlfn.IFNA(G45/$J$1,0) -> 0 | N45: =_xlfn.IFNA(H45/$J$1,0) -> 0 | O45: =_xlfn.IFNA(C45/$P$1,0) -> 287.63508 | P45: =_xlfn.IFNA(D45/$P$1,0) -> 0 | Q45: =_xlfn.IFNA(E45/$P$1,0) -> 0 | R45: =_xlfn.IFNA(F45/$P$1,0) -> 0 | S45: =_xlfn.IFNA(G45/$P$1,0) -> 0 | T45: =_xlfn.IFNA(H45/$P$1,0) -> 0 | U45: =_xlfn.IFNA(C45/$V$1,0) -> 328.72581 | V45: =_xlfn.IFNA(D45/$V$1,0) -> 0 | W45: =_xlfn.IFNA(E45/$V$1,0) -> 0 | X45: =_xlfn.IFNA(F45/$V$1,0) -> 0 | Y45: =_xlfn.IFNA(G45/$V$1,0) -> 0 | Z45: =_xlfn.IFNA(H45/$V$1,0) -> 0 | AA45: =_xlfn.IFNA(C45/$AB$1,0) -> 383.51345 | AB45: =_xlfn.IFNA(D45/$AB$1,0) -> 0 | AC45: =_xlfn.IFNA(E45/$AB$1,0) -> 0 | AD45: =_xlfn.IFNA(F45/$AB$1,0) -> 0 | AE45: =_xlfn.IFNA(G45/$AB$1,0) -> 0 | AF45: =_xlfn.IFNA(H45/$AB$1,0) -> 0 | AG45: 30 | AM45: =_xlfn.IFNA(C45/$AN$1,0) -> 255.67563 | AN45: =_xlfn.IFNA(D45/$AN$1,0) -> 0 | AO45: =_xlfn.IFNA(E45/$AN$1,0) -> 0 | AP45: =_xlfn.IFNA(F45/$AN$1,0) -> 0 | AQ45: =_xlfn.IFNA(G45/$AN$1,0) -> 0 | AR45: =_xlfn.IFNA(H45/$AN$1,0) -> 0
B46: Lotus | C46: =Roscas!S32 -> 196.87982 | I46: =_xlfn.IFNA(C46/$J$1,0) -> 437.5107 | J46: =_xlfn.IFNA(D46/$J$1,0) -> 0 | K46: =_xlfn.IFNA(E46/$J$1,0) -> 0 | L46: =_xlfn.IFNA(F46/$J$1,0) -> 0 | M46: =_xlfn.IFNA(G46/$J$1,0) -> 0 | N46: =_xlfn.IFNA(H46/$J$1,0) -> 0 | O46: =_xlfn.IFNA(C46/$P$1,0) -> 492.19954 | P46: =_xlfn.IFNA(D46/$P$1,0) -> 0 | Q46: =_xlfn.IFNA(E46/$P$1,0) -> 0 | R46: =_xlfn.IFNA(F46/$P$1,0) -> 0 | S46: =_xlfn.IFNA(G46/$P$1,0) -> 0 | T46: =_xlfn.IFNA(H46/$P$1,0) -> 0 | U46: =_xlfn.IFNA(C46/$V$1,0) -> 562.51376 | V46: =_xlfn.IFNA(D46/$V$1,0) -> 0 | W46: =_xlfn.IFNA(E46/$V$1,0) -> 0 | X46: =_xlfn.IFNA(F46/$V$1,0) -> 0 | Y46: =_xlfn.IFNA(G46/$V$1,0) -> 0 | Z46: =_xlfn.IFNA(H46/$V$1,0) -> 0 | AA46: =_xlfn.IFNA(C46/$AB$1,0) -> 656.26606 | AB46: =_xlfn.IFNA(D46/$AB$1,0) -> 0 | AC46: =_xlfn.IFNA(E46/$AB$1,0) -> 0 | AD46: =_xlfn.IFNA(F46/$AB$1,0) -> 0 | AE46: =_xlfn.IFNA(G46/$AB$1,0) -> 0 | AF46: =_xlfn.IFNA(H46/$AB$1,0) -> 0 | AG46: 32 | AM46: =_xlfn.IFNA(C46/$AN$1,0) -> 437.5107 | AN46: =_xlfn.IFNA(D46/$AN$1,0) -> 0 | AO46: =_xlfn.IFNA(E46/$AN$1,0) -> 0 | AP46: =_xlfn.IFNA(F46/$AN$1,0) -> 0 | AQ46: =_xlfn.IFNA(G46/$AN$1,0) -> 0 | AR46: =_xlfn.IFNA(H46/$AN$1,0) -> 0
I47: =_xlfn.IFNA(C47/$J$1,0) -> 0 | J47: =_xlfn.IFNA(D47/$J$1,0) -> 0 | K47: =_xlfn.IFNA(E47/$J$1,0) -> 0 | L47: =_xlfn.IFNA(F47/$J$1,0) -> 0 | M47: =_xlfn.IFNA(G47/$J$1,0) -> 0 | N47: =_xlfn.IFNA(H47/$J$1,0) -> 0 | O47: =_xlfn.IFNA(C47/$P$1,0) -> 0 | P47: =_xlfn.IFNA(D47/$P$1,0) -> 0 | Q47: =_xlfn.IFNA(E47/$P$1,0) -> 0 | R47: =_xlfn.IFNA(F47/$P$1,0) -> 0 | S47: =_xlfn.IFNA(G47/$P$1,0) -> 0 | T47: =_xlfn.IFNA(H47/$P$1,0) -> 0 | U47: =_xlfn.IFNA(C47/$V$1,0) -> 0 | V47: =_xlfn.IFNA(D47/$V$1,0) -> 0 | W47: =_xlfn.IFNA(E47/$V$1,0) -> 0 | X47: =_xlfn.IFNA(F47/$V$1,0) -> 0 | Y47: =_xlfn.IFNA(G47/$V$1,0) -> 0 | Z47: =_xlfn.IFNA(H47/$V$1,0) -> 0 | AA47: =_xlfn.IFNA(C47/$AB$1,0) -> 0 | AB47: =_xlfn.IFNA(D47/$AB$1,0) -> 0 | AC47: =_xlfn.IFNA(E47/$AB$1,0) -> 0 | AD47: =_xlfn.IFNA(F47/$AB$1,0) -> 0 | AE47: =_xlfn.IFNA(G47/$AB$1,0) -> 0 | AF47: =_xlfn.IFNA(H47/$AB$1,0) -> 0 | AM47: =_xlfn.IFNA(C47/$AN$1,0) -> 0 | AN47: =_xlfn.IFNA(D47/$AN$1,0) -> 0 | AO47: =_xlfn.IFNA(E47/$AN$1,0) -> 0 | AP47: =_xlfn.IFNA(F47/$AN$1,0) -> 0 | AQ47: =_xlfn.IFNA(G47/$AN$1,0) -> 0 | AR47: =_xlfn.IFNA(H47/$AN$1,0) -> 0
C49: Individual | D49: Mini | E49: Chico | F49: Mediano | G49: Grande | H49: Rebanada | I49: Individual | J49: Mini | K49: Chico | L49: Mediano | M49: Grande | N49: Rebanada | O49: Individual | P49: Mini | Q49: Chico | R49: Mediano | S49: Grande | T49: Rebanada | U49: Individual | V49: Mini | W49: Chico | X49: Mediano | Y49: Grande | Z49: Rebanada | AA49: Individual | AB49: Mini | AC49: Chico | AD49: Mediano | AE49: Grande | AF49: Rebanada | AG49: Individual | AH49: Mini | AI49: Chico | AJ49: Mediano | AK49: Grande | AL49: Rebanada | AM49: Individual | AN49: Mini | AO49: Chico | AP49: Mediano | AQ49: Grande | AR49: Rebanada
A50: Promedio | B50: Pastel | C50: 0 | D50: =AVERAGE(D10,D11,D13,D14) -> 68.724739 | E50: =AVERAGE(E10:E12,E14:E15) -> 164.66064 | F50: =AVERAGE(F10:F12,F14:F17) -> 220.88223 | G50: =AVERAGE(G10:G12,G14:G17) -> 350.48547 | H50: =AVERAGE(H10:H12,H14:H17) -> 25.737577 | I50: =_xlfn.IFNA(C50/$J$1,0) -> 0 | J50: =_xlfn.IFNA(D50/$J$1,0) -> 152.72164 | K50: =_xlfn.IFNA(E50/$J$1,0) -> 365.91253 | L50: =_xlfn.IFNA(F50/$J$1,0) -> 490.8494 | M50: =_xlfn.IFNA(G50/$J$1,0) -> 778.8566 | N50: =_xlfn.IFNA(H50/$J$1,0) -> 57.194616 | O50: =_xlfn.IFNA(C50/$P$1,0) -> 0 | P50: =_xlfn.IFNA(D50/$P$1,0) -> 171.81185 | Q50: =_xlfn.IFNA(E50/$P$1,0) -> 411.65159 | R50: =_xlfn.IFNA(F50/$P$1,0) -> 552.20557 | S50: =_xlfn.IFNA(G50/$P$1,0) -> 876.21368 | T50: =_xlfn.IFNA(H50/$P$1,0) -> 64.343943 | U50: =_xlfn.IFNA(C50/$V$1,0) -> 0 | V50: =_xlfn.IFNA(D50/$V$1,0) -> 196.3564 | W50: =_xlfn.IFNA(E50/$V$1,0) -> 470.45896 | X50: =_xlfn.IFNA(F50/$V$1,0) -> 631.09208 | Y50: =_xlfn.IFNA(G50/$V$1,0) -> 1001.3871 | Z50: =_xlfn.IFNA(H50/$V$1,0) -> 73.535935 | AA50: =_xlfn.IFNA(C50/$AB$1,0) -> 0 | AB50: =_xlfn.IFNA(D50/$AB$1,0) -> 229.08246 | AC50: =_xlfn.IFNA(E50/$AB$1,0) -> 548.86879 | AD50: =_xlfn.IFNA(F50/$AB$1,0) -> 736.2741 | AE50: =_xlfn.IFNA(G50/$AB$1,0) -> 1168.2849 | AF50: =_xlfn.IFNA(H50/$AB$1,0) -> 85.791924 | AM50: =_xlfn.IFNA(AG50/$J$1,0) -> 0 | AN50: =_xlfn.IFNA(AH50/$J$1,0) -> 0 | AO50: =_xlfn.IFNA(AI50/$J$1,0) -> 0 | AP50: =_xlfn.IFNA(AJ50/$J$1,0) -> 0 | AQ50: =_xlfn.IFNA(AK50/$J$1,0) -> 0 | AR50: =_xlfn.IFNA(AL50/$J$1,0) -> 0
B51: Pay | C51: =AVERAGE(C3:C6) -> 19.176338 | D51: =AVERAGE(D3:D9) -> 0 | E51: =AVERAGE(E3:E9) -> 0 | F51: =AVERAGE(F3:F5) -> 141.39691 | G51: =AVERAGE(G3:G5) -> 236.54777 | H51: =AVERAGE(H3:H5) -> 32.269112 | I51: =_xlfn.IFNA(C51/$J$1,0) -> 42.614084 | J51: =_xlfn.IFNA(D51/$J$1,0) -> 0 | K51: =_xlfn.IFNA(E51/$J$1,0) -> 0 | L51: =_xlfn.IFNA(F51/$J$1,0) -> 314.21537 | M51: =_xlfn.IFNA(G51/$J$1,0) -> 525.66172 | N51: =_xlfn.IFNA(H51/$J$1,0) -> 71.709137 | O51: =_xlfn.IFNA(C51/$P$1,0) -> 47.940845 | P51: =_xlfn.IFNA(D51/$P$1,0) -> 0 | Q51: =_xlfn.IFNA(E51/$P$1,0) -> 0 | R51: =_xlfn.IFNA(F51/$P$1,0) -> 353.49229 | S51: =_xlfn.IFNA(G51/$P$1,0) -> 591.36944 | T51: =_xlfn.IFNA(H51/$P$1,0) -> 80.67278 | U51: =_xlfn.IFNA(C51/$V$1,0) -> 54.789537 | V51: =_xlfn.IFNA(D51/$V$1,0) -> 0 | W51: =_xlfn.IFNA(E51/$V$1,0) -> 0 | X51: =_xlfn.IFNA(F51/$V$1,0) -> 403.99118 | Y51: =_xlfn.IFNA(G51/$V$1,0) -> 675.85079 | Z51: =_xlfn.IFNA(H51/$V$1,0) -> 92.197462 | AA51: =_xlfn.IFNA(C51/$AB$1,0) -> 63.921127 | AB51: =_xlfn.IFNA(D51/$AB$1,0) -> 0 | AC51: =_xlfn.IFNA(E51/$AB$1,0) -> 0 | AD51: =_xlfn.IFNA(F51/$AB$1,0) -> 471.32305 | AE51: =_xlfn.IFNA(G51/$AB$1,0) -> 788.49258 | AF51: =_xlfn.IFNA(H51/$AB$1,0) -> 107.56371 | AM51: =_xlfn.IFNA(AG51/$J$1,0) -> 0 | AN51: =_xlfn.IFNA(AH51/$J$1,0) -> 0 | AO51: =_xlfn.IFNA(AI51/$J$1,0) -> 0 | AP51: =_xlfn.IFNA(AJ51/$J$1,0) -> 0 | AQ51: =_xlfn.IFNA(AK51/$J$1,0) -> 0 | AR51: =_xlfn.IFNA(AL51/$J$1,0) -> 0
B52: Vasos | C52: =IFERROR(AVERAGE(C20:C22),0) -> 0 | D52: =IFERROR(AVERAGE(D20:D21),0) -> 23.125881 | E52: =IFERROR(AVERAGE(E20:E22),0) -> 32.405495 | F52: =IFERROR(AVERAGE(F20:F22),0) -> 39.465763 | G52: =IFERROR(AVERAGE(G20:G21),0) -> 43.884037 | H52: =IFERROR(AVERAGE(H20:H22),0) -> 0 | I52: =_xlfn.IFNA(C52/$J$1,0) -> 0 | J52: =_xlfn.IFNA(D52/$J$1,0) -> 51.390846 | K52: =_xlfn.IFNA(E52/$J$1,0) -> 72.012211 | L52: =_xlfn.IFNA(F52/$J$1,0) -> 87.701696 | M52: =_xlfn.IFNA(G52/$J$1,0) -> 97.520081 | N52: =_xlfn.IFNA(H52/$J$1,0) -> 0 | O52: =_xlfn.IFNA(C52/$P$1,0) -> 0 | P52: =_xlfn.IFNA(D52/$P$1,0) -> 57.814702 | Q52: =_xlfn.IFNA(E52/$P$1,0) -> 81.013738 | R52: =_xlfn.IFNA(F52/$P$1,0) -> 98.664408 | S52: =_xlfn.IFNA(G52/$P$1,0) -> 109.71009 | T52: =_xlfn.IFNA(H52/$P$1,0) -> 0 | U52: =_xlfn.IFNA(C52/$V$1,0) -> 0 | V52: =_xlfn.IFNA(D52/$V$1,0) -> 66.073945 | W52: =_xlfn.IFNA(E52/$V$1,0) -> 92.587129 | X52: =_xlfn.IFNA(F52/$V$1,0) -> 112.75932 | Y52: =_xlfn.IFNA(G52/$V$1,0) -> 125.38296 | Z52: =_xlfn.IFNA(H52/$V$1,0) -> 0 | AA52: =_xlfn.IFNA(C52/$AB$1,0) -> 0 | AB52: =_xlfn.IFNA(D52/$AB$1,0) -> 77.086269 | AC52: =_xlfn.IFNA(E52/$AB$1,0) -> 108.01832 | AD52: =_xlfn.IFNA(F52/$AB$1,0) -> 131.55254 | AE52: =_xlfn.IFNA(G52/$AB$1,0) -> 146.28012 | AF52: =_xlfn.IFNA(H52/$AB$1,0) -> 0 | AM52: =_xlfn.IFNA(AG52/$J$1,0) -> 0 | AN52: =_xlfn.IFNA(AH52/$J$1,0) -> 0 | AO52: =_xlfn.IFNA(AI52/$J$1,0) -> 0 | AP52: =_xlfn.IFNA(AJ52/$J$1,0) -> 0 | AQ52: =_xlfn.IFNA(AK52/$J$1,0) -> 0 | AR52: =_xlfn.IFNA(AL52/$J$1,0) -> 0
B53: Bollos | C53: =AVERAGE(C23:C27) -> 14.795071 | D53: =AVERAGE(D23:D27) -> 0 | E53: =AVERAGE(E23:E27) -> 0 | F53: =AVERAGE(F23:F27) -> 0 | G53: =AVERAGE(G23:G27) -> 0 | H53: =AVERAGE(H23:H27) -> 0 | I53: =_xlfn.IFNA(C53/$J$1,0) -> 32.877936 | J53: =_xlfn.IFNA(D53/$J$1,0) -> 0 | K53: =_xlfn.IFNA(E53/$J$1,0) -> 0 | L53: =_xlfn.IFNA(F53/$J$1,0) -> 0 | M53: =_xlfn.IFNA(G53/$J$1,0) -> 0 | N53: =_xlfn.IFNA(H53/$J$1,0) -> 0 | O53: =_xlfn.IFNA(C53/$P$1,0) -> 36.987678 | P53: =_xlfn.IFNA(D53/$P$1,0) -> 0 | Q53: =_xlfn.IFNA(E53/$P$1,0) -> 0 | R53: =_xlfn.IFNA(F53/$P$1,0) -> 0 | S53: =_xlfn.IFNA(G53/$P$1,0) -> 0 | T53: =_xlfn.IFNA(H53/$P$1,0) -> 0 | U53: =_xlfn.IFNA(C53/$V$1,0) -> 42.271632 | V53: =_xlfn.IFNA(D53/$V$1,0) -> 0 | W53: =_xlfn.IFNA(E53/$V$1,0) -> 0 | X53: =_xlfn.IFNA(F53/$V$1,0) -> 0 | Y53: =_xlfn.IFNA(G53/$V$1,0) -> 0 | Z53: =_xlfn.IFNA(H53/$V$1,0) -> 0 | AA53: =_xlfn.IFNA(C53/$AB$1,0) -> 49.316904 | AB53: =_xlfn.IFNA(D53/$AB$1,0) -> 0 | AC53: =_xlfn.IFNA(E53/$AB$1,0) -> 0 | AD53: =_xlfn.IFNA(F53/$AB$1,0) -> 0 | AE53: =_xlfn.IFNA(G53/$AB$1,0) -> 0 | AF53: =_xlfn.IFNA(H53/$AB$1,0) -> 0 | AM53: =_xlfn.IFNA(AG53/$J$1,0) -> 0 | AN53: =_xlfn.IFNA(AH53/$J$1,0) -> 0 | AO53: =_xlfn.IFNA(AI53/$J$1,0) -> 0 | AP53: =_xlfn.IFNA(AJ53/$J$1,0) -> 0 | AQ53: =_xlfn.IFNA(AK53/$J$1,0) -> 0 | AR53: =_xlfn.IFNA(AL53/$J$1,0) -> 0
AG54: COMPETENCIAS - ANALISIS 2025
AH55: Rango de precios
AG56: Presentación/Empresa | AH56: LA REBANADA | AI56: GINA | AJ56: EL PECADO
AG57: Pastel Grande | AH57: 480 - 450 | AI57: 640 - 700 | AJ57: 730 -800
AG58: Pastel Mediano | AH58: 420 - 390 | AI58: 420 | AJ58: 430 - 450 - 480
AG59: Pastel Chico | AH59: 350 - 320 | AI59: 320 | AJ59: 310 - 350
AG60: Pay Grande | AH60: 400 | AI60: 420 | AJ60: 400
AG61: Pay Mediano | AH61: 280 | AI61: 320 | AJ61: 300

Sheet Pastel Fresas Con Crema
A1: Costo Insumos
C2: Presentación
A3: Insumo | C3: Rebanada | D3: Individual | E3: Mini | F3: Chico | G3: Mediano | H3: Grande | J3: Dream Whip
A4: Pan | E4: ='Insumos 2'!T114 -> 12.762854 | F4: ='Insumos 2'!U114 -> 28.528732 | G4: ='Insumos 2'!V114 -> 41.291585 | H4: ='Insumos 2'!W114 -> 72.072585 | J4: Elemento | K4: Mini | L4: Chico | M4: Mediano | N4: Grande | O4: 1/2 Plancha | Q4: Producto | R4: Costo normal | S4: Costo Extra | T4: Precio de Venta | U4: Cantidad
E5: =[2]PAN!$L$15 -> 0.6959007 | F5: =[2]PAN!$L$14*2 -> 3.0619631 | G5: =[2]PAN!$L$13*2 -> 5.1032718 | H5: =[2]PAN!$L$12*2 -> 7.6549076 | J5: Cobertura | K5: 0.22 | L5: 0.45 | M5: 0.68 | N5: 0.96 | O5: 1.96
A6: Betún | E6: =K9 -> 32.426288 | F6: =L9 -> 70.411368 | G6: =M9 -> 102.83766 | H6: =N9 -> 155.64618 | J6: Relleno | K6: 0.07 | L6: 0.17 | M6: 0.23 | N6: 0.42 | O6: 0.7 | Q6: Fresas con crema | R6: =H12 -> 338.61711 | S6: =H12+N5*'Insumos 1'!$G$13 -> 427.55779 | T6: 660 | U6: 2
B7: =[2]INSUMOS!$K$14 -> 1.0924758 | E7: =$B$7*K8 -> 0.38236654 | F7: =$B$7*L8 -> 0.83028163 | G7: =$B$7*M8 -> 1.2126482 | H7: =$B$7*N8 -> 1.8353594 | J7: Decorado | K7: 0.06 | L7: 0.14 | M7: 0.2 | N7: 0.3 | O7: 2.66 | Q7: 3 Pecados | R7: ='Pastel 3 Pecados'!H18 -> 350.57494 | S7: =R7+'Pastel 3 Pecados'!N5*'Insumos 1'!$G$13 -> 451.55967 | T7: 660 | U7: 2
A8: Fresa | E8: =K15 -> 7.2082895 | F8: =L15 -> 11.71347 | G8: =M15 -> 18.020724 | H8: =N15 -> 36.041448 | J8: Total | K8: =SUM(K5:K7) -> 0.35 | L8: =SUM(L5:L7) -> 0.76 | M8: =SUM(M5:M7) -> 1.11 | N8: =SUM(N5:N7) -> 1.68 | O8: =SUM(O5:O7) -> 5.32
A9: Mermelada | E9: =K21 -> 6.90625 | F9: =L21 -> 15.347222 | G9: =M21 -> 19.951389 | H9: =N21 -> 30.694444 | J9: Total por decorar | K9: =K8*'Insumos 1'!$G$13 -> 32.426288 | L9: =L8*'Insumos 1'!$G$13 -> 70.411368 | M9: =M8*'Insumos 1'!$G$13 -> 102.83766 | N9: =N8*'Insumos 1'!$G$13 -> 155.64618 | O9: =O8*'Insumos 1'!$G$13 -> 492.87958
A10: Armado | E10: ='[2]ARMADO- EMBETUNADO'!$G$9 -> 6.0976752 | F10: ='[2]ARMADO- EMBETUNADO'!$G$9 -> 6.0976752 | G10: ='[2]ARMADO- EMBETUNADO'!$G$9 -> 6.0976752 | H10: ='[2]ARMADO- EMBETUNADO'!$G$9 -> 6.0976752 | J10: Fresa Fresca
A11: Presentación | C11: ='Insumos 3'!S8 -> 2.80714 | E11: ='Insumos 3'!O8 -> 11.486 | F11: ='Insumos 3'!K8 -> 13.62849 | G11: ='Insumos 3'!G8 -> 15.5984 | H11: ='Insumos 3'!C7 -> 28.57451 | J11: Elemento | K11: Mini | L11: Chico | M11: Mediano | N11: Grande | O11: 1/2 Plancha | Q11: Dream whip | T11: San Valentín- Fresas Con Crema
A12: Subtotal 1 | C12: =SUM(C4:C11)+(G12/10) -> 23.818475 | D12: =SUM(D4:D11) -> 0 | E12: =SUM(E4:E11) -> 77.965623 | F12: =SUM(F4:F11) -> 149.6192 | G12: =SUM(G4:G11) -> 210.11335 | H12: =SUM(H4:H11) -> 338.61711 | J12: Exterior | K12: 0.08 | L12: 0.13 | M12: 0.2 | N12: 0.4 | O12: 0.4 | Q12: Elemento | R12: Mini | U12: Mini
A13: Costo sin M.O. | C13: =SUM(C4:C11)+(G13/10) -> 22.577115 | E13: =E12-E10-E7-E5 -> 70.789681 | F13: =F12-F10-F7-F5 -> 139.62928 | G13: =G12-G10-G7-G5 -> 197.69975 | H13: =H12-H10-H7-H5 -> 323.02917 | J13: Relleno | O13: 0.35 | Q13: Cobertura | R13: 0.225 | T13: Insumo
J14: Total Fresa | K14: =SUM(K12:K13) -> 0.08 | L14: =SUM(L12:L13) -> 0.13 | M14: =SUM(M12:M13) -> 0.2 | N14: =SUM(N12:N13) -> 0.4 | O14: =SUM(O12:O13) -> 0.75 | Q14: Relleno | R14: 0.07 | T14: Pan | U14: ='Insumos 2'!T114 -> 12.762854
J15: Total por decorar | K15: =K14*'Costo Materia Prima'!$I$18 -> 7.2082895 | L15: =L14*'Costo Materia Prima'!$I$18 -> 11.71347 | M15: =M14*'Costo Materia Prima'!$I$18 -> 18.020724 | N15: =N14*'Costo Materia Prima'!$I$18 -> 36.041448 | O15: =O14*'Costo Materia Prima'!$I$18 -> 67.577714 | Q15: Decorado | R15: 0 | U15: =[2]PAN!$L$15 -> 0.6959007
J16: Mermelada de Fresa | Q16: Total | R16: =SUM(R13:R15) -> 0.295 | T16: Betún | U16: =R17 -> 27.330728
J17: Elemento | K17: Mini | L17: Chico | M17: Mediano | N17: Grande | O17: 1/2 Plancha | Q17: Total por decorar | R17: =R16*'Insumos 1'!$G$13 -> 27.330728 | U17: =$B$7*R16 -> 0.32228037
J18: Cobertura | K18: 0.05 | L18: 0.1 | M18: 0.13 | N18: 0.2 | O18: 0.4 | T18: Fondant | U18: =R33 -> 0
J19: Relleno | K19: 0.04 | L19: 0.1 | M19: 0.13 | N19: 0.2 | O19: 0.2 | Q19: Mermelada de Fresa | T19: Mermelada | U19: =R23 -> 5.3715278
J20: Total Fresa | K20: =SUM(K18:K19) -> 0.09 | L20: =SUM(L18:L19) -> 0.2 | M20: =SUM(M18:M19) -> 0.26 | N20: =SUM(N18:N19) -> 0.4 | O20: =SUM(O18:O19) -> 0.6 | Q20: Elemento | R20: Mini | T20: Armado | U20: ='[2]ARMADO- EMBETUNADO'!$G$9 -> 6.0976752
J21: Total por decorar | K21: =K20*'Costo Materia Prima'!$I$11 -> 6.90625 | L21: =L20*'Costo Materia Prima'!$I$11 -> 15.347222 | M21: =M20*'Costo Materia Prima'!$I$11 -> 19.951389 | N21: =N20*'Costo Materia Prima'!$I$11 -> 30.694444 | O21: =O20*'Insumos 1'!$G$71 -> 7.3406854 | Q21: Relleno | R21: 0.07 | T21: Presentación | U21: ='Insumos 3'!O8 -> 11.486
J22: Baño de 3 Leches | Q22: Total Fresa | R22: =SUM(R21:R21) -> 0.07 | T22: Subtotal 1 | U22: =SUM(U14:U21) -> 64.066966
J23: Elemento | K23: Mini | L23: Chico | M23: Mediano | N23: Grande | O23: 1/2 Plancha | Q23: Total por decorar | R23: =R22*'Costo Materia Prima'!$I$11 -> 5.3715278 | T23: Costo sin M.O. | U23: =U22-U15-U17-U20 -> 56.95111
J24: Baño 2 panes | K24: =0.04*2 -> 0.08 | L24: =0.08*2 -> 0.16 | M24: =0.1*2 -> 0.2 | N24: =0.13*2 -> 0.26 | O24: 0.8
J25: Total por decorar | K25: =K24*'Insumos 1'!$G$32 -> 3.161176 | L25: =L24*'Insumos 1'!$G$32 -> 6.322352 | M25: =M24*'Insumos 1'!$G$32 -> 7.90294 | N25: =N24*'Insumos 1'!$G$32 -> 10.273822 | O25: =O24*'Insumos 1'!$G$32 -> 31.61176 | Q25: Baño de 3 Leches | U25: =U22/(1-0.5) -> 128.13393
Q26: Elemento | R26: Mini | U26: 195
Q27: Baño 2 panes | R27: =0.04*2 -> 0.08
Q28: Total por decorar | R28: =R27*'Insumos 1'!$G$32 -> 3.161176
Q30: Fondant
Q31: Elemento | R31: Mini
Q32: Corazones | R32: =12/1000 -> 0.012
Q33: Total por decorar | R33: =R32*'Costo Materia Prima'!I181 -> 0

Sheet Lista de Precio Actual
I1: Precio Ajustado | J1: 0.45 | O1: Mínimo de margen | P1: 0.4 | U1: Buen margen | V1: 0.35 | AA1: Mejor margen | AB1: 0.3 | AG1: Precio Propuesto
C2: Individual | D2: Mini | E2: Chico | F2: Mediano | G2: Grande | H2: Rebanada | I2: Individual | J2: Mini | K2: Chico | L2: Mediano | M2: Grande | N2: Rebanada | O2: Individual | P2: Mini | Q2: Chico | R2: Mediano | S2: Grande | T2: Rebanada | U2: Individual | V2: Mini | W2: Chico | X2: Mediano | Y2: Grande | Z2: Rebanada | AA2: Individual | AB2: Mini | AC2: Chico | AD2: Mediano | AE2: Grande | AF2: Rebanada | AG2: Individual | AH2: Mini | AI2: Chico | AJ2: Mediano | AK2: Grande | AL2: Rebanada
A3: Pay | B3: Fresa | C3: 0 | D3: 0 | E3: 0 | F3: 395 | G3: 495 | H3: 70 | I3: =_xlfn.IFNA(C3/$J$1,0) -> 0 | J3: =_xlfn.IFNA(D3/$J$1,0) -> 0 | K3: =_xlfn.IFNA(E3/$J$1,0) -> 0 | L3: =_xlfn.IFNA(F3/$J$1,0) -> 877.77778 | M3: =_xlfn.IFNA(G3/$J$1,0) -> 1100 | N3: =_xlfn.IFNA(H3/$J$1,0) -> 155.55556 | O3: =_xlfn.IFNA(C3/$P$1,0) -> 0 | P3: =_xlfn.IFNA(D3/$P$1,0) -> 0 | Q3: =_xlfn.IFNA(E3/$P$1,0) -> 0 | R3: =_xlfn.IFNA(F3/$P$1,0) -> 987.5 | S3: =_xlfn.IFNA(G3/$P$1,0) -> 1237.5 | T3: =_xlfn.IFNA(H3/$P$1,0) -> 175 | U3: =_xlfn.IFNA(C3/$V$1,0) -> 0 | V3: =_xlfn.IFNA(D3/$V$1,0) -> 0 | W3: =_xlfn.IFNA(E3/$V$1,0) -> 0 | X3: =_xlfn.IFNA(F3/$V$1,0) -> 1128.5714 | Y3: =_xlfn.IFNA(G3/$V$1,0) -> 1414.2857 | Z3: =_xlfn.IFNA(H3/$V$1,0) -> 200 | AA3: =_xlfn.IFNA(C3/$AB$1,0) -> 0 | AB3: =_xlfn.IFNA(D3/$AB$1,0) -> 0 | AC3: =_xlfn.IFNA(E3/$AB$1,0) -> 0 | AD3: =_xlfn.IFNA(F3/$AB$1,0) -> 1316.6667 | AE3: =_xlfn.IFNA(G3/$AB$1,0) -> 1650 | AF3: =_xlfn.IFNA(H3/$AB$1,0) -> 233.33333 | AG3: 55 | AJ3: 395 | AK3: 495 | AL3: 70
B4: Guayaba | C4: 0 | D4: 0 | E4: 0 | F4: 380 | G4: 475 | H4: 70 | I4: =_xlfn.IFNA(C4/$J$1,0) -> 0 | J4: =_xlfn.IFNA(D4/$J$1,0) -> 0 | K4: =_xlfn.IFNA(E4/$J$1,0) -> 0 | L4: =_xlfn.IFNA(F4/$J$1,0) -> 844.44444 | M4: =_xlfn.IFNA(G4/$J$1,0) -> 1055.5556 | N4: =_xlfn.IFNA(H4/$J$1,0) -> 155.55556 | O4: =_xlfn.IFNA(C4/$P$1,0) -> 0 | P4: =_xlfn.IFNA(D4/$P$1,0) -> 0 | Q4: =_xlfn.IFNA(E4/$P$1,0) -> 0 | R4: =_xlfn.IFNA(F4/$P$1,0) -> 950 | S4: =_xlfn.IFNA(G4/$P$1,0) -> 1187.5 | T4: =_xlfn.IFNA(H4/$P$1,0) -> 175 | U4: =_xlfn.IFNA(C4/$V$1,0) -> 0 | V4: =_xlfn.IFNA(D4/$V$1,0) -> 0 | W4: =_xlfn.IFNA(E4/$V$1,0) -> 0 | X4: =_xlfn.IFNA(F4/$V$1,0) -> 1085.7143 | Y4: =_xlfn.IFNA(G4/$V$1,0) -> 1357.1429 | Z4: =_xlfn.IFNA(H4/$V$1,0) -> 200 | AA4: =_xlfn.IFNA(C4/$AB$1,0) -> 0 | AB4: =_xlfn.IFNA(D4/$AB$1,0) -> 0 | AC4: =_xlfn.IFNA(E4/$AB$1,0) -> 0 | AD4: =_xlfn.IFNA(F4/$AB$1,0) -> 1266.6667 | AE4: =_xlfn.IFNA(G4/$AB$1,0) -> 1583.3333 | AF4: =_xlfn.IFNA(H4/$AB$1,0) -> 233.33333 | AG4: 55 | AJ4: 380 | AK4: 475 | AL4: 70
B5: Galleta con cajeta | C5: 0 | D5: 0 | E5: 0 | F5: 370 | G5: 475 | H5: 70 | I5: =_xlfn.IFNA(C5/$J$1,0) -> 0 | J5: =_xlfn.IFNA(D5/$J$1,0) -> 0 | K5: =_xlfn.IFNA(E5/$J$1,0) -> 0 | L5: =_xlfn.IFNA(F5/$J$1,0) -> 822.22222 | M5: =_xlfn.IFNA(G5/$J$1,0) -> 1055.5556 | N5: =_xlfn.IFNA(H5/$J$1,0) -> 155.55556 | O5: =_xlfn.IFNA(C5/$P$1,0) -> 0 | P5: =_xlfn.IFNA(D5/$P$1,0) -> 0 | Q5: =_xlfn.IFNA(E5/$P$1,0) -> 0 | R5: =_xlfn.IFNA(F5/$P$1,0) -> 925 | S5: =_xlfn.IFNA(G5/$P$1,0) -> 1187.5 | T5: =_xlfn.IFNA(H5/$P$1,0) -> 175 | U5: =_xlfn.IFNA(C5/$V$1,0) -> 0 | V5: =_xlfn.IFNA(D5/$V$1,0) -> 0 | W5: =_xlfn.IFNA(E5/$V$1,0) -> 0 | X5: =_xlfn.IFNA(F5/$V$1,0) -> 1057.1429 | Y5: =_xlfn.IFNA(G5/$V$1,0) -> 1357.1429 | Z5: =_xlfn.IFNA(H5/$V$1,0) -> 200 | AA5: =_xlfn.IFNA(C5/$AB$1,0) -> 0 | AB5: =_xlfn.IFNA(D5/$AB$1,0) -> 0 | AC5: =_xlfn.IFNA(E5/$AB$1,0) -> 0 | AD5: =_xlfn.IFNA(F5/$AB$1,0) -> 1233.3333 | AE5: =_xlfn.IFNA(G5/$AB$1,0) -> 1583.3333 | AF5: =_xlfn.IFNA(H5/$AB$1,0) -> 233.33333 | AG5: 55 | AJ5: 370 | AK5: 475 | AL5: 70
B7: Pay horneado | C7: =Pay!C58 -> 0 | D7: 0 | E7: 0 | F7: =Pay!D58 -> 86.851881 | G7: =Pay!E58 -> 148.87704 | H7: =Pay!F58 -> 21.310271 | I7: =_xlfn.IFNA(C7/$J$1,0) -> 0 | J7: =_xlfn.IFNA(D7/$J$1,0) -> 0 | K7: =_xlfn.IFNA(E7/$J$1,0) -> 0 | L7: =_xlfn.IFNA(F7/$J$1,0) -> 193.00418 | M7: =_xlfn.IFNA(G7/$J$1,0) -> 330.83788 | N7: =_xlfn.IFNA(H7/$J$1,0) -> 47.356157 | O7: =_xlfn.IFNA(C7/$P$1,0) -> 0 | P7: =_xlfn.IFNA(D7/$P$1,0) -> 0 | Q7: =_xlfn.IFNA(E7/$P$1,0) -> 0 | R7: =_xlfn.IFNA(F7/$P$1,0) -> 217.1297 | S7: =_xlfn.IFNA(G7/$P$1,0) -> 372.19261 | T7: =_xlfn.IFNA(H7/$P$1,0) -> 53.275676 | U7: =_xlfn.IFNA(C7/$V$1,0) -> 0 | V7: =_xlfn.IFNA(D7/$V$1,0) -> 0 | W7: =_xlfn.IFNA(E7/$V$1,0) -> 0 | X7: =_xlfn.IFNA(F7/$V$1,0) -> 248.14823 | Y7: =_xlfn.IFNA(G7/$V$1,0) -> 425.36298 | Z7: =_xlfn.IFNA(H7/$V$1,0) -> 60.886487 | AA7: =_xlfn.IFNA(C7/$AB$1,0) -> 0 | AB7: =_xlfn.IFNA(D7/$AB$1,0) -> 0 | AC7: =_xlfn.IFNA(E7/$AB$1,0) -> 0 | AD7: =_xlfn.IFNA(F7/$AB$1,0) -> 289.50627 | AE7: =_xlfn.IFNA(G7/$AB$1,0) -> 496.25681 | AF7: =_xlfn.IFNA(H7/$AB$1,0) -> 71.034235 | AG7: 45 | AL7: 60
B8: Pay de queso | C8: =Pay!C59 -> 0 | D8: 0 | E8: 0 | F8: =Pay!D59 -> 115.18762 | G8: =Pay!E59 -> 195.44594 | H8: =Pay!F59 -> 27.131383 | I8: =_xlfn.IFNA(C8/$J$1,0) -> 0 | J8: =_xlfn.IFNA(D8/$J$1,0) -> 0 | K8: =_xlfn.IFNA(E8/$J$1,0) -> 0 | L8: =_xlfn.IFNA(F8/$J$1,0) -> 255.97249 | M8: =_xlfn.IFNA(G8/$J$1,0) -> 434.32432 | N8: =_xlfn.IFNA(H8/$J$1,0) -> 60.291962 | O8: =_xlfn.IFNA(C8/$P$1,0) -> 0 | P8: =_xlfn.IFNA(D8/$P$1,0) -> 0 | Q8: =_xlfn.IFNA(E8/$P$1,0) -> 0 | R8: =_xlfn.IFNA(F8/$P$1,0) -> 287.96905 | S8: =_xlfn.IFNA(G8/$P$1,0) -> 488.61486 | T8: =_xlfn.IFNA(H8/$P$1,0) -> 67.828458 | U8: =_xlfn.IFNA(C8/$V$1,0) -> 0 | V8: =_xlfn.IFNA(D8/$V$1,0) -> 0 | W8: =_xlfn.IFNA(E8/$V$1,0) -> 0 | X8: =_xlfn.IFNA(F8/$V$1,0) -> 329.10749 | Y8: =_xlfn.IFNA(G8/$V$1,0) -> 558.41698 | Z8: =_xlfn.IFNA(H8/$V$1,0) -> 77.518237 | AA8: =_xlfn.IFNA(C8/$AB$1,0) -> 0 | AB8: =_xlfn.IFNA(D8/$AB$1,0) -> 0 | AC8: =_xlfn.IFNA(E8/$AB$1,0) -> 0 | AD8: =_xlfn.IFNA(F8/$AB$1,0) -> 383.95874 | AE8: =_xlfn.IFNA(G8/$AB$1,0) -> 651.48648 | AF8: =_xlfn.IFNA(H8/$AB$1,0) -> 90.437944 | AG8: 50 | AL8: 65
A9: Pastel | B9: Fresas con Crema | C9: ='Pastel Fresas Con Crema'!D12 -> 0 | D9: 185 | E9: 335 | F9: 490 | G9: 700 | H9: 70 | I9: =_xlfn.IFNA(C9/$J$1,0) -> 0 | J9: =_xlfn.IFNA(D9/$J$1,0) -> 411.11111 | K9: =_xlfn.IFNA(E9/$J$1,0) -> 744.44444 | L9: =_xlfn.IFNA(F9/$J$1,0) -> 1088.8889 | M9: =_xlfn.IFNA(G9/$J$1,0) -> 1555.5556 | N9: =_xlfn.IFNA(H9/$J$1,0) -> 155.55556 | O9: =_xlfn.IFNA(C9/$P$1,0) -> 0 | P9: =_xlfn.IFNA(D9/$P$1,0) -> 462.5 | Q9: =_xlfn.IFNA(E9/$P$1,0) -> 837.5 | R9: =_xlfn.IFNA(F9/$P$1,0) -> 1225 | S9: =_xlfn.IFNA(G9/$P$1,0) -> 1750 | T9: =_xlfn.IFNA(H9/$P$1,0) -> 175 | U9: =_xlfn.IFNA(C9/$V$1,0) -> 0 | V9: =_xlfn.IFNA(D9/$V$1,0) -> 528.57143 | W9: =_xlfn.IFNA(E9/$V$1,0) -> 957.14286 | X9: =_xlfn.IFNA(F9/$V$1,0) -> 1400 | Y9: =_xlfn.IFNA(G9/$V$1,0) -> 2000 | Z9: =_xlfn.IFNA(H9/$V$1,0) -> 200 | AA9: =_xlfn.IFNA(C9/$AB$1,0) -> 0 | AB9: =_xlfn.IFNA(D9/$AB$1,0) -> 616.66667 | AC9: =_xlfn.IFNA(E9/$AB$1,0) -> 1116.6667 | AD9: =_xlfn.IFNA(F9/$AB$1,0) -> 1633.3333 | AE9: =_xlfn.IFNA(G9/$AB$1,0) -> 2333.3333 | AF9: =_xlfn.IFNA(H9/$AB$1,0) -> 233.33333 | AH9: 185 | AI9: 335 | AJ9: 490 | AK9: 700 | AL9: 70
B10: 3 Pecados | C10: 0 | D10: 185 | E10: 340 | F10: 490 | G10: 700 | H10: 70 | I10: =_xlfn.IFNA(C10/$J$1,0) -> 0 | J10: =_xlfn.IFNA(D10/$J$1,0) -> 411.11111 | K10: =_xlfn.IFNA(E10/$J$1,0) -> 755.55556 | L10: =_xlfn.IFNA(F10/$J$1,0) -> 1088.8889 | M10: =_xlfn.IFNA(G10/$J$1,0) -> 1555.5556 | N10: =_xlfn.IFNA(H10/$J$1,0) -> 155.55556 | O10: =_xlfn.IFNA(C10/$P$1,0) -> 0 | P10: =_xlfn.IFNA(D10/$P$1,0) -> 462.5 | Q10: =_xlfn.IFNA(E10/$P$1,0) -> 850 | R10: =_xlfn.IFNA(F10/$P$1,0) -> 1225 | S10: =_xlfn.IFNA(G10/$P$1,0) -> 1750 | T10: =_xlfn.IFNA(H10/$P$1,0) -> 175 | U10: =_xlfn.IFNA(C10/$V$1,0) -> 0 | V10: =_xlfn.IFNA(D10/$V$1,0) -> 528.57143 | W10: =_xlfn.IFNA(E10/$V$1,0) -> 971.42857 | X10: =_xlfn.IFNA(F10/$V$1,0) -> 1400 | Y10: =_xlfn.IFNA(G10/$V$1,0) -> 2000 | Z10: =_xlfn.IFNA(H10/$V$1,0) -> 200 | AA10: =_xlfn.IFNA(C10/$AB$1,0) -> 0 | AB10: =_xlfn.IFNA(D10/$AB$1,0) -> 616.66667 | AC10: =_xlfn.IFNA(E10/$AB$1,0) -> 1133.3333 | AD10: =_xlfn.IFNA(F10/$AB$1,0) -> 1633.3333 | AE10: =_xlfn.IFNA(G10/$AB$1,0) -> 2333.3333 | AF10: =_xlfn.IFNA(H10/$AB$1,0) -> 233.33333 | AH10: 185 | AI10: 340 | AJ10: 490 | AK10: 700 | AL10: 70
B11: Zanahoria | C11: 0 | D11: 0 | E11: 330 | F11: 440 | G11: 700 | H11: 70 | I11: =_xlfn.IFNA(C11/$J$1,0) -> 0 | J11: =_xlfn.IFNA(D11/$J$1,0) -> 0 | K11: =_xlfn.IFNA(E11/$J$1,0) -> 733.33333 | L11: =_xlfn.IFNA(F11/$J$1,0) -> 977.77778 | M11: =_xlfn.IFNA(G11/$J$1,0) -> 1555.5556 | N11: =_xlfn.IFNA(H11/$J$1,0) -> 155.55556 | O11: =_xlfn.IFNA(C11/$P$1,0) -> 0 | P11: =_xlfn.IFNA(D11/$P$1,0) -> 0 | Q11: =_xlfn.IFNA(E11/$P$1,0) -> 825 | R11: =_xlfn.IFNA(F11/$P$1,0) -> 1100 | S11: =_xlfn.IFNA(G11/$P$1,0) -> 1750 | T11: =_xlfn.IFNA(H11/$P$1,0) -> 175 | U11: =_xlfn.IFNA(C11/$V$1,0) -> 0 | V11: =_xlfn.IFNA(D11/$V$1,0) -> 0 | W11: =_xlfn.IFNA(E11/$V$1,0) -> 942.85714 | X11: =_xlfn.IFNA(F11/$V$1,0) -> 1257.1429 | Y11: =_xlfn.IFNA(G11/$V$1,0) -> 2000 | Z11: =_xlfn.IFNA(H11/$V$1,0) -> 200 | AA11: =_xlfn.IFNA(C11/$AB$1,0) -> 0 | AB11: =_xlfn.IFNA(D11/$AB$1,0) -> 0 | AC11: =_xlfn.IFNA(E11/$AB$1,0) -> 1100 | AD11: =_xlfn.IFNA(F11/$AB$1,0) -> 1466.6667 | AE11: =_xlfn.IFNA(G11/$AB$1,0) -> 2333.3333 | AF11: =_xlfn.IFNA(H11/$AB$1,0) -> 233.33333 | AI11: 330 | AJ11: 440 | AK11: 700 | AL11: 70
B12: Crunch | C12: 0 | D12: 185 | E12: 360 | F12: 490 | G12: 700 | H12: 70 | I12: =_xlfn.IFNA(C12/$J$1,0) -> 0 | J12: =_xlfn.IFNA(D12/$J$1,0) -> 411.11111 | K12: =_xlfn.IFNA(E12/$J$1,0) -> 800 | L12: =_xlfn.IFNA(F12/$J$1,0) -> 1088.8889 | M12: =_xlfn.IFNA(G12/$J$1,0) -> 1555.5556 | N12: =_xlfn.IFNA(H12/$J$1,0) -> 155.55556 | O12: =_xlfn.IFNA(C12/$P$1,0) -> 0 | P12: =_xlfn.IFNA(D12/$P$1,0) -> 462.5 | Q12: =_xlfn.IFNA(E12/$P$1,0) -> 900 | R12: =_xlfn.IFNA(F12/$P$1,0) -> 1225 | S12: =_xlfn.IFNA(G12/$P$1,0) -> 1750 | T12: =_xlfn.IFNA(H12/$P$1,0) -> 175 | U12: =_xlfn.IFNA(C12/$V$1,0) -> 0 | V12: =_xlfn.IFNA(D12/$V$1,0) -> 528.57143 | W12: =_xlfn.IFNA(E12/$V$1,0) -> 1028.5714 | X12: =_xlfn.IFNA(F12/$V$1,0) -> 1400 | Y12: =_xlfn.IFNA(G12/$V$1,0) -> 2000 | Z12: =_xlfn.IFNA(H12/$V$1,0) -> 200 | AA12: =_xlfn.IFNA(C12/$AB$1,0) -> 0 | AB12: =_xlfn.IFNA(D12/$AB$1,0) -> 616.66667 | AC12: =_xlfn.IFNA(E12/$AB$1,0) -> 1200 | AD12: =_xlfn.IFNA(F12/$AB$1,0) -> 1633.3333 | AE12: =_xlfn.IFNA(G12/$AB$1,0) -> 2333.3333 | AF12: =_xlfn.IFNA(H12/$AB$1,0) -> 233.33333 | AH12: 185 | AI12: 360 | AJ12: 490 | AK12: 720 | AL12: 70
B13: Snicker's | C13: 0 | D13: 0 | E13: 400 | F13: 500 | G13: 750 | H13: 70 | I13: =_xlfn.IFNA(C13/$J$1,0) -> 0 | J13: =_xlfn.IFNA(D13/$J$1,0) -> 0 | K13: =_xlfn.IFNA(E13/$J$1,0) -> 888.88889 | L13: =_xlfn.IFNA(F13/$J$1,0) -> 1111.1111 | M13: =_xlfn.IFNA(G13/$J$1,0) -> 1666.6667 | N13: =_xlfn.IFNA(H13/$J$1,0) -> 155.55556 | O13: =_xlfn.IFNA(C13/$P$1,0) -> 0 | P13: =_xlfn.IFNA(D13/$P$1,0) -> 0 | Q13: =_xlfn.IFNA(E13/$P$1,0) -> 1000 | R13: =_xlfn.IFNA(F13/$P$1,0) -> 1250 | S13: =_xlfn.IFNA(G13/$P$1,0) -> 1875 | T13: =_xlfn.IFNA(H13/$P$1,0) -> 175 | U13: =_xlfn.IFNA(C13/$V$1,0) -> 0 | V13: =_xlfn.IFNA(D13/$V$1,0) -> 0 | W13: =_xlfn.IFNA(E13/$V$1,0) -> 1142.8571 | X13: =_xlfn.IFNA(F13/$V$1,0) -> 1428.5714 | Y13: =_xlfn.IFNA(G13/$V$1,0) -> 2142.8571 | Z13: =_xlfn.IFNA(H13/$V$1,0) -> 200 | AA13: =_xlfn.IFNA(C13/$AB$1,0) -> 0 | AB13: =_xlfn.IFNA(D13/$AB$1,0) -> 0 | AC13: =_xlfn.IFNA(E13/$AB$1,0) -> 1333.3333 | AD13: =_xlfn.IFNA(F13/$AB$1,0) -> 1666.6667 | AE13: =_xlfn.IFNA(G13/$AB$1,0) -> 2500 | AF13: =_xlfn.IFNA(H13/$AB$1,0) -> 233.33333 | AI13: 400 | AJ13: 500 | AK13: 750 | AL13: 70
B14: Dulce de Leche | C14: 0 | D14: ='Pastel Vainilla'!E12 -> 0 | E14: 340 | F14: 450 | G14: 710 | H14: 70 | I14: =_xlfn.IFNA(C14/$J$1,0) -> 0 | J14: =_xlfn.IFNA(D14/$J$1,0) -> 0 | K14: =_xlfn.IFNA(E14/$J$1,0) -> 755.55556 | L14: =_xlfn.IFNA(F14/$J$1,0) -> 1000 | M14: =_xlfn.IFNA(G14/$J$1,0) -> 1577.7778 | N14: =_xlfn.IFNA(H14/$J$1,0) -> 155.55556 | O14: =_xlfn.IFNA(C14/$P$1,0) -> 0 | P14: =_xlfn.IFNA(D14/$P$1,0) -> 0 | Q14: =_xlfn.IFNA(E14/$P$1,0) -> 850 | R14: =_xlfn.IFNA(F14/$P$1,0) -> 1125 | S14: =_xlfn.IFNA(G14/$P$1,0) -> 1775 | T14: =_xlfn.IFNA(H14/$P$1,0) -> 175 | U14: =_xlfn.IFNA(C14/$V$1,0) -> 0 | V14: =_xlfn.IFNA(D14/$V$1,0) -> 0 | W14: =_xlfn.IFNA(E14/$V$1,0) -> 971.42857 | X14: =_xlfn.IFNA(F14/$V$1,0) -> 1285.7143 | Y14: =_xlfn.IFNA(G14/$V$1,0) -> 2028.5714 | Z14: =_xlfn.IFNA(H14/$V$1,0) -> 200 | AA14: =_xlfn.IFNA(C14/$AB$1,0) -> 0 | AB14: =_xlfn.IFNA(D14/$AB$1,0) -> 0 | AC14: =_xlfn.IFNA(E14/$AB$1,0) -> 1133.3333 | AD14: =_xlfn.IFNA(F14/$AB$1,0) -> 1500 | AE14: =_xlfn.IFNA(G14/$AB$1,0) -> 2366.6667 | AF14: =_xlfn.IFNA(H14/$AB$1,0) -> 233.33333 | AI14: 340 | AJ14: 450 | AK14: 710 | AL14: 70
B15: 3 Leches | C15: 0 | D15: 0 | E15: 0 | F15: 435 | G15: 0 | H15: 70 | I15: =_xlfn.IFNA(C15/$J$1,0) -> 0 | J15: =_xlfn.IFNA(D15/$J$1,0) -> 0 | K15: =_xlfn.IFNA(E15/$J$1,0) -> 0 | L15: =_xlfn.IFNA(F15/$J$1,0) -> 966.66667 | M15: =_xlfn.IFNA(G15/$J$1,0) -> 0 | N15: =_xlfn.IFNA(H15/$J$1,0) -> 155.55556 | O15: =_xlfn.IFNA(C15/$P$1,0) -> 0 | P15: =_xlfn.IFNA(D15/$P$1,0) -> 0 | Q15: =_xlfn.IFNA(E15/$P$1,0) -> 0 | R15: =_xlfn.IFNA(F15/$P$1,0) -> 1087.5 | S15: =_xlfn.IFNA(G15/$P$1,0) -> 0 | T15: =_xlfn.IFNA(H15/$P$1,0) -> 175 | U15: =_xlfn.IFNA(C15/$V$1,0) -> 0 | V15: =_xlfn.IFNA(D15/$V$1,0) -> 0 | W15: =_xlfn.IFNA(E15/$V$1,0) -> 0 | X15: =_xlfn.IFNA(F15/$V$1,0) -> 1242.8571 | Y15: =_xlfn.IFNA(G15/$V$1,0) -> 0 | Z15: =_xlfn.IFNA(H15/$V$1,0) -> 200 | AA15: =_xlfn.IFNA(C15/$AB$1,0) -> 0 | AB15: =_xlfn.IFNA(D15/$AB$1,0) -> 0 | AC15: =_xlfn.IFNA(E15/$AB$1,0) -> 0 | AD15: =_xlfn.IFNA(F15/$AB$1,0) -> 1450 | AE15: =_xlfn.IFNA(G15/$AB$1,0) -> 0 | AF15: =_xlfn.IFNA(H15/$AB$1,0) -> 233.33333 | AI15: =-AI15 -> 0 | AJ15: 435 | AK15: =-AK15 -> 0 | AL15: 75
I16: =_xlfn.IFNA(C16/$J$1,0) -> 0 | J16: =_xlfn.IFNA(D16/$J$1,0) -> 0 | K16: =_xlfn.IFNA(E16/$J$1,0) -> 0 | L16: =_xlfn.IFNA(F16/$J$1,0) -> 0 | M16: =_xlfn.IFNA(G16/$J$1,0) -> 0 | N16: =_xlfn.IFNA(H16/$J$1,0) -> 0 | O16: =_xlfn.IFNA(C16/$P$1,0) -> 0 | P16: =_xlfn.IFNA(D16/$P$1,0) -> 0 | Q16: =_xlfn.IFNA(E16/$P$1,0) -> 0 | R16: =_xlfn.IFNA(F16/$P$1,0) -> 0 | S16: =_xlfn.IFNA(G16/$P$1,0) -> 0 | T16: =_xlfn.IFNA(H16/$P$1,0) -> 0 | U16: =_xlfn.IFNA(C16/$V$1,0) -> 0 | V16: =_xlfn.IFNA(D16/$V$1,0) -> 0 | W16: =_xlfn.IFNA(E16/$V$1,0) -> 0 | X16: =_xlfn.IFNA(F16/$V$1,0) -> 0 | Y16: =_xlfn.IFNA(G16/$V$1,0) -> 0 | Z16: =_xlfn.IFNA(H16/$V$1,0) -> 0 | AA16: =_xlfn.IFNA(C16/$AB$1,0) -> 0 | AB16: =_xlfn.IFNA(D16/$AB$1,0) -> 0 | AC16: =_xlfn.IFNA(E16/$AB$1,0) -> 0 | AD16: =_xlfn.IFNA(F16/$AB$1,0) -> 0 | AE16: =_xlfn.IFNA(G16/$AB$1,0) -> 0 | AF16: =_xlfn.IFNA(H16/$AB$1,0) -> 0 | AI16: =-AI16 -> 0 | AJ16: 480 | AK16: =-AK16 -> 0 | AL16: 80
I17: =_xlfn.IFNA(C17/$J$1,0) -> 0 | J17: =_xlfn.IFNA(D17/$J$1,0) -> 0 | K17: =_xlfn.IFNA(E17/$J$1,0) -> 0 | L17: =_xlfn.IFNA(F17/$J$1,0) -> 0 | M17: =_xlfn.IFNA(G17/$J$1,0) -> 0 | N17: =_xlfn.IFNA(H17/$J$1,0) -> 0 | O17: =_xlfn.IFNA(C17/$P$1,0) -> 0 | P17: =_xlfn.IFNA(D17/$P$1,0) -> 0 | Q17: =_xlfn.IFNA(E17/$P$1,0) -> 0 | R17: =_xlfn.IFNA(F17/$P$1,0) -> 0 | S17: =_xlfn.IFNA(G17/$P$1,0) -> 0 | T17: =_xlfn.IFNA(H17/$P$1,0) -> 0 | U17: =_xlfn.IFNA(C17/$V$1,0) -> 0 | V17: =_xlfn.IFNA(D17/$V$1,0) -> 0 | W17: =_xlfn.IFNA(E17/$V$1,0) -> 0 | X17: =_xlfn.IFNA(F17/$V$1,0) -> 0 | Y17: =_xlfn.IFNA(G17/$V$1,0) -> 0 | Z17: =_xlfn.IFNA(H17/$V$1,0) -> 0 | AA17: =_xlfn.IFNA(C17/$AB$1,0) -> 0 | AB17: =_xlfn.IFNA(D17/$AB$1,0) -> 0 | AC17: =_xlfn.IFNA(E17/$AB$1,0) -> 0 | AD17: =_xlfn.IFNA(F17/$AB$1,0) -> 0 | AE17: =_xlfn.IFNA(G17/$AB$1,0) -> 0 | AF17: =_xlfn.IFNA(H17/$AB$1,0) -> 0 | AG17: 55
A18: Vasos | B18: Fresas con crema | D18: 0 | E18: 90 | F18: 105 | G18: 115 | I18: =_xlfn.IFNA(C18/$J$1,0) -> 0 | J18: =_xlfn.IFNA(D18/$J$1,0) -> 0 | K18: =_xlfn.IFNA(E18/$J$1,0) -> 200 | L18: =_xlfn.IFNA(F18/$J$1,0) -> 233.33333 | M18: =_xlfn.IFNA(G18/$J$1,0) -> 255.55556 | N18: =_xlfn.IFNA(H18/$J$1,0) -> 0 | O18: =_xlfn.IFNA(C18/$P$1,0) -> 0 | P18: =_xlfn.IFNA(D18/$P$1,0) -> 0 | Q18: =_xlfn.IFNA(E18/$P$1,0) -> 225 | R18: =_xlfn.IFNA(F18/$P$1,0) -> 262.5 | S18: =_xlfn.IFNA(G18/$P$1,0) -> 287.5 | T18: =_xlfn.IFNA(H18/$P$1,0) -> 0 | U18: =_xlfn.IFNA(C18/$V$1,0) -> 0 | V18: =_xlfn.IFNA(D18/$V$1,0) -> 0 | W18: =_xlfn.IFNA(E18/$V$1,0) -> 257.14286 | X18: =_xlfn.IFNA(F18/$V$1,0) -> 300 | Y18: =_xlfn.IFNA(G18/$V$1,0) -> 328.57143 | Z18: =_xlfn.IFNA(H18/$V$1,0) -> 0 | AA18: =_xlfn.IFNA(C18/$AB$1,0) -> 0 | AB18: =_xlfn.IFNA(D18/$AB$1,0) -> 0 | AC18: =_xlfn.IFNA(E18/$AB$1,0) -> 300 | AD18: =_xlfn.IFNA(F18/$AB$1,0) -> 350 | AE18: =_xlfn.IFNA(G18/$AB$1,0) -> 383.33333 | AF18: =_xlfn.IFNA(H18/$AB$1,0) -> 0 | AH18: 60 | AI18: 90 | AJ18: 105 | AK18: 115
B19: Fresas con pay | D19: 0 | G19: 0 | I19: =_xlfn.IFNA(C19/$J$1,0) -> 0 | J19: =_xlfn.IFNA(D19/$J$1,0) -> 0 | K19: =_xlfn.IFNA(E19/$J$1,0) -> 0 | L19: =_xlfn.IFNA(F19/$J$1,0) -> 0 | M19: =_xlfn.IFNA(G19/$J$1,0) -> 0 | N19: =_xlfn.IFNA(H19/$J$1,0) -> 0 | O19: =_xlfn.IFNA(C19/$P$1,0) -> 0 | P19: =_xlfn.IFNA(D19/$P$1,0) -> 0 | Q19: =_xlfn.IFNA(E19/$P$1,0) -> 0 | R19: =_xlfn.IFNA(F19/$P$1,0) -> 0 | S19: =_xlfn.IFNA(G19/$P$1,0) -> 0 | T19: =_xlfn.IFNA(H19/$P$1,0) -> 0 | U19: =_xlfn.IFNA(C19/$V$1,0) -> 0 | V19: =_xlfn.IFNA(D19/$V$1,0) -> 0 | W19: =_xlfn.IFNA(E19/$V$1,0) -> 0 | X19: =_xlfn.IFNA(F19/$V$1,0) -> 0 | Y19: =_xlfn.IFNA(G19/$V$1,0) -> 0 | Z19: =_xlfn.IFNA(H19/$V$1,0) -> 0 | AA19: =_xlfn.IFNA(C19/$AB$1,0) -> 0 | AB19: =_xlfn.IFNA(D19/$AB$1,0) -> 0 | AC19: =_xlfn.IFNA(E19/$AB$1,0) -> 0 | AD19: =_xlfn.IFNA(F19/$AB$1,0) -> 0 | AE19: =_xlfn.IFNA(G19/$AB$1,0) -> 0 | AF19: =_xlfn.IFNA(H19/$AB$1,0) -> 0
B20: Crema | D20: 0 | G20: 0 | I20: =_xlfn.IFNA(C20/$J$1,0) -> 0 | J20: =_xlfn.IFNA(D20/$J$1,0) -> 0 | K20: =_xlfn.IFNA(E20/$J$1,0) -> 0 | L20: =_xlfn.IFNA(F20/$J$1,0) -> 0 | M20: =_xlfn.IFNA(G20/$J$1,0) -> 0 | N20: =_xlfn.IFNA(H20/$J$1,0) -> 0 | O20: =_xlfn.IFNA(C20/$P$1,0) -> 0 | P20: =_xlfn.IFNA(D20/$P$1,0) -> 0 | Q20: =_xlfn.IFNA(E20/$P$1,0) -> 0 | R20: =_xlfn.IFNA(F20/$P$1,0) -> 0 | S20: =_xlfn.IFNA(G20/$P$1,0) -> 0 | T20: =_xlfn.IFNA(H20/$P$1,0) -> 0 | U20: =_xlfn.IFNA(C20/$V$1,0) -> 0 | V20: =_xlfn.IFNA(D20/$V$1,0) -> 0 | W20: =_xlfn.IFNA(E20/$V$1,0) -> 0 | X20: =_xlfn.IFNA(F20/$V$1,0) -> 0 | Y20: =_xlfn.IFNA(G20/$V$1,0) -> 0 | Z20: =_xlfn.IFNA(H20/$V$1,0) -> 0 | AA20: =_xlfn.IFNA(C20/$AB$1,0) -> 0 | AB20: =_xlfn.IFNA(D20/$AB$1,0) -> 0 | AC20: =_xlfn.IFNA(E20/$AB$1,0) -> 0 | AD20: =_xlfn.IFNA(F20/$AB$1,0) -> 0 | AE20: =_xlfn.IFNA(G20/$AB$1,0) -> 0 | AF20: =_xlfn.IFNA(H20/$AB$1,0) -> 0
A21: Bollos | B21: Chocolate | C21: 36 | D21: ='Pastel Fresas Con Crema'!E24 -> 0 | E21: ='Pastel Fresas Con Crema'!F24 -> 0 | F21: ='Pastel Fresas Con Crema'!G24 -> 0 | G21: ='Pastel Fresas Con Crema'!H24 -> 0 | H21: ='Pastel Fresas Con Crema'!C24 -> 0 | I21: =_xlfn.IFNA(C21/$J$1,0) -> 80 | J21: =_xlfn.IFNA(D21/$J$1,0) -> 0 | K21: =_xlfn.IFNA(E21/$J$1,0) -> 0 | L21: =_xlfn.IFNA(F21/$J$1,0) -> 0 | M21: =_xlfn.IFNA(G21/$J$1,0) -> 0 | N21: =_xlfn.IFNA(H21/$J$1,0) -> 0 | O21: =_xlfn.IFNA(C21/$P$1,0) -> 90 | P21: =_xlfn.IFNA(D21/$P$1,0) -> 0 | Q21: =_xlfn.IFNA(E21/$P$1,0) -> 0 | R21: =_xlfn.IFNA(F21/$P$1,0) -> 0 | S21: =_xlfn.IFNA(G21/$P$1,0) -> 0 | T21: =_xlfn.IFNA(H21/$P$1,0) -> 0 | U21: =_xlfn.IFNA(C21/$V$1,0) -> 102.85714 | V21: =_xlfn.IFNA(D21/$V$1,0) -> 0 | W21: =_xlfn.IFNA(E21/$V$1,0) -> 0 | X21: =_xlfn.IFNA(F21/$V$1,0) -> 0 | Y21: =_xlfn.IFNA(G21/$V$1,0) -> 0 | Z21: =_xlfn.IFNA(H21/$V$1,0) -> 0 | AA21: =_xlfn.IFNA(C21/$AB$1,0) -> 120 | AB21: =_xlfn.IFNA(D21/$AB$1,0) -> 0 | AC21: =_xlfn.IFNA(E21/$AB$1,0) -> 0 | AD21: =_xlfn.IFNA(F21/$AB$1,0) -> 0 | AE21: =_xlfn.IFNA(G21/$AB$1,0) -> 0 | AF21: =_xlfn.IFNA(H21/$AB$1,0) -> 0 | AG21: 36
B22: Vainilla | C22: 34 | I22: =_xlfn.IFNA(C22/$J$1,0) -> 75.555556 | J22: =_xlfn.IFNA(D22/$J$1,0) -> 0 | K22: =_xlfn.IFNA(E22/$J$1,0) -> 0 | L22: =_xlfn.IFNA(F22/$J$1,0) -> 0 | M22: =_xlfn.IFNA(G22/$J$1,0) -> 0 | N22: =_xlfn.IFNA(H22/$J$1,0) -> 0 | O22: =_xlfn.IFNA(C22/$P$1,0) -> 85 | P22: =_xlfn.IFNA(D22/$P$1,0) -> 0 | Q22: =_xlfn.IFNA(E22/$P$1,0) -> 0 | R22: =_xlfn.IFNA(F22/$P$1,0) -> 0 | S22: =_xlfn.IFNA(G22/$P$1,0) -> 0 | T22: =_xlfn.IFNA(H22/$P$1,0) -> 0 | U22: =_xlfn.IFNA(C22/$V$1,0) -> 97.142857 | V22: =_xlfn.IFNA(D22/$V$1,0) -> 0 | W22: =_xlfn.IFNA(E22/$V$1,0) -> 0 | X22: =_xlfn.IFNA(F22/$V$1,0) -> 0 | Y22: =_xlfn.IFNA(G22/$V$1,0) -> 0 | Z22: =_xlfn.IFNA(H22/$V$1,0) -> 0 | AA22: =_xlfn.IFNA(C22/$AB$1,0) -> 113.33333 | AB22: =_xlfn.IFNA(D22/$AB$1,0) -> 0 | AC22: =_xlfn.IFNA(E22/$AB$1,0) -> 0 | AD22: =_xlfn.IFNA(F22/$AB$1,0) -> 0 | AE22: =_xlfn.IFNA(G22/$AB$1,0) -> 0 | AF22: =_xlfn.IFNA(H22/$AB$1,0) -> 0 | AG22: 34
B23: Zanahoria | C23: 27 | D23: 0 | E23: ='Pastel Zanahoria'!F21 -> 0 | F23: ='Pastel Zanahoria'!G21 -> 0 | G23: ='Pastel Zanahoria'!H21 -> 0 | H23: ='Pastel Zanahoria'!C21 -> 0 | I23: =_xlfn.IFNA(C23/$J$1,0) -> 60 | J23: =_xlfn.IFNA(D23/$J$1,0) -> 0 | K23: =_xlfn.IFNA(E23/$J$1,0) -> 0 | L23: =_xlfn.IFNA(F23/$J$1,0) -> 0 | M23: =_xlfn.IFNA(G23/$J$1,0) -> 0 | N23: =_xlfn.IFNA(H23/$J$1,0) -> 0 | O23: =_xlfn.IFNA(C23/$P$1,0) -> 67.5 | P23: =_xlfn.IFNA(D23/$P$1,0) -> 0 | Q23: =_xlfn.IFNA(E23/$P$1,0) -> 0 | R23: =_xlfn.IFNA(F23/$P$1,0) -> 0 | S23: =_xlfn.IFNA(G23/$P$1,0) -> 0 | T23: =_xlfn.IFNA(H23/$P$1,0) -> 0 | U23: =_xlfn.IFNA(C23/$V$1,0) -> 77.142857 | V23: =_xlfn.IFNA(D23/$V$1,0) -> 0 | W23: =_xlfn.IFNA(E23/$V$1,0) -> 0 | X23: =_xlfn.IFNA(F23/$V$1,0) -> 0 | Y23: =_xlfn.IFNA(G23/$V$1,0) -> 0 | Z23: =_xlfn.IFNA(H23/$V$1,0) -> 0 | AA23: =_xlfn.IFNA(C23/$AB$1,0) -> 90 | AB23: =_xlfn.IFNA(D23/$AB$1,0) -> 0 | AC23: =_xlfn.IFNA(E23/$AB$1,0) -> 0 | AD23: =_xlfn.IFNA(F23/$AB$1,0) -> 0 | AE23: =_xlfn.IFNA(G23/$AB$1,0) -> 0 | AF23: =_xlfn.IFNA(H23/$AB$1,0) -> 0 | AG23: 27
B24: Red Velvet | C24: 30 | D24: ='Pastel Chocolate'!E24 -> 0 | E24: ='Pastel Chocolate'!F24 -> 0 | F24: ='Pastel Chocolate'!G24 -> 0 | G24: ='Pastel Chocolate'!H24 -> 0 | H24: ='Pastel Chocolate'!C24 -> 0 | I24: =_xlfn.IFNA(C24/$J$1,0) -> 66.666667 | J24: =_xlfn.IFNA(D24/$J$1,0) -> 0 | K24: =_xlfn.IFNA(E24/$J$1,0) -> 0 | L24: =_xlfn.IFNA(F24/$J$1,0) -> 0 | M24: =_xlfn.IFNA(G24/$J$1,0) -> 0 | N24: =_xlfn.IFNA(H24/$J$1,0) -> 0 | O24: =_xlfn.IFNA(C24/$P$1,0) -> 75 | P24: =_xlfn.IFNA(D24/$P$1,0) -> 0 | Q24: =_xlfn.IFNA(E24/$P$1,0) -> 0 | R24: =_xlfn.IFNA(F24/$P$1,0) -> 0 | S24: =_xlfn.IFNA(G24/$P$1,0) -> 0 | T24: =_xlfn.IFNA(H24/$P$1,0) -> 0 | U24: =_xlfn.IFNA(C24/$V$1,0) -> 85.714286 | V24: =_xlfn.IFNA(D24/$V$1,0) -> 0 | W24: =_xlfn.IFNA(E24/$V$1,0) -> 0 | X24: =_xlfn.IFNA(F24/$V$1,0) -> 0 | Y24: =_xlfn.IFNA(G24/$V$1,0) -> 0 | Z24: =_xlfn.IFNA(H24/$V$1,0) -> 0 | AA24: =_xlfn.IFNA(C24/$AB$1,0) -> 100 | AB24: =_xlfn.IFNA(D24/$AB$1,0) -> 0 | AC24: =_xlfn.IFNA(E24/$AB$1,0) -> 0 | AD24: =_xlfn.IFNA(F24/$AB$1,0) -> 0 | AE24: =_xlfn.IFNA(G24/$AB$1,0) -> 0 | AF24: =_xlfn.IFNA(H24/$AB$1,0) -> 0 | AG24: 30
B25: Lotus | C25: 39 | D25: 0 | E25: 0 | F25: 0 | G25: 0 | H25: 0 | I25: =_xlfn.IFNA(C25/$J$1,0) -> 86.666667 | J25: =_xlfn.IFNA(D25/$J$1,0) -> 0 | K25: =_xlfn.IFNA(E25/$J$1,0) -> 0 | L25: =_xlfn.IFNA(F25/$J$1,0) -> 0 | M25: =_xlfn.IFNA(G25/$J$1,0) -> 0 | N25: =_xlfn.IFNA(H25/$J$1,0) -> 0 | O25: =_xlfn.IFNA(C25/$P$1,0) -> 97.5 | P25: =_xlfn.IFNA(D25/$P$1,0) -> 0 | Q25: =_xlfn.IFNA(E25/$P$1,0) -> 0 | R25: =_xlfn.IFNA(F25/$P$1,0) -> 0 | S25: =_xlfn.IFNA(G25/$P$1,0) -> 0 | T25: =_xlfn.IFNA(H25/$P$1,0) -> 0 | U25: =_xlfn.IFNA(C25/$V$1,0) -> 111.42857 | V25: =_xlfn.IFNA(D25/$V$1,0) -> 0 | W25: =_xlfn.IFNA(E25/$V$1,0) -> 0 | X25: =_xlfn.IFNA(F25/$V$1,0) -> 0 | Y25: =_xlfn.IFNA(G25/$V$1,0) -> 0 | Z25: =_xlfn.IFNA(H25/$V$1,0) -> 0 | AA25: =_xlfn.IFNA(C25/$AB$1,0) -> 130 | AB25: =_xlfn.IFNA(D25/$AB$1,0) -> 0 | AC25: =_xlfn.IFNA(E25/$AB$1,0) -> 0 | AD25: =_xlfn.IFNA(F25/$AB$1,0) -> 0 | AE25: =_xlfn.IFNA(G25/$AB$1,0) -> 0 | AF25: =_xlfn.IFNA(H25/$AB$1,0) -> 0 | AG25: 39
A26: Cheesecake | B26: Lotus | C26: 135 | D26: ='Resumen Costos'!D28 -> 0 | E26: 0 | F26: 650 | G26: ='Resumen Costos'!G28 -> 0 | H26: ='Resumen Costos'!H28 -> 0 | I26: =_xlfn.IFNA(C26/$J$1,0) -> 300 | J26: =_xlfn.IFNA(D26/$J$1,0) -> 0 | K26: =_xlfn.IFNA(E26/$J$1,0) -> 0 | L26: =_xlfn.IFNA(F26/$J$1,0) -> 1444.4444 | M26: =_xlfn.IFNA(G26/$J$1,0) -> 0 | N26: =_xlfn.IFNA(H26/$J$1,0) -> 0 | O26: =_xlfn.IFNA(C26/$P$1,0) -> 337.5 | P26: =_xlfn.IFNA(D26/$P$1,0) -> 0 | Q26: =_xlfn.IFNA(E26/$P$1,0) -> 0 | R26: =_xlfn.IFNA(F26/$P$1,0) -> 1625 | S26: =_xlfn.IFNA(G26/$P$1,0) -> 0 | T26: =_xlfn.IFNA(H26/$P$1,0) -> 0 | U26: =_xlfn.IFNA(C26/$V$1,0) -> 385.71429 | V26: =_xlfn.IFNA(D26/$V$1,0) -> 0 | W26: =_xlfn.IFNA(E26/$V$1,0) -> 0 | X26: =_xlfn.IFNA(F26/$V$1,0) -> 1857.1429 | Y26: =_xlfn.IFNA(G26/$V$1,0) -> 0 | Z26: =_xlfn.IFNA(H26/$V$1,0) -> 0 | AA26: =_xlfn.IFNA(C26/$AB$1,0) -> 450 | AB26: =_xlfn.IFNA(D26/$AB$1,0) -> 0 | AC26: =_xlfn.IFNA(E26/$AB$1,0) -> 0 | AD26: =_xlfn.IFNA(F26/$AB$1,0) -> 2166.6667 | AE26: =_xlfn.IFNA(G26/$AB$1,0) -> 0 | AF26: =_xlfn.IFNA(H26/$AB$1,0) -> 0 | AG26: 135 | AJ26: 650
B27: Tortuga | C27: 125 | D27: ='Resumen Costos'!D29 -> 0 | E27: 0 | F27: 590 | G27: ='Resumen Costos'!G29 -> 0 | H27: ='Resumen Costos'!H29 -> 0 | I27: =_xlfn.IFNA(C27/$J$1,0) -> 277.77778 | J27: =_xlfn.IFNA(D27/$J$1,0) -> 0 | K27: =_xlfn.IFNA(E27/$J$1,0) -> 0 | L27: =_xlfn.IFNA(F27/$J$1,0) -> 1311.1111 | M27: =_xlfn.IFNA(G27/$J$1,0) -> 0 | N27: =_xlfn.IFNA(H27/$J$1,0) -> 0 | O27: =_xlfn.IFNA(C27/$P$1,0) -> 312.5 | P27: =_xlfn.IFNA(D27/$P$1,0) -> 0 | Q27: =_xlfn.IFNA(E27/$P$1,0) -> 0 | R27: =_xlfn.IFNA(F27/$P$1,0) -> 1475 | S27: =_xlfn.IFNA(G27/$P$1,0) -> 0 | T27: =_xlfn.IFNA(H27/$P$1,0) -> 0 | U27: =_xlfn.IFNA(C27/$V$1,0) -> 357.14286 | V27: =_xlfn.IFNA(D27/$V$1,0) -> 0 | W27: =_xlfn.IFNA(E27/$V$1,0) -> 0 | X27: =_xlfn.IFNA(F27/$V$1,0) -> 1685.7143 | Y27: =_xlfn.IFNA(G27/$V$1,0) -> 0 | Z27: =_xlfn.IFNA(H27/$V$1,0) -> 0 | AA27: =_xlfn.IFNA(C27/$AB$1,0) -> 416.66667 | AB27: =_xlfn.IFNA(D27/$AB$1,0) -> 0 | AC27: =_xlfn.IFNA(E27/$AB$1,0) -> 0 | AD27: =_xlfn.IFNA(F27/$AB$1,0) -> 1966.6667 | AE27: =_xlfn.IFNA(G27/$AB$1,0) -> 0 | AF27: =_xlfn.IFNA(H27/$AB$1,0) -> 0 | AG27: 125 | AJ27: 590
B28: Rol de Canela | C28: 130 | D28: ='Resumen Costos'!D33 -> 0 | E28: 0 | F28: 635 | G28: ='Resumen Costos'!G33 -> 0 | H28: ='Resumen Costos'!H33 -> 0 | I28: =_xlfn.IFNA(C28/$J$1,0) -> 288.88889 | J28: =_xlfn.IFNA(D28/$J$1,0) -> 0 | K28: =_xlfn.IFNA(E28/$J$1,0) -> 0 | L28: =_xlfn.IFNA(F28/$J$1,0) -> 1411.1111 | M28: =_xlfn.IFNA(G28/$J$1,0) -> 0 | N28: =_xlfn.IFNA(H28/$J$1,0) -> 0 | O28: =_xlfn.IFNA(C28/$P$1,0) -> 325 | P28: =_xlfn.IFNA(D28/$P$1,0) -> 0 | Q28: =_xlfn.IFNA(E28/$P$1,0) -> 0 | R28: =_xlfn.IFNA(F28/$P$1,0) -> 1587.5 | S28: =_xlfn.IFNA(G28/$P$1,0) -> 0 | T28: =_xlfn.IFNA(H28/$P$1,0) -> 0 | U28: =_xlfn.IFNA(C28/$V$1,0) -> 371.42857 | V28: =_xlfn.IFNA(D28/$V$1,0) -> 0 | W28: =_xlfn.IFNA(E28/$V$1,0) -> 0 | X28: =_xlfn.IFNA(F28/$V$1,0) -> 1814.2857 | Y28: =_xlfn.IFNA(G28/$V$1,0) -> 0 | Z28: =_xlfn.IFNA(H28/$V$1,0) -> 0 | AA28: =_xlfn.IFNA(C28/$AB$1,0) -> 433.33333 | AB28: =_xlfn.IFNA(D28/$AB$1,0) -> 0 | AC28: =_xlfn.IFNA(E28/$AB$1,0) -> 0 | AD28: =_xlfn.IFNA(F28/$AB$1,0) -> 2116.6667 | AE28: =_xlfn.IFNA(G28/$AB$1,0) -> 0 | AF28: =_xlfn.IFNA(H28/$AB$1,0) -> 0 | AG28: 130 | AJ28: 635
A29: Galletas | B29: Chispas de Chocolate | C29: 32 | D29: 0 | E29: 0 | F29: 0 | G29: 0 | H29: 0 | I29: =_xlfn.IFNA(C29/$J$1,0) -> 71.111111 | J29: =_xlfn.IFNA(D29/$J$1,0) -> 0 | K29: =_xlfn.IFNA(E29/$J$1,0) -> 0 | L29: =_xlfn.IFNA(F29/$J$1,0) -> 0 | M29: =_xlfn.IFNA(G29/$J$1,0) -> 0 | N29: =_xlfn.IFNA(H29/$J$1,0) -> 0 | O29: =_xlfn.IFNA(C29/$P$1,0) -> 80 | P29: =_xlfn.IFNA(D29/$P$1,0) -> 0 | Q29: =_xlfn.IFNA(E29/$P$1,0) -> 0 | R29: =_xlfn.IFNA(F29/$P$1,0) -> 0 | S29: =_xlfn.IFNA(G29/$P$1,0) -> 0 | T29: =_xlfn.IFNA(H29/$P$1,0) -> 0 | U29: =_xlfn.IFNA(C29/$V$1,0) -> 91.428571 | V29: =_xlfn.IFNA(D29/$V$1,0) -> 0 | W29: =_xlfn.IFNA(E29/$V$1,0) -> 0 | X29: =_xlfn.IFNA(F29/$V$1,0) -> 0 | Y29: =_xlfn.IFNA(G29/$V$1,0) -> 0 | Z29: =_xlfn.IFNA(H29/$V$1,0) -> 0 | AA29: =_xlfn.IFNA(C29/$AB$1,0) -> 106.66667 | AB29: =_xlfn.IFNA(D29/$AB$1,0) -> 0 | AC29: =_xlfn.IFNA(E29/$AB$1,0) -> 0 | AD29: =_xlfn.IFNA(F29/$AB$1,0) -> 0 | AE29: =_xlfn.IFNA(G29/$AB$1,0) -> 0 | AF29: =_xlfn.IFNA(H29/$AB$1,0) -> 0 | AG29: 32
B30: Lotus | C30: 48 | I30: =_xlfn.IFNA(C30/$J$1,0) -> 106.66667 | J30: =_xlfn.IFNA(D30/$J$1,0) -> 0 | K30: =_xlfn.IFNA(E30/$J$1,0) -> 0 | L30: =_xlfn.IFNA(F30/$J$1,0) -> 0 | M30: =_xlfn.IFNA(G30/$J$1,0) -> 0 | N30: =_xlfn.IFNA(H30/$J$1,0) -> 0 | O30: =_xlfn.IFNA(C30/$P$1,0) -> 120 | P30: =_xlfn.IFNA(D30/$P$1,0) -> 0 | Q30: =_xlfn.IFNA(E30/$P$1,0) -> 0 | R30: =_xlfn.IFNA(F30/$P$1,0) -> 0 | S30: =_xlfn.IFNA(G30/$P$1,0) -> 0 | T30: =_xlfn.IFNA(H30/$P$1,0) -> 0 | U30: =_xlfn.IFNA(C30/$V$1,0) -> 137.14286 | V30: =_xlfn.IFNA(D30/$V$1,0) -> 0 | W30: =_xlfn.IFNA(E30/$V$1,0) -> 0 | X30: =_xlfn.IFNA(F30/$V$1,0) -> 0 | Y30: =_xlfn.IFNA(G30/$V$1,0) -> 0 | Z30: =_xlfn.IFNA(H30/$V$1,0) -> 0 | AA30: =_xlfn.IFNA(C30/$AB$1,0) -> 160 | AB30: =_xlfn.IFNA(D30/$AB$1,0) -> 0 | AC30: =_xlfn.IFNA(E30/$AB$1,0) -> 0 | AD30: =_xlfn.IFNA(F30/$AB$1,0) -> 0 | AE30: =_xlfn.IFNA(G30/$AB$1,0) -> 0 | AF30: =_xlfn.IFNA(H30/$AB$1,0) -> 0 | AG30: 48
B31: Red Velvet | C31: 30 | I31: =_xlfn.IFNA(C31/$J$1,0) -> 66.666667 | J31: =_xlfn.IFNA(D31/$J$1,0) -> 0 | K31: =_xlfn.IFNA(E31/$J$1,0) -> 0 | L31: =_xlfn.IFNA(F31/$J$1,0) -> 0 | M31: =_xlfn.IFNA(G31/$J$1,0) -> 0 | N31: =_xlfn.IFNA(H31/$J$1,0) -> 0 | O31: =_xlfn.IFNA(C31/$P$1,0) -> 75 | P31: =_xlfn.IFNA(D31/$P$1,0) -> 0 | Q31: =_xlfn.IFNA(E31/$P$1,0) -> 0 | R31: =_xlfn.IFNA(F31/$P$1,0) -> 0 | S31: =_xlfn.IFNA(G31/$P$1,0) -> 0 | T31: =_xlfn.IFNA(H31/$P$1,0) -> 0 | U31: =_xlfn.IFNA(C31/$V$1,0) -> 85.714286 | V31: =_xlfn.IFNA(D31/$V$1,0) -> 0 | W31: =_xlfn.IFNA(E31/$V$1,0) -> 0 | X31: =_xlfn.IFNA(F31/$V$1,0) -> 0 | Y31: =_xlfn.IFNA(G31/$V$1,0) -> 0 | Z31: =_xlfn.IFNA(H31/$V$1,0) -> 0 | AA31: =_xlfn.IFNA(C31/$AB$1,0) -> 100 | AB31: =_xlfn.IFNA(D31/$AB$1,0) -> 0 | AC31: =_xlfn.IFNA(E31/$AB$1,0) -> 0 | AD31: =_xlfn.IFNA(F31/$AB$1,0) -> 0 | AE31: =_xlfn.IFNA(G31/$AB$1,0) -> 0 | AF31: =_xlfn.IFNA(H31/$AB$1,0) -> 0 | AG31: 30
B32: Nutella | C32: 30 | I32: =_xlfn.IFNA(C32/$J$1,0) -> 66.666667 | J32: =_xlfn.IFNA(D32/$J$1,0) -> 0 | K32: =_xlfn.IFNA(E32/$J$1,0) -> 0 | L32: =_xlfn.IFNA(F32/$J$1,0) -> 0 | M32: =_xlfn.IFNA(G32/$J$1,0) -> 0 | N32: =_xlfn.IFNA(H32/$J$1,0) -> 0 | O32: =_xlfn.IFNA(C32/$P$1,0) -> 75 | P32: =_xlfn.IFNA(D32/$P$1,0) -> 0 | Q32: =_xlfn.IFNA(E32/$P$1,0) -> 0 | R32: =_xlfn.IFNA(F32/$P$1,0) -> 0 | S32: =_xlfn.IFNA(G32/$P$1,0) -> 0 | T32: =_xlfn.IFNA(H32/$P$1,0) -> 0 | U32: =_xlfn.IFNA(C32/$V$1,0) -> 85.714286 | V32: =_xlfn.IFNA(D32/$V$1,0) -> 0 | W32: =_xlfn.IFNA(E32/$V$1,0) -> 0 | X32: =_xlfn.IFNA(F32/$V$1,0) -> 0 | Y32: =_xlfn.IFNA(G32/$V$1,0) -> 0 | Z32: =_xlfn.IFNA(H32/$V$1,0) -> 0 | AA32: =_xlfn.IFNA(C32/$AB$1,0) -> 100 | AB32: =_xlfn.IFNA(D32/$AB$1,0) -> 0 | AC32: =_xlfn.IFNA(E32/$AB$1,0) -> 0 | AD32: =_xlfn.IFNA(F32/$AB$1,0) -> 0 | AE32: =_xlfn.IFNA(G32/$AB$1,0) -> 0 | AF32: =_xlfn.IFNA(H32/$AB$1,0) -> 0 | AG32: 30
I35: =_xlfn.IFNA(C35/$J$1,0) -> 0 | J35: =_xlfn.IFNA(D35/$J$1,0) -> 0 | K35: =_xlfn.IFNA(E35/$J$1,0) -> 0 | L35: =_xlfn.IFNA(F35/$J$1,0) -> 0 | M35: =_xlfn.IFNA(G35/$J$1,0) -> 0 | N35: =_xlfn.IFNA(H35/$J$1,0) -> 0 | O35: =_xlfn.IFNA(C35/$P$1,0) -> 0 | P35: =_xlfn.IFNA(D35/$P$1,0) -> 0 | Q35: =_xlfn.IFNA(E35/$P$1,0) -> 0 | R35: =_xlfn.IFNA(F35/$P$1,0) -> 0 | S35: =_xlfn.IFNA(G35/$P$1,0) -> 0 | T35: =_xlfn.IFNA(H35/$P$1,0) -> 0 | U35: =_xlfn.IFNA(C35/$V$1,0) -> 0 | V35: =_xlfn.IFNA(D35/$V$1,0) -> 0 | W35: =_xlfn.IFNA(E35/$V$1,0) -> 0 | X35: =_xlfn.IFNA(F35/$V$1,0) -> 0 | Y35: =_xlfn.IFNA(G35/$V$1,0) -> 0 | Z35: =_xlfn.IFNA(H35/$V$1,0) -> 0 | AA35: =_xlfn.IFNA(C35/$AB$1,0) -> 0 | AB35: =_xlfn.IFNA(D35/$AB$1,0) -> 0 | AC35: =_xlfn.IFNA(E35/$AB$1,0) -> 0 | AD35: =_xlfn.IFNA(F35/$AB$1,0) -> 0 | AE35: =_xlfn.IFNA(G35/$AB$1,0) -> 0 | AF35: =_xlfn.IFNA(H35/$AB$1,0) -> 0
C37: Individual | D37: Mini | E37: Chico | F37: Mediano | G37: Grande | H37: Rebanada | I37: Individual | J37: Mini | K37: Chico | L37: Mediano | M37: Grande | N37: Rebanada | O37: Individual | P37: Mini | Q37: Chico | R37: Mediano | S37: Grande | T37: Rebanada | U37: Individual | V37: Mini | W37: Chico | X37: Mediano | Y37: Grande | Z37: Rebanada | AA37: Individual | AB37: Mini | AC37: Chico | AD37: Mediano | AE37: Grande | AF37: Rebanada | AG37: Individual | AH37: Mini | AI37: Chico | AJ37: Mediano | AK37: Grande | AL37: Rebanada
A38: Promedio | B38: Pastel | C38: 0 | D38: =AVERAGE(D9,D10,D12) -> 185 | E38: =AVERAGE(E9:E11,E12:E13) -> 353 | F38: =AVERAGE(F9:F11,F12:F15) -> 470.71429 | G38: =AVERAGE(G9:G11,G12:G15) -> 608.57143 | H38: =AVERAGE(H9:H11,H12:H15) -> 70 | I38: =_xlfn.IFNA(C38/$J$1,0) -> 0 | J38: =_xlfn.IFNA(D38/$J$1,0) -> 411.11111 | K38: =_xlfn.IFNA(E38/$J$1,0) -> 784.44444 | L38: =_xlfn.IFNA(F38/$J$1,0) -> 1046.0317 | M38: =_xlfn.IFNA(G38/$J$1,0) -> 1352.381 | N38: =_xlfn.IFNA(H38/$J$1,0) -> 155.55556 | O38: =_xlfn.IFNA(C38/$P$1,0) -> 0 | P38: =_xlfn.IFNA(D38/$P$1,0) -> 462.5 | Q38: =_xlfn.IFNA(E38/$P$1,0) -> 882.5 | R38: =_xlfn.IFNA(F38/$P$1,0) -> 1176.7857 | S38: =_xlfn.IFNA(G38/$P$1,0) -> 1521.4286 | T38: =_xlfn.IFNA(H38/$P$1,0) -> 175 | U38: =_xlfn.IFNA(C38/$V$1,0) -> 0 | V38: =_xlfn.IFNA(D38/$V$1,0) -> 528.57143 | W38: =_xlfn.IFNA(E38/$V$1,0) -> 1008.5714 | X38: =_xlfn.IFNA(F38/$V$1,0) -> 1344.898 | Y38: =_xlfn.IFNA(G38/$V$1,0) -> 1738.7755 | Z38: =_xlfn.IFNA(H38/$V$1,0) -> 200 | AA38: =_xlfn.IFNA(C38/$AB$1,0) -> 0 | AB38: =_xlfn.IFNA(D38/$AB$1,0) -> 616.66667 | AC38: =_xlfn.IFNA(E38/$AB$1,0) -> 1176.6667 | AD38: =_xlfn.IFNA(F38/$AB$1,0) -> 1569.0476 | AE38: =_xlfn.IFNA(G38/$AB$1,0) -> 2028.5714 | AF38: =_xlfn.IFNA(H38/$AB$1,0) -> 233.33333
B39: Pay | C39: =AVERAGE(C3:C6) -> 0 | D39: =AVERAGE(D3:D8) -> 0 | E39: =AVERAGE(E3:E8) -> 0 | F39: =AVERAGE(F3:F5) -> 381.66667 | G39: =AVERAGE(G3:G5) -> 481.66667 | H39: =AVERAGE(H3:H5) -> 70 | I39: =_xlfn.IFNA(C39/$J$1,0) -> 0 | J39: =_xlfn.IFNA(D39/$J$1,0) -> 0 | K39: =_xlfn.IFNA(E39/$J$1,0) -> 0 | L39: =_xlfn.IFNA(F39/$J$1,0) -> 848.14815 | M39: =_xlfn.IFNA(G39/$J$1,0) -> 1070.3704 | N39: =_xlfn.IFNA(H39/$J$1,0) -> 155.55556 | O39: =_xlfn.IFNA(C39/$P$1,0) -> 0 | P39: =_xlfn.IFNA(D39/$P$1,0) -> 0 | Q39: =_xlfn.IFNA(E39/$P$1,0) -> 0 | R39: =_xlfn.IFNA(F39/$P$1,0) -> 954.16667 | S39: =_xlfn.IFNA(G39/$P$1,0) -> 1204.1667 | T39: =_xlfn.IFNA(H39/$P$1,0) -> 175 | U39: =_xlfn.IFNA(C39/$V$1,0) -> 0 | V39: =_xlfn.IFNA(D39/$V$1,0) -> 0 | W39: =_xlfn.IFNA(E39/$V$1,0) -> 0 | X39: =_xlfn.IFNA(F39/$V$1,0) -> 1090.4762 | Y39: =_xlfn.IFNA(G39/$V$1,0) -> 1376.1905 | Z39: =_xlfn.IFNA(H39/$V$1,0) -> 200 | AA39: =_xlfn.IFNA(C39/$AB$1,0) -> 0 | AB39: =_xlfn.IFNA(D39/$AB$1,0) -> 0 | AC39: =_xlfn.IFNA(E39/$AB$1,0) -> 0 | AD39: =_xlfn.IFNA(F39/$AB$1,0) -> 1272.2222 | AE39: =_xlfn.IFNA(G39/$AB$1,0) -> 1605.5556 | AF39: =_xlfn.IFNA(H39/$AB$1,0) -> 233.33333
B40: Vasos | C40: =IFERROR(AVERAGE(C18:C20),0) -> 0 | D40: =IFERROR(AVERAGE(D18:D19),0) -> 0 | E40: =IFERROR(AVERAGE(E18:E20),0) -> 90 | F40: =IFERROR(AVERAGE(F18:F20),0) -> 105 | G40: =IFERROR(AVERAGE(G18:G19),0) -> 57.5 | H40: =IFERROR(AVERAGE(H18:H20),0) -> 0 | I40: =_xlfn.IFNA(C40/$J$1,0) -> 0 | J40: =_xlfn.IFNA(D40/$J$1,0) -> 0 | K40: =_xlfn.IFNA(E40/$J$1,0) -> 200 | L40: =_xlfn.IFNA(F40/$J$1,0) -> 233.33333 | M40: =_xlfn.IFNA(G40/$J$1,0) -> 127.77778 | N40: =_xlfn.IFNA(H40/$J$1,0) -> 0 | O40: =_xlfn.IFNA(C40/$P$1,0) -> 0 | P40: =_xlfn.IFNA(D40/$P$1,0) -> 0 | Q40: =_xlfn.IFNA(E40/$P$1,0) -> 225 | R40: =_xlfn.IFNA(F40/$P$1,0) -> 262.5 | S40: =_xlfn.IFNA(G40/$P$1,0) -> 143.75 | T40: =_xlfn.IFNA(H40/$P$1,0) -> 0 | U40: =_xlfn.IFNA(C40/$V$1,0) -> 0 | V40: =_xlfn.IFNA(D40/$V$1,0) -> 0 | W40: =_xlfn.IFNA(E40/$V$1,0) -> 257.14286 | X40: =_xlfn.IFNA(F40/$V$1,0) -> 300 | Y40: =_xlfn.IFNA(G40/$V$1,0) -> 164.28571 | Z40: =_xlfn.IFNA(H40/$V$1,0) -> 0 | AA40: =_xlfn.IFNA(C40/$AB$1,0) -> 0 | AB40: =_xlfn.IFNA(D40/$AB$1,0) -> 0 | AC40: =_xlfn.IFNA(E40/$AB$1,0) -> 300 | AD40: =_xlfn.IFNA(F40/$AB$1,0) -> 350 | AE40: =_xlfn.IFNA(G40/$AB$1,0) -> 191.66667 | AF40: =_xlfn.IFNA(H40/$AB$1,0) -> 0
B41: Bollos | C41: =AVERAGE(C21:C25) -> 33.2 | D41: =AVERAGE(D21:D25) -> 0 | E41: =AVERAGE(E21:E25) -> 0 | F41: =AVERAGE(F21:F25) -> 0 | G41: =AVERAGE(G21:G25) -> 0 | H41: =AVERAGE(H21:H25) -> 0 | I41: =_xlfn.IFNA(C41/$J$1,0) -> 73.777778 | J41: =_xlfn.IFNA(D41/$J$1,0) -> 0 | K41: =_xlfn.IFNA(E41/$J$1,0) -> 0 | L41: =_xlfn.IFNA(F41/$J$1,0) -> 0 | M41: =_xlfn.IFNA(G41/$J$1,0) -> 0 | N41: =_xlfn.IFNA(H41/$J$1,0) -> 0 | O41: =_xlfn.IFNA(C41/$P$1,0) -> 83 | P41: =_xlfn.IFNA(D41/$P$1,0) -> 0 | Q41: =_xlfn.IFNA(E41/$P$1,0) -> 0 | R41: =_xlfn.IFNA(F41/$P$1,0) -> 0 | S41: =_xlfn.IFNA(G41/$P$1,0) -> 0 | T41: =_xlfn.IFNA(H41/$P$1,0) -> 0 | U41: =_xlfn.IFNA(C41/$V$1,0) -> 94.857143 | V41: =_xlfn.IFNA(D41/$V$1,0) -> 0 | W41: =_xlfn.IFNA(E41/$V$1,0) -> 0 | X41: =_xlfn.IFNA(F41/$V$1,0) -> 0 | Y41: =_xlfn.IFNA(G41/$V$1,0) -> 0 | Z41: =_xlfn.IFNA(H41/$V$1,0) -> 0 | AA41: =_xlfn.IFNA(C41/$AB$1,0) -> 110.66667 | AB41: =_xlfn.IFNA(D41/$AB$1,0) -> 0 | AC41: =_xlfn.IFNA(E41/$AB$1,0) -> 0 | AD41: =_xlfn.IFNA(F41/$AB$1,0) -> 0 | AE41: =_xlfn.IFNA(G41/$AB$1,0) -> 0 | AF41: =_xlfn.IFNA(H41/$AB$1,0) -> 0
AG42: COMPETENCIAS - ANALISIS 2025
AH43: Rango de precios
AG44: Presentación/Empresa | AH44: LA REBANADA | AI44: GINA | AJ44: EL PECADO
AG45: Pastel Grande | AH45: 480 - 450 | AI45: 640 - 700 | AJ45: 730 -800
AG46: Pastel Mediano | AH46: 420 - 390 | AI46: 420 | AJ46: 430 - 450 - 480
AG47: Pastel Chico | AH47: 350 - 320 | AI47: 320 | AJ47: 310 - 350
AG48: Pay Grande | AH48: 400 | AI48: 420 | AJ48: 400
AG49: Pay Mediano | AH49: 280 | AI49: 320 | AJ49: 300

Sheet Costo Materia Prima
A2: Proveedor | B2: Nombre Corto | C2: Código de Barras | D2: Producto | E2: Descripción | F2: Cantidad | G2: Unidad | H2: Precio | I2: Costo | J2: $/Unidad | K2: Estado | L2: Fecha
A3: Abarrotera del Duero | B3: Duero | C3: 501 | D3: Azúcar Estándar | E3: Azucar estándar granel (costal de 50 kg) | F3: =_xlfn.IFNA(VLOOKUP(TablaPrecios[[#This Row],[Producto]],'[1]Costo Materia Prima'!A$3:K$424,3,FALSE),"") -> 50 | G3: =_xlfn.IFNA(VLOOKUP(TablaPrecios[[#This Row],[Producto]],'[1]Costo Materia Prima'!A$3:K$424,4,FALSE),"") -> KG | H3: =_xlfn.IFNA(VLOOKUP(TablaPrecios[[#This Row],[Producto]],'[1]Costo Materia Prima'!A$3:K$424,5,FALSE),"") -> 1020 | I3: =IFERROR(TablaPrecios[[#This Row],[Precio]]/TablaPrecios[[#This Row],[Cantidad]],0) -> 20.4 | J3: =_xlfn.IFNA(VLOOKUP(TablaPrecios[[#This Row],[Producto]],'[1]Costo Materia Prima'!A$3:K$424,8,FALSE),"") -> KG | K3: =_xlfn.IFNA(VLOOKUP(TablaPrecios[[#This Row],[Producto]],'[1]Costo Materia Prima'!A$3:K$424,9,FALSE),"-") -> Verificado | L3: =_xlfn.IFNA(VLOOKUP(TablaPrecios[[#This Row],[Producto]],'[1]Costo Materia Prima'!A$3:K$424,11,FALSE),"") -> 46042
A4: Abarrotera del Duero | B4: Duero | D4: Jugo de Piña | E4: Jumex Jugo de piña | F4: =_xlfn.IFNA(VLOOKUP(TablaPrecios[[#This Row],[Producto]],'[1]Costo Materia Prima'!A$3:K$424,3,FALSE),"") -> 0 | G4: =_xlfn.IFNA(VLOOKUP(TablaPrecios[[#This Row],[Producto]],'[1]Costo Materia Prima'!A$3:K$424,4,FALSE),"") -> LT | H4: =_xlfn.IFNA(VLOOKUP(TablaPrecios[[#This Row],[Producto]],'[1]Costo Materia Prima'!A$3:K$424,5,FALSE),"") -> 0 | I4: =IFERROR(TablaPrecios[[#This Row],[Precio]]/TablaPrecios[[#This Row],[Cantidad]],0) -> 0 | J4: =_xlfn.IFNA(VLOOKUP(TablaPrecios[[#This Row],[Producto]],'[1]Costo Materia Prima'!A$3:K$424,8,FALSE),"") -> LT | K4: =_xlfn.IFNA(VLOOKUP(TablaPrecios[[#This Row],[Producto]],'[1]Costo Materia Prima'!A$3:K$424,9,FALSE),"-") -> Verificado | L4: =_xlfn.IFNA(VLOOKUP(TablaPrecios[[#This Row],[Producto]],'[1]Costo Materia Prima'!A$3:K$424,11,FALSE),"") -> 46024
A5: Abarrotera del Duero | B5: Duero | C5: 7501000658923 | D5: Galleta María | E5: Galletas Gamesa Marías (Pieza 170 gr) | F5: =_xlfn.IFNA(VLOOKUP(TablaPrecios[[#This Row],[Producto]],'[1]Costo Materia Prima'!A$3:K$424,3,FALSE),"") -> 264 | G5: =_xlfn.IFNA(VLOOKUP(TablaPrecios[[#This Row],[Producto]],'[1]Costo Materia Prima'!A$3:K$424,4,FALSE),"") -> PZ | H5: =_xlfn.IFNA(VLOOKUP(TablaPrecios[[#This Row],[Producto]],'[1]Costo Materia Prima'!A$3:K$424,5,FALSE),"") -> 3666.96 | I5: =IFERROR(TablaPrecios[[#This Row],[Precio]]/TablaPrecios[[#This Row],[Cantidad]],0) -> 13.89 | J5: =_xlfn.IFNA(VLOOKUP(TablaPrecios[[#This Row],[Producto]],'[1]Costo Materia Prima'!A$3:K$424,8,FALSE),"") -> PZ | K5: =_xlfn.IFNA(VLOOKUP(TablaPrecios[[#This Row],[Producto]],'[1]Costo Materia Prima'!A$3:K$424,9,FALSE),"-") -> Verificado | L5: =_xlfn.IFNA(VLOOKUP(TablaPrecios[[#This Row],[Producto]],'[1]Costo Materia Prima'!A$3:K$424,11,FALSE),"") -> 46042
A6: Abarrotera del Duero | B6: Duero | C6: 7501020515848 | D6: Media Crema | E6: Lala Media Crema cartón con 24 envases de 500 ml c/u | F6: =_xlfn.IFNA(VLOOKUP(TablaPrecios[[#This Row],[Producto]],'[1]Costo Materia Prima'!A$3:K$424,3,FALSE),"") -> 576 | G6: =_xlfn.IFNA(VLOOKUP(TablaPrecios[[#This Row],[Producto]],'[1]Costo Materia Prima'!A$3:K$424,4,FALSE),"") -> LT | H6: =_xlfn.IFNA(VLOOKUP(TablaPrecios[[#This Row],[Producto]],'[1]Costo Materia Prima'!A$3:K$424,5,FALSE),"") -> 33600 | I6: =IFERROR(TablaPrecios[[#This Row],[Precio]]/TablaPrecios[[#This Row],[Cantidad]],0) -> 58.333333 | J6: =_xlfn.IFNA(VLOOKUP(TablaPrecios[[#This Row],[Producto]],'[1]Costo Materia Prima'!A$3:K$424,8,FALSE),"") -> LT | K6: =_xlfn.IFNA(VLOOKUP(TablaPrecios[[#This Row],[Producto]],'[1]Costo Materia Prima'!A$3:K$424,9,FALSE),"-") -> Verificado | L6: =_xlfn.IFNA(VLOOKUP(TablaPrecios[[#This Row],[Producto]],'[1]Costo Materia Prima'!A$3:K$424,11,FALSE),"") -> 46042
A7: Abarrotera del Duero | B7: Duero | D7: LecheLala | E7: Leche Lala Entera cartón de 1 LT | F7: =_xlfn.IFNA(VLOOKUP(TablaPrecios[[#This Row],[Producto]],'[1]Costo Materia Prima'!A$3:K$424,3,FALSE),"") -> 0 | G7: =_xlfn.IFNA(VLOOKUP(TablaPrecios[[#This Row],[Producto]],'[1]Costo Materia Prima'!A$3:K$424,4,FALSE),"") -> LT | H7: =_xlfn.IFNA(VLOOKUP(TablaPrecios[[#This Row],[Producto]],'[1]Costo Materia Prima'!A$3:K$424,5,FALSE),"") -> 0 | I7: =IFERROR(TablaPrecios[[#This Row],[Precio]]/TablaPrecios[[#This Row],[Cantidad]],0) -> 0 | J7: =_xlfn.IFNA(VLOOKUP(TablaPrecios[[#This Row],[Producto]],'[1]Costo Materia Prima'!A$3:K$424,8,FALSE),"") -> LT | K7: =_xlfn.IFNA(VLOOKUP(TablaPrecios[[#This Row],[Producto]],'[1]Costo Materia Prima'!A$3:K$424,9,FALSE),"-") -> Verificado | L7: =_xlfn.IFNA(VLOOKUP(TablaPrecios[[#This Row],[Producto]],'[1]Costo Materia Prima'!A$3:K$424,11,FALSE),"") -> 46024
A8: Abarrotera del Duero | B8: Duero | C8: 7501020540666 | D8: NutriLeche | E8: Leche Nutrileche (1 Litro) | F8: =_xlfn.IFNA(VLOOKUP(TablaPrecios[[#This Row],[Producto]],'[1]Costo Materia Prima'!A$3:K$424,3,FALSE),"") -> 240 | G8: =_xlfn.IFNA(VLOOKUP(TablaPrecios[[#This Row],[Producto]],'[1]Costo Materia Prima'!A$3:K$424,4,FALSE),"") -> LT | H8: =_xlfn.IFNA(VLOOKUP(TablaPrecios[[#This Row],[Producto]],'[1]Costo Materia Prima'!A$3:K$424,5,FALSE),"") -> 4692 | I8: =IFERROR(TablaPrecios[[#This Row],[Precio]]/TablaPrecios[[#This Row],[Cantidad]],0) -> 19.55 | J8: =_xlfn.IFNA(VLOOKUP(TablaPrecios[[#This Row],[Producto]],'[1]Costo Materia Prima'!A$3:K$424,8,FALSE),"") -> LT | K8: =_xlfn.IFNA(VLOOKUP(TablaPrecios[[#This Row],[Producto]],'[1]Costo Materia Prima'!A$3:K$424,9,FALSE),"-") -> Verificado | L8: =_xlfn.IFNA(VLOOKUP(TablaPrecios[[#This Row],[Producto]],'[1]Costo Materia Prima'!A$3:K$424,11,FALSE),"") -> 46042
D9: Limón | F9: =_xlfn.IFNA(VLOOKUP(TablaPrecios[[#This Row],[Producto]],'[1]Costo Materia Prima'!A$3:K$424,3,FALSE),"") -> 3.74 | G9: =_xlfn.IFNA(VLOOKUP(TablaPrecios[[#This Row],[Producto]],'[1]Costo Materia Prima'!A$3:K$424,4,FALSE),"") -> KG | H9: =_xlfn.IFNA(VLOOKUP(TablaPrecios[[#This Row],[Producto]],'[1]Costo Materia Prima'!A$3:K$424,5,FALSE),"") -> 100.98 | I9: =IFERROR(TablaPrecios[[#This Row],[Precio]]/TablaPrecios[[#This Row],[Cantidad]],0) -> 27 | J9: =_xlfn.IFNA(VLOOKUP(TablaPrecios[[#This Row],[Producto]],'[1]Costo Materia Prima'!A$3:K$424,8,FALSE),"") -> KG | K9: =_xlfn.IFNA(VLOOKUP(TablaPrecios[[#This Row],[Producto]],'[1]Costo Materia Prima'!A$3:K$424,9,FALSE),"-") -> Verificado | L9: =_xlfn.IFNA(VLOOKUP(TablaPrecios[[#This Row],[Producto]],'[1]Costo Materia Prima'!A$3:K$424,11,FALSE),"") -> 46024
A10: Aceites Grasas y Derivados | B10: Aceites | D10: Aceite | E10: Aceite Cristal Puro de Maiz (cartón con 12 envases de1 Lt) | F10: =_xlfn.IFNA(VLOOKUP(TablaPrecios[[#This Row],[Producto]],'[1]Costo Materia Prima'!A$3:K$424,3,FALSE),"") -> 160 | G10: =_xlfn.IFNA(VLOOKUP(TablaPrecios[[#This Row],[Producto]],'[1]Costo Materia Prima'!A$3:K$424,4,FALSE),"") -> LT | H10: =_xlfn.IFNA(VLOOKUP(TablaPrecios[[#This Row],[Producto]],'[1]Costo Materia Prima'!A$3:K$424,5,FALSE),"") -> 6560 | I10: =IFERROR(TablaPrecios[[#This Row],[Precio]]/TablaPrecios[[#This Row],[Cantidad]],0) -> 41 | J10: =_xlfn.IFNA(VLOOKUP(TablaPrecios[[#This Row],[Producto]],'[1]Costo Materia Prima'!A$3:K$424,8,FALSE),"") -> LT | K10: =_xlfn.IFNA(VLOOKUP(TablaPrecios[[#This Row],[Producto]],'[1]Costo Materia Prima'!A$3:K$424,9,FALSE),"-") -> Verificado | L10: =_xlfn.IFNA(VLOOKUP(TablaPrecios[[#This Row],[Producto]],'[1]Costo Materia Prima'!A$3:K$424,11,FALSE),"") -> 46042
A11: Abarrotera Santa Cruz | B11: Santa Cruz | D11: Mermelada Fresa Preparada | E11: Mermelada Fresa Preparada 40 LB | F11: =_xlfn.IFNA(VLOOKUP(TablaPrecios[[#This Row],[Producto]],'[1]Costo Materia Prima'!A$3:K$424,3,FALSE),"") -> 126 | G11: =_xlfn.IFNA(VLOOKUP(TablaPrecios[[#This Row],[Producto]],'[1]Costo Materia Prima'!A$3:K$424,4,FALSE),"") -> KG | H11: =_xlfn.IFNA(VLOOKUP(TablaPrecios[[#This Row],[Producto]],'[1]Costo Materia Prima'!A$3:K$424,5,FALSE),"") -> 9668.75 | I11: =IFERROR(TablaPrecios[[#This Row],[Precio]]/TablaPrecios[[#This Row],[Cantidad]],0) -> 76.736111 | J11: =_xlfn.IFNA(VLOOKUP(TablaPrecios[[#This Row],[Producto]],'[1]Costo Materia Prima'!A$3:K$424,8,FALSE),"") -> KG | K11: =_xlfn.IFNA(VLOOKUP(TablaPrecios[[#This Row],[Producto]],'[1]Costo Materia Prima'!A$3:K$424,9,FALSE),"-") -> Verificado | L11: =_xlfn.IFNA(VLOOKUP(TablaPrecios[[#This Row],[Producto]],'[1]Costo Materia Prima'!A$3:K$424,11,FALSE),"") -> 46024
A12: Alegría de Guadalajara | B12: Alegría | D12: Gragea Colores | E12: Confetti Sequins (2.27 kg) | F12: =_xlfn.IFNA(VLOOKUP(TablaPrecios[[#This Row],[Producto]],'[1]Costo Materia Prima'!A$3:K$424,3,FALSE),"") -> 0 | G12: =_xlfn.IFNA(VLOOKUP(TablaPrecios[[#This Row],[Producto]],'[1]Costo Materia Prima'!A$3:K$424,4,FALSE),"") -> KG | H12: =_xlfn.IFNA(VLOOKUP(TablaPrecios[[#This Row],[Producto]],'[1]Costo Materia Prima'!A$3:K$424,5,FALSE),"") -> 0 | I12: =IFERROR(TablaPrecios[[#This Row],[Precio]]/TablaPrecios[[#This Row],[Cantidad]],0) -> 0 | J12: =_xlfn.IFNA(VLOOKUP(TablaPrecios[[#This Row],[Producto]],'[1]Costo Materia Prima'!A$3:K$424,8,FALSE),"") -> KG | K12: =_xlfn.IFNA(VLOOKUP(TablaPrecios[[#This Row],[Producto]],'[1]Costo Materia Prima'!A$3:K$424,9,FALSE),"-") -> Verificado | L12: =_xlfn.IFNA(VLOOKUP(TablaPrecios[[#This Row],[Producto]],'[1]Costo Materia Prima'!A$3:K$424,11,FALSE),"") -> 46024
A13: Alegría de Guadalajara | B13: Alegría | D13: Grageas Bright | E13: Confeti Sequins Bright 2.2 Kg | F13: =_xlfn.IFNA(VLOOKUP(TablaPrecios[[#This Row],[Producto]],'[1]Costo Materia Prima'!A$3:K$424,3,FALSE),"") -> 0 | G13: =_xlfn.IFNA(VLOOKUP(TablaPrecios[[#This Row],[Producto]],'[1]Costo Materia Prima'!A$3:K$424,4,FALSE),"") -> KG | H13: =_xlfn.IFNA(VLOOKUP(TablaPrecios[[#This Row],[Producto]],'[1]Costo Materia Prima'!A$3:K$424,5,FALSE),"") -> 0 | I13: =IFERROR(TablaPrecios[[#This Row],[Precio]]/TablaPrecios[[#This Row],[Cantidad]],0) -> 0 | J13: =_xlfn.IFNA(VLOOKUP(TablaPrecios[[#This Row],[Producto]],'[1]Costo Materia Prima'!A$3:K$424,8,FALSE),"") -> KG | K13: =_xlfn.IFNA(VLOOKUP(TablaPrecios[[#This Row],[Producto]],'[1]Costo Materia Prima'!A$3:K$424,9,FALSE),"-") -> Verificado | L13: =_xlfn.IFNA(VLOOKUP(TablaPrecios[[#This Row],[Producto]],'[1]Costo Materia Prima'!A$3:K$424,11,FALSE),"") -> 46024
A14: Alegría de Guadalajara | B14: Alegría | D14: Colorante Rojo | E14: Colorante en gel color rojo (Super Ed) | F14: =_xlfn.IFNA(VLOOKUP(TablaPrecios[[#This Row],[Producto]],'[1]Costo Materia Prima'!A$3:K$424,3,FALSE),"") -> 0.62 | G14: =_xlfn.IFNA(VLOOKUP(TablaPrecios[[#This Row],[Producto]],'[1]Costo Materia Prima'!A$3:K$424,4,FALSE),"") -> KG | H14: =_xlfn.IFNA(VLOOKUP(TablaPrecios[[#This Row],[Producto]],'[1]Costo Materia Prima'!A$3:K$424,5,FALSE),"") -> 313.21 | I14: =IFERROR(TablaPrecios[[#This Row],[Precio]]/TablaPrecios[[#This Row],[Cantidad]],0) -> 505.17742 | J14: =_xlfn.IFNA(VLOOKUP(TablaPrecios[[#This Row],[Producto]],'[1]Costo Materia Prima'!A$3:K$424,8,FALSE),"") -> KG | K14: =_xlfn.IFNA(VLOOKUP(TablaPrecios[[#This Row],[Producto]],'[1]Costo Materia Prima'!A$3:K$424,9,FALSE),"-") -> Verificado | L14: =_xlfn.IFNA(VLOOKUP(TablaPrecios[[#This Row],[Producto]],'[1]Costo Materia Prima'!A$3:K$424,11,FALSE),"") -> 46042
A15: Alegría de Guadalajara | B15: Alegría | D15: Corazon Perla | F15: =_xlfn.IFNA(VLOOKUP(TablaPrecios[[#This Row],[Producto]],'[1]Costo Materia Prima'!A$3:K$424,3,FALSE),"") -> 0 | G15: =_xlfn.IFNA(VLOOKUP(TablaPrecios[[#This Row],[Producto]],'[1]Costo Materia Prima'!A$3:K$424,4,FALSE),"") -> KG | H15: =_xlfn.IFNA(VLOOKUP(TablaPrecios[[#This Row],[Producto]],'[1]Costo Materia Prima'!A$3:K$424,5,FALSE),"") -> 0 | I15: =IFERROR(TablaPrecios[[#This Row],[Precio]]/TablaPrecios[[#This Row],[Cantidad]],0) -> 0 | J15: =_xlfn.IFNA(VLOOKUP(TablaPrecios[[#This Row],[Producto]],'[1]Costo Materia Prima'!A$3:K$424,8,FALSE),"") -> KG | K15: =_xlfn.IFNA(VLOOKUP(TablaPrecios[[#This Row],[Producto]],'[1]Costo Materia Prima'!A$3:K$424,9,FALSE),"-") -> Verificado | L15: =_xlfn.IFNA(VLOOKUP(TablaPrecios[[#This Row],[Producto]],'[1]Costo Materia Prima'!A$3:K$424,11,FALSE),"") -> 45940
A16: Alegría de Guadalajara | B16: Alegría | D16: Mini Corazon | F16: =_xlfn.IFNA(VLOOKUP(TablaPrecios[[#This Row],[Producto]],'[1]Costo Materia Prima'!A$3:K$424,3,FALSE),"") -> 0 | G16: =_xlfn.IFNA(VLOOKUP(TablaPrecios[[#This Row],[Producto]],'[1]Costo Materia Prima'!A$3:K$424,4,FALSE),"") -> KG | H16: =_xlfn.IFNA(VLOOKUP(TablaPrecios[[#This Row],[Producto]],'[1]Costo Materia Prima'!A$3:K$424,5,FALSE),"") -> 0 | I16: =IFERROR(TablaPrecios[[#This Row],[Precio]]/TablaPrecios[[#This Row],[Cantidad]],0) -> 0 | J16: =_xlfn.IFNA(VLOOKUP(TablaPrecios[[#This Row],[Producto]],'[1]Costo Materia Prima'!A$3:K$424,8,FALSE),"") -> KG | K16: =_xlfn.IFNA(VLOOKUP(TablaPrecios[[#This Row],[Producto]],'[1]Costo Materia Prima'!A$3:K$424,9,FALSE),"-") -> Verificado | L16: =_xlfn.IFNA(VLOOKUP(TablaPrecios[[#This Row],[Producto]],'[1]Costo Materia Prima'!A$3:K$424,11,FALSE),"") -> 46024
A17: Alegría de Guadalajara | B17: Alegría | D17: ROJOBLANCOROSA | F17: =_xlfn.IFNA(VLOOKUP(TablaPrecios[[#This Row],[Producto]],'[1]Costo Materia Prima'!A$3:K$424,3,FALSE),"") -> 0 | G17: =_xlfn.IFNA(VLOOKUP(TablaPrecios[[#This Row],[Producto]],'[1]Costo Materia Prima'!A$3:K$424,4,FALSE),"") -> KG | H17: =_xlfn.IFNA(VLOOKUP(TablaPrecios[[#This Row],[Producto]],'[1]Costo Materia Prima'!A$3:K$424,5,FALSE),"") -> 0 | I17: =IFERROR(TablaPrecios[[#This Row],[Precio]]/TablaPrecios[[#This Row],[Cantidad]],0) -> 0 | J17: =_xlfn.IFNA(VLOOKUP(TablaPrecios[[#This Row],[Producto]],'[1]Costo Materia Prima'!A$3:K$424,8,FALSE),"") -> kg | K17: =_xlfn.IFNA(VLOOKUP(TablaPrecios[[#This Row],[Producto]],'[1]Costo Materia Prima'!A$3:K$424,9,FALSE),"-") -> Verificado | L17: =_xlfn.IFNA(VLOOKUP(TablaPrecios[[#This Row],[Producto]],'[1]Costo Materia Prima'!A$3:K$424,11,FALSE),"") -> 45940
A18: Agrofesas | B18: Agrofresas | D18: Fresa | E18: Caja de fresas (1 caja de 5-6 kg a $300) | F18: =_xlfn.IFNA(VLOOKUP(TablaPrecios[[#This Row],[Producto]],'[1]Costo Materia Prima'!A$3:K$424,3,FALSE),"") -> 133.18 | G18: =_xlfn.IFNA(VLOOKUP(TablaPrecios[[#This Row],[Producto]],'[1]Costo Materia Prima'!A$3:K$424,4,FALSE),"") -> Kg | H18: =_xlfn.IFNA(VLOOKUP(TablaPrecios[[#This Row],[Producto]],'[1]Costo Materia Prima'!A$3:K$424,5,FALSE),"") -> 12000 | I18: =IFERROR(TablaPrecios[[#This Row],[Precio]]/TablaPrecios[[#This Row],[Cantidad]],0) -> 90.103619 | J18: =_xlfn.IFNA(VLOOKUP(TablaPrecios[[#This Row],[Producto]],'[1]Costo Materia Prima'!A$3:K$424,8,FALSE),"") -> KG | K18: =_xlfn.IFNA(VLOOKUP(TablaPrecios[[#This Row],[Producto]],'[1]Costo Materia Prima'!A$3:K$424,9,FALSE),"-") -> Verificado | L18: =_xlfn.IFNA(VLOOKUP(TablaPrecios[[#This Row],[Producto]],'[1]Costo Materia Prima'!A$3:K$424,11,FALSE),"") -> 46042 | M18: Minimo y máx del 2024 entre 2 más un margen del 15%.
A19: Barcel | B19: Barcel | C19: Bubulubu | D19: Bubulubu | E19: Chocolate bubulubu | F19: =_xlfn.IFNA(VLOOKUP(TablaPrecios[[#This Row],[Producto]],'[1]Costo Materia Prima'!A$3:K$424,3,FALSE),"") -> 0 | G19: =_xlfn.IFNA(VLOOKUP(TablaPrecios[[#This Row],[Producto]],'[1]Costo Materia Prima'!A$3:K$424,4,FALSE),"") -> KG | H19: =_xlfn.IFNA(VLOOKUP(TablaPrecios[[#This Row],[Producto]],'[1]Costo Materia Prima'!A$3:K$424,5,FALSE),"") -> 0 | I19: =IFERROR(TablaPrecios[[#This Row],[Precio]]/TablaPrecios[[#This Row],[Cantidad]],0) -> 0 | J19: =_xlfn.IFNA(VLOOKUP(TablaPrecios[[#This Row],[Producto]],'[1]Costo Materia Prima'!A$3:K$424,8,FALSE),"") -> KG | K19: =_xlfn.IFNA(VLOOKUP(TablaPrecios[[#This Row],[Producto]],'[1]Costo Materia Prima'!A$3:K$424,9,FALSE),"-") -> Verificado | L19: =_xlfn.IFNA(VLOOKUP(TablaPrecios[[#This Row],[Producto]],'[1]Costo Materia Prima'!A$3:K$424,11,FALSE),"") -> 46024
A20: Casa Elina | B20: Elina | C20: 29519052102 | D20: Coco | E20: Coco Suave Rallado FSI-Dawn | F20: =_xlfn.IFNA(VLOOKUP(TablaPrecios[[#This Row],[Producto]],'[1]Costo Materia Prima'!A$3:K$424,3,FALSE),"") -> 0 | G20: =_xlfn.IFNA(VLOOKUP(TablaPrecios[[#This Row],[Producto]],'[1]Costo Materia Prima'!A$3:K$424,4,FALSE),"") -> KG | H20: =_xlfn.IFNA(VLOOKUP(TablaPrecios[[#This Row],[Producto]],'[1]Costo Materia Prima'!A$3:K$424,5,FALSE),"") -> 0 | I20: =IFERROR(TablaPrecios[[#This Row],[Precio]]/TablaPrecios[[#This Row],[Cantidad]],0) -> 0 | J20: =_xlfn.IFNA(VLOOKUP(TablaPrecios[[#This Row],[Producto]],'[1]Costo Materia Prima'!A$3:K$424,8,FALSE),"") -> KG | K20: =_xlfn.IFNA(VLOOKUP(TablaPrecios[[#This Row],[Producto]],'[1]Costo Materia Prima'!A$3:K$424,9,FALSE),"-") -> Verificado | L20: =_xlfn.IFNA(VLOOKUP(TablaPrecios[[#This Row],[Producto]],'[1]Costo Materia Prima'!A$3:K$424,11,FALSE),"") -> 46024
A21: Casa Elina | B21: Elina | C21: 10005036 | D21: Desmoldante | E21: Desmoldante | F21: =_xlfn.IFNA(VLOOKUP(TablaPrecios[[#This Row],[Producto]],'[1]Costo Materia Prima'!A$3:K$424,3,FALSE),"") -> 0 | G21: =_xlfn.IFNA(VLOOKUP(TablaPrecios[[#This Row],[Producto]],'[1]Costo Materia Prima'!A$3:K$424,4,FALSE),"") -> LT | H21: =_xlfn.IFNA(VLOOKUP(TablaPrecios[[#This Row],[Producto]],'[1]Costo Materia Prima'!A$3:K$424,5,FALSE),"") -> 2399 | I21: =IFERROR(TablaPrecios[[#This Row],[Precio]]/TablaPrecios[[#This Row],[Cantidad]],0) -> 0 | J21: =_xlfn.IFNA(VLOOKUP(TablaPrecios[[#This Row],[Producto]],'[1]Costo Materia Prima'!A$3:K$424,8,FALSE),"") -> LT | K21: =_xlfn.IFNA(VLOOKUP(TablaPrecios[[#This Row],[Producto]],'[1]Costo Materia Prima'!A$3:K$424,9,FALSE),"-") -> Verificado | L21: =_xlfn.IFNA(VLOOKUP(TablaPrecios[[#This Row],[Producto]],'[1]Costo Materia Prima'!A$3:K$424,11,FALSE),"") -> 46024
A22: Casa Elina | B22: Elina | C22: 19900003554 | D22: Royal | E22: Polvo para hornear | F22: =_xlfn.IFNA(VLOOKUP(TablaPrecios[[#This Row],[Producto]],'[1]Costo Materia Prima'!A$3:K$424,3,FALSE),"") -> 80 | G22: =_xlfn.IFNA(VLOOKUP(TablaPrecios[[#This Row],[Producto]],'[1]Costo Materia Prima'!A$3:K$424,4,FALSE),"") -> KG | H22: =_xlfn.IFNA(VLOOKUP(TablaPrecios[[#This Row],[Producto]],'[1]Costo Materia Prima'!A$3:K$424,5,FALSE),"") -> 2835 | I22: =IFERROR(TablaPrecios[[#This Row],[Precio]]/TablaPrecios[[#This Row],[Cantidad]],0) -> 35.4375 | J22: =_xlfn.IFNA(VLOOKUP(TablaPrecios[[#This Row],[Producto]],'[1]Costo Materia Prima'!A$3:K$424,8,FALSE),"") -> KG | K22: =_xlfn.IFNA(VLOOKUP(TablaPrecios[[#This Row],[Producto]],'[1]Costo Materia Prima'!A$3:K$424,9,FALSE),"-") -> Verificado | L22: =_xlfn.IFNA(VLOOKUP(TablaPrecios[[#This Row],[Producto]],'[1]Costo Materia Prima'!A$3:K$424,11,FALSE),"") -> 46042
A23: Casa Elina | B23: Elina | D23: Relleno Mora Azul | E23: Relleno Mora Azul Premium American Donut | F23: =_xlfn.IFNA(VLOOKUP(TablaPrecios[[#This Row],[Producto]],'[1]Costo Materia Prima'!A$3:K$424,3,FALSE),"") -> 13.5 | G23: =_xlfn.IFNA(VLOOKUP(TablaPrecios[[#This Row],[Producto]],'[1]Costo Materia Prima'!A$3:K$424,4,FALSE),"") -> KG | H23: =_xlfn.IFNA(VLOOKUP(TablaPrecios[[#This Row],[Producto]],'[1]Costo Materia Prima'!A$3:K$424,5,FALSE),"") -> 1917 | I23: =IFERROR(TablaPrecios[[#This Row],[Precio]]/TablaPrecios[[#This Row],[Cantidad]],0) -> 142 | J23: =_xlfn.IFNA(VLOOKUP(TablaPrecios[[#This Row],[Producto]],'[1]Costo Materia Prima'!A$3:K$424,8,FALSE),"") -> KG | K23: =_xlfn.IFNA(VLOOKUP(TablaPrecios[[#This Row],[Producto]],'[1]Costo Materia Prima'!A$3:K$424,9,FALSE),"-") -> Verificado | L23: =_xlfn.IFNA(VLOOKUP(TablaPrecios[[#This Row],[Producto]],'[1]Costo Materia Prima'!A$3:K$424,11,FALSE),"") -> 46024
A24: Casa Elina | B24: Elina | C24: 33200011927 | D24: Bicarbonato | E24: Bicarbonato | F24: =_xlfn.IFNA(VLOOKUP(TablaPrecios[[#This Row],[Producto]],'[1]Costo Materia Prima'!A$3:K$424,3,FALSE),"") -> 10 | G24: =_xlfn.IFNA(VLOOKUP(TablaPrecios[[#This Row],[Producto]],'[1]Costo Materia Prima'!A$3:K$424,4,FALSE),"") -> KG | H24: =_xlfn.IFNA(VLOOKUP(TablaPrecios[[#This Row],[Producto]],'[1]Costo Materia Prima'!A$3:K$424,5,FALSE),"") -> 384 | I24: =IFERROR(TablaPrecios[[#This Row],[Precio]]/TablaPrecios[[#This Row],[Cantidad]],0) -> 38.4 | J24: =_xlfn.IFNA(VLOOKUP(TablaPrecios[[#This Row],[Producto]],'[1]Costo Materia Prima'!A$3:K$424,8,FALSE),"") -> KG | K24: =_xlfn.IFNA(VLOOKUP(TablaPrecios[[#This Row],[Producto]],'[1]Costo Materia Prima'!A$3:K$424,9,FALSE),"-") -> Verificado | L24: =_xlfn.IFNA(VLOOKUP(TablaPrecios[[#This Row],[Producto]],'[1]Costo Materia Prima'!A$3:K$424,11,FALSE),"") -> 46042
A25: Casa Ley | B25: Ley | E25: Kiwi | F25: =_xlfn.IFNA(VLOOKUP(TablaPrecios[[#This Row],[Producto]],'[1]Costo Materia Prima'!A$3:K$424,3,FALSE),"") | G25: =_xlfn.IFNA(VLOOKUP(TablaPrecios[[#This Row],[Producto]],'[1]Costo Materia Prima'!A$3:K$424,4,FALSE),"") | H25: =_xlfn.IFNA(VLOOKUP(TablaPrecios[[#This Row],[Producto]],'[1]Costo Materia Prima'!A$3:K$424,5,FALSE),"") | I25: =IFERROR(TablaPrecios[[#This Row],[Precio]]/TablaPrecios[[#This Row],[Cantidad]],0) -> 0 | J25: =_xlfn.IFNA(VLOOKUP(TablaPrecios[[#This Row],[Producto]],'[1]Costo Materia Prima'!A$3:K$424,8,FALSE),"") | K25: =_xlfn.IFNA(VLOOKUP(TablaPrecios[[#This Row],[Producto]],'[1]Costo Materia Prima'!A$3:K$424,9,FALSE),"-") -> - | L25: =_xlfn.IFNA(VLOOKUP(TablaPrecios[[#This Row],[Producto]],'[1]Costo Materia Prima'!A$3:K$424,11,FALSE),"")
A26: Casa Ley | B26: Ley | E26: Uva | F26: =_xlfn.IFNA(VLOOKUP(TablaPrecios[[#This Row],[Producto]],'[1]Costo Materia Prima'!A$3:K$424,3,FALSE),"") | G26: =_xlfn.IFNA(VLOOKUP(TablaPrecios[[#This Row],[Producto]],'[1]Costo Materia Prima'!A$3:K$424,4,FALSE),"") | H26: =_xlfn.IFNA(VLOOKUP(TablaPrecios[[#This Row],[Producto]],'[1]Costo Materia Prima'!A$3:K$424,5,FALSE),"") | I26: =IFERROR(TablaPrecios[[#This Row],[Precio]]/TablaPrecios[[#This Row],[Cantidad]],0) -> 0 | J26: =_xlfn.IFNA(VLOOKUP(TablaPrecios[[#This Row],[Producto]],'[1]Costo Materia Prima'!A$3:K$424,8,FALSE),"") | K26: =_xlfn.IFNA(VLOOKUP(TablaPrecios[[#This Row],[Producto]],'[1]Costo Materia Prima'!A$3:K$424,9,FALSE),"-") -> - | L26: =_xlfn.IFNA(VLOOKUP(TablaPrecios[[#This Row],[Producto]],'[1]Costo Materia Prima'!A$3:K$424,11,FALSE),"")
A27: Casa Estampa | B27: Casa Estampa | D27: Liston Palmita | E27: Liston con Logo Dolce palmita algodón 150 metros | F27: =_xlfn.IFNA(VLOOKUP(TablaPrecios[[#This Row],[Producto]],'[1]Costo Materia Prima'!A$3:K$424,3,FALSE),"") -> 50000 | G27: =_xlfn.IFNA(VLOOKUP(TablaPrecios[[#This Row],[Producto]],'[1]Costo Materia Prima'!A$3:K$424,4,FALSE),"") -> CM | H27: =_xlfn.IFNA(VLOOKUP(TablaPrecios[[#This Row],[Producto]],'[1]Costo Materia Prima'!A$3:K$424,5,FALSE),"") -> 7622.8 | I27: =IFERROR(TablaPrecios[[#This Row],[Precio]]/TablaPrecios[[#This Row],[Cantidad]],0) -> 0.152456 | J27: =_xlfn.IFNA(VLOOKUP(TablaPrecios[[#This Row],[Producto]],'[1]Costo Materia Prima'!A$3:K$424,8,FALSE),"") -> CM | K27: =_xlfn.IFNA(VLOOKUP(TablaPrecios[[#This Row],[Producto]],'[1]Costo Materia Prima'!A$3:K$424,9,FALSE),"-") -> Verificado | L27: =_xlfn.IFNA(VLOOKUP(TablaPrecios[[#This Row],[Producto]],'[1]Costo Materia Prima'!A$3:K$424,11,FALSE),"") -> 46024
D28: Arandano | E28: Arandano KG | F28: =_xlfn.IFNA(VLOOKUP(TablaPrecios[[#This Row],[Producto]],'[1]Costo Materia Prima'!A$3:K$424,3,FALSE),"") -> 15 | G28: =_xlfn.IFNA(VLOOKUP(TablaPrecios[[#This Row],[Producto]],'[1]Costo Materia Prima'!A$3:K$424,4,FALSE),"") -> KG | H28: =_xlfn.IFNA(VLOOKUP(TablaPrecios[[#This Row],[Producto]],'[1]Costo Materia Prima'!A$3:K$424,5,FALSE),"") -> 1800 | I28: =IFERROR(TablaPrecios[[#This Row],[Precio]]/TablaPrecios[[#This Row],[Cantidad]],0) -> 120 | J28: =_xlfn.IFNA(VLOOKUP(TablaPrecios[[#This Row],[Producto]],'[1]Costo Materia Prima'!A$3:K$424,8,FALSE),"") -> KG | K28: =_xlfn.IFNA(VLOOKUP(TablaPrecios[[#This Row],[Producto]],'[1]Costo Materia Prima'!A$3:K$424,9,FALSE),"-") -> Verificado | L28: =_xlfn.IFNA(VLOOKUP(TablaPrecios[[#This Row],[Producto]],'[1]Costo Materia Prima'!A$3:K$424,11,FALSE),"") -> 46042
A29: Comercializadora Beili | B29: Beili | D29: Coco Rallado | E29: Coco Rallado | F29: =_xlfn.IFNA(VLOOKUP(TablaPrecios[[#This Row],[Producto]],'[1]Costo Materia Prima'!A$3:K$424,3,FALSE),"") -> 10 | G29: =_xlfn.IFNA(VLOOKUP(TablaPrecios[[#This Row],[Producto]],'[1]Costo Materia Prima'!A$3:K$424,4,FALSE),"") -> KG | H29: =_xlfn.IFNA(VLOOKUP(TablaPrecios[[#This Row],[Producto]],'[1]Costo Materia Prima'!A$3:K$424,5,FALSE),"") -> 990 | I29: =IFERROR(TablaPrecios[[#This Row],[Precio]]/TablaPrecios[[#This Row],[Cantidad]],0) -> 99 | J29: =_xlfn.IFNA(VLOOKUP(TablaPrecios[[#This Row],[Producto]],'[1]Costo Materia Prima'!A$3:K$424,8,FALSE),"") -> KG | K29: =_xlfn.IFNA(VLOOKUP(TablaPrecios[[#This Row],[Producto]],'[1]Costo Materia Prima'!A$3:K$424,9,FALSE),"-") -> Verificado | L29: =_xlfn.IFNA(VLOOKUP(TablaPrecios[[#This Row],[Producto]],'[1]Costo Materia Prima'!A$3:K$424,11,FALSE),"") -> 46042
B30: Beili | C30: AL-2923 | D30: Domo 3 Leches | E30: Domo 3 Leches Mediano Tapa y Charola | F30: =_xlfn.IFNA(VLOOKUP(TablaPrecios[[#This Row],[Producto]],'[1]Costo Materia Prima'!A$3:K$424,3,FALSE),"") -> 200 | G30: =_xlfn.IFNA(VLOOKUP(TablaPrecios[[#This Row],[Producto]],'[1]Costo Materia Prima'!A$3:K$424,4,FALSE),"") -> PZ | H30: =_xlfn.IFNA(VLOOKUP(TablaPrecios[[#This Row],[Producto]],'[1]Costo Materia Prima'!A$3:K$424,5,FALSE),"") -> 2494 | I30: =IFERROR(TablaPrecios[[#This Row],[Precio]]/TablaPrecios[[#This Row],[Cantidad]],0) -> 12.47 | J30: =_xlfn.IFNA(VLOOKUP(TablaPrecios[[#This Row],[Producto]],'[1]Costo Materia Prima'!A$3:K$424,8,FALSE),"") -> PZ | K30: =_xlfn.IFNA(VLOOKUP(TablaPrecios[[#This Row],[Producto]],'[1]Costo Materia Prima'!A$3:K$424,9,FALSE),"-") -> Verificado | L30: =_xlfn.IFNA(VLOOKUP(TablaPrecios[[#This Row],[Producto]],'[1]Costo Materia Prima'!A$3:K$424,11,FALSE),"") -> 46042
B31: Beili | D31: Charola 3 Leches | E31: Charola 3 Leches Mediano | F31: =_xlfn.IFNA(VLOOKUP(TablaPrecios[[#This Row],[Producto]],'[1]Costo Materia Prima'!A$3:K$424,3,FALSE),"") -> 0 | G31: =_xlfn.IFNA(VLOOKUP(TablaPrecios[[#This Row],[Producto]],'[1]Costo Materia Prima'!A$3:K$424,4,FALSE),"") -> PZ | H31: =_xlfn.IFNA(VLOOKUP(TablaPrecios[[#This Row],[Producto]],'[1]Costo Materia Prima'!A$3:K$424,5,FALSE),"") -> 0 | I31: =IFERROR(TablaPrecios[[#This Row],[Precio]]/TablaPrecios[[#This Row],[Cantidad]],0) -> 0 | J31: =_xlfn.IFNA(VLOOKUP(TablaPrecios[[#This Row],[Producto]],'[1]Costo Materia Prima'!A$3:K$424,8,FALSE),"") -> PZ | K31: =_xlfn.IFNA(VLOOKUP(TablaPrecios[[#This Row],[Producto]],'[1]Costo Materia Prima'!A$3:K$424,9,FALSE),"-") -> Verificado | L31: =_xlfn.IFNA(VLOOKUP(TablaPrecios[[#This Row],[Producto]],'[1]Costo Materia Prima'!A$3:K$424,11,FALSE),"") -> 46024
A32: Comercializadora Beili | B32: Beili | D32: Nuez Granillo | E32: Nuez Granillo | F32: =_xlfn.IFNA(VLOOKUP(TablaPrecios[[#This Row],[Producto]],'[1]Costo Materia Prima'!A$3:K$424,3,FALSE),"") -> 20 | G32: =_xlfn.IFNA(VLOOKUP(TablaPrecios[[#This Row],[Producto]],'[1]Costo Materia Prima'!A$3:K$424,4,FALSE),"") -> KG | H32: =_xlfn.IFNA(VLOOKUP(TablaPrecios[[#This Row],[Producto]],'[1]Costo Materia Prima'!A$3:K$424,5,FALSE),"") -> 3980 | I32: =IFERROR(TablaPrecios[[#This Row],[Precio]]/TablaPrecios[[#This Row],[Cantidad]],0) -> 199 | J32: =_xlfn.IFNA(VLOOKUP(TablaPrecios[[#This Row],[Producto]],'[1]Costo Materia Prima'!A$3:K$424,8,FALSE),"") -> KG | K32: =_xlfn.IFNA(VLOOKUP(TablaPrecios[[#This Row],[Producto]],'[1]Costo Materia Prima'!A$3:K$424,9,FALSE),"-") -> Verificado | L32: =_xlfn.IFNA(VLOOKUP(TablaPrecios[[#This Row],[Producto]],'[1]Costo Materia Prima'!A$3:K$424,11,FALSE),"") -> 46042
A33: Comercializadora Beili | B33: Beili | D33: Nuez Picada | E33: Nuez Picada | F33: =_xlfn.IFNA(VLOOKUP(TablaPrecios[[#This Row],[Producto]],'[1]Costo Materia Prima'!A$3:K$424,3,FALSE),"") -> 20 | G33: =_xlfn.IFNA(VLOOKUP(TablaPrecios[[#This Row],[Producto]],'[1]Costo Materia Prima'!A$3:K$424,4,FALSE),"") -> KG | H33: =_xlfn.IFNA(VLOOKUP(TablaPrecios[[#This Row],[Producto]],'[1]Costo Materia Prima'!A$3:K$424,5,FALSE),"") -> 4380 | I33: =IFERROR(TablaPrecios[[#This Row],[Precio]]/TablaPrecios[[#This Row],[Cantidad]],0) -> 219 | J33: =_xlfn.IFNA(VLOOKUP(TablaPrecios[[#This Row],[Producto]],'[1]Costo Materia Prima'!A$3:K$424,8,FALSE),"") -> KG | K33: =_xlfn.IFNA(VLOOKUP(TablaPrecios[[#This Row],[Producto]],'[1]Costo Materia Prima'!A$3:K$424,9,FALSE),"-") -> Verificado | L33: =_xlfn.IFNA(VLOOKUP(TablaPrecios[[#This Row],[Producto]],'[1]Costo Materia Prima'!A$3:K$424,11,FALSE),"") -> 46042
A34: Centro Mercado Gve | D34: Avena | E34: Avena | F34: =_xlfn.IFNA(VLOOKUP(TablaPrecios[[#This Row],[Producto]],'[1]Costo Materia Prima'!A$3:K$424,3,FALSE),"") -> 4 | G34: =_xlfn.IFNA(VLOOKUP(TablaPrecios[[#This Row],[Producto]],'[1]Costo Materia Prima'!A$3:K$424,4,FALSE),"") -> KG | H34: =_xlfn.IFNA(VLOOKUP(TablaPrecios[[#This Row],[Producto]],'[1]Costo Materia Prima'!A$3:K$424,5,FALSE),"") -> 107.12 | I34: =IFERROR(TablaPrecios[[#This Row],[Precio]]/TablaPrecios[[#This Row],[Cantidad]],0) -> 26.78 | J34: =_xlfn.IFNA(VLOOKUP(TablaPrecios[[#This Row],[Producto]],'[1]Costo Materia Prima'!A$3:K$424,8,FALSE),"") -> KG | K34: =_xlfn.IFNA(VLOOKUP(TablaPrecios[[#This Row],[Producto]],'[1]Costo Materia Prima'!A$3:K$424,9,FALSE),"-") -> Verificado | L34: =_xlfn.IFNA(VLOOKUP(TablaPrecios[[#This Row],[Producto]],'[1]Costo Materia Prima'!A$3:K$424,11,FALSE),"") -> 46024
A35: Centro Mercado Gve | E35: Arándanos | F35: =_xlfn.IFNA(VLOOKUP(TablaPrecios[[#This Row],[Producto]],'[1]Costo Materia Prima'!A$3:K$424,3,FALSE),"") | G35: =_xlfn.IFNA(VLOOKUP(TablaPrecios[[#This Row],[Producto]],'[1]Costo Materia Prima'!A$3:K$424,4,FALSE),"") | H35: =_xlfn.IFNA(VLOOKUP(TablaPrecios[[#This Row],[Producto]],'[1]Costo Materia Prima'!A$3:K$424,5,FALSE),"") | I35: =IFERROR(TablaPrecios[[#This Row],[Precio]]/TablaPrecios[[#This Row],[Cantidad]],0) -> 0 | J35: =_xlfn.IFNA(VLOOKUP(TablaPrecios[[#This Row],[Producto]],'[1]Costo Materia Prima'!A$3:K$424,8,FALSE),"") | K35: =_xlfn.IFNA(VLOOKUP(TablaPrecios[[#This Row],[Producto]],'[1]Costo Materia Prima'!A$3:K$424,9,FALSE),"-") -> - | L35: =_xlfn.IFNA(VLOOKUP(TablaPrecios[[#This Row],[Producto]],'[1]Costo Materia Prima'!A$3:K$424,11,FALSE),"")
A36: Centro Mercado Gve | E36: Dátil | F36: =_xlfn.IFNA(VLOOKUP(TablaPrecios[[#This Row],[Producto]],'[1]Costo Materia Prima'!A$3:K$424,3,FALSE),"") | G36: =_xlfn.IFNA(VLOOKUP(TablaPrecios[[#This Row],[Producto]],'[1]Costo Materia Prima'!A$3:K$424,4,FALSE),"") | H36: =_xlfn.IFNA(VLOOKUP(TablaPrecios[[#This Row],[Producto]],'[1]Costo Materia Prima'!A$3:K$424,5,FALSE),"") | I36: =IFERROR(TablaPrecios[[#This Row],[Precio]]/TablaPrecios[[#This Row],[Cantidad]],0) -> 0 | J36: =_xlfn.IFNA(VLOOKUP(TablaPrecios[[#This Row],[Producto]],'[1]Costo Materia Prima'!A$3:K$424,8,FALSE),"") | K36: =_xlfn.IFNA(VLOOKUP(TablaPrecios[[#This Row],[Producto]],'[1]Costo Materia Prima'!A$3:K$424,9,FALSE),"-") -> - | L36: =_xlfn.IFNA(VLOOKUP(TablaPrecios[[#This Row],[Producto]],'[1]Costo Materia Prima'!A$3:K$424,11,FALSE),"")
D37: Galleta Molida Lotus | E37: Galleta Molida Lotus | F37: =_xlfn.IFNA(VLOOKUP(TablaPrecios[[#This Row],[Producto]],'[1]Costo Materia Prima'!A$3:K$424,3,FALSE),"") -> 12 | G37: =_xlfn.IFNA(VLOOKUP(TablaPrecios[[#This Row],[Producto]],'[1]Costo Materia Prima'!A$3:K$424,4,FALSE),"") -> KG | H37: =_xlfn.IFNA(VLOOKUP(TablaPrecios[[#This Row],[Producto]],'[1]Costo Materia Prima'!A$3:K$424,5,FALSE),"") -> 3897.92 | I37: =IFERROR(TablaPrecios[[#This Row],[Precio]]/TablaPrecios[[#This Row],[Cantidad]],0) -> 324.82667 | J37: =_xlfn.IFNA(VLOOKUP(TablaPrecios[[#This Row],[Producto]],'[1]Costo Materia Prima'!A$3:K$424,8,FALSE),"") -> KG | K37: =_xlfn.IFNA(VLOOKUP(TablaPrecios[[#This Row],[Producto]],'[1]Costo Materia Prima'!A$3:K$424,9,FALSE),"-") -> Verificado | L37: =_xlfn.IFNA(VLOOKUP(TablaPrecios[[#This Row],[Producto]],'[1]Costo Materia Prima'!A$3:K$424,11,FALSE),"") -> 46042
D38: Galleta Lotus | E38: Galleta Lotus (barritas, consideradas en kg) | F38: =_xlfn.IFNA(VLOOKUP(TablaPrecios[[#This Row],[Producto]],'[1]Costo Materia Prima'!A$3:K$424,3,FALSE),"") -> 2.5 | G38: =_xlfn.IFNA(VLOOKUP(TablaPrecios[[#This Row],[Producto]],'[1]Costo Materia Prima'!A$3:K$424,4,FALSE),"") -> KG | H38: =_xlfn.IFNA(VLOOKUP(TablaPrecios[[#This Row],[Producto]],'[1]Costo Materia Prima'!A$3:K$424,5,FALSE),"") -> 660.87 | I38: =IFERROR(TablaPrecios[[#This Row],[Precio]]/TablaPrecios[[#This Row],[Cantidad]],0) -> 264.348 | J38: =_xlfn.IFNA(VLOOKUP(TablaPrecios[[#This Row],[Producto]],'[1]Costo Materia Prima'!A$3:K$424,8,FALSE),"") -> KG | K38: =_xlfn.IFNA(VLOOKUP(TablaPrecios[[#This Row],[Producto]],'[1]Costo Materia Prima'!A$3:K$424,9,FALSE),"-") -> Verificado | L38: =_xlfn.IFNA(VLOOKUP(TablaPrecios[[#This Row],[Producto]],'[1]Costo Materia Prima'!A$3:K$424,11,FALSE),"") -> 46042
D39: Crema Lotus | E39: Crema Lotus 8 KG | F39: =_xlfn.IFNA(VLOOKUP(TablaPrecios[[#This Row],[Producto]],'[1]Costo Materia Prima'!A$3:K$424,3,FALSE),"") -> 8 | G39: =_xlfn.IFNA(VLOOKUP(TablaPrecios[[#This Row],[Producto]],'[1]Costo Materia Prima'!A$3:K$424,4,FALSE),"") -> KG | H39: =_xlfn.IFNA(VLOOKUP(TablaPrecios[[#This Row],[Producto]],'[1]Costo Materia Prima'!A$3:K$424,5,FALSE),"") -> 2525.73 | I39: =IFERROR(TablaPrecios[[#This Row],[Precio]]/TablaPrecios[[#This Row],[Cantidad]],0) -> 315.71625 | J39: =_xlfn.IFNA(VLOOKUP(TablaPrecios[[#This Row],[Producto]],'[1]Costo Materia Prima'!A$3:K$424,8,FALSE),"") -> KG | K39: =_xlfn.IFNA(VLOOKUP(TablaPrecios[[#This Row],[Producto]],'[1]Costo Materia Prima'!A$3:K$424,9,FALSE),"-") -> Verificado | L39: =_xlfn.IFNA(VLOOKUP(TablaPrecios[[#This Row],[Producto]],'[1]Costo Materia Prima'!A$3:K$424,11,FALSE),"") -> 46042
A40: Confitados Finos Comercial | B40: Confitados | C40: B211 | D40: Azucar Glass | E40: Configlass Ref. Bls. 5 kg (Empaque con 9 bolsas c/u 5 kg) | F40: =_xlfn.IFNA(VLOOKUP(TablaPrecios[[#This Row],[Producto]],'[1]Costo Materia Prima'!A$3:K$424,3,FALSE),"") -> 550 | G40: =_xlfn.IFNA(VLOOKUP(TablaPrecios[[#This Row],[Producto]],'[1]Costo Materia Prima'!A$3:K$424,4,FALSE),"") -> KG | H40: =_xlfn.IFNA(VLOOKUP(TablaPrecios[[#This Row],[Producto]],'[1]Costo Materia Prima'!A$3:K$424,5,FALSE),"") -> 18518.76 | I40: =IFERROR(TablaPrecios[[#This Row],[Precio]]/TablaPrecios[[#This Row],[Cantidad]],0) -> 33.670473 | J40: =_xlfn.IFNA(VLOOKUP(TablaPrecios[[#This Row],[Producto]],'[1]Costo Materia Prima'!A$3:K$424,8,FALSE),"") -> KG | K40: =_xlfn.IFNA(VLOOKUP(TablaPrecios[[#This Row],[Producto]],'[1]Costo Materia Prima'!A$3:K$424,9,FALSE),"-") -> Verificado | L40: =_xlfn.IFNA(VLOOKUP(TablaPrecios[[#This Row],[Producto]],'[1]Costo Materia Prima'!A$3:K$424,11,FALSE),"") -> 46042
A41: Conservas La Costeña | B41: Costeña | C41: 7501017003167 | D41: Durazno | E41: Durazno en Mitades caja de 12/820 Gr | F41: =_xlfn.IFNA(VLOOKUP(TablaPrecios[[#This Row],[Producto]],'[1]Costo Materia Prima'!A$3:K$424,3,FALSE),"") -> 1 | G41: =_xlfn.IFNA(VLOOKUP(TablaPrecios[[#This Row],[Producto]],'[1]Costo Materia Prima'!A$3:K$424,4,FALSE),"") -> KG | H41: =_xlfn.IFNA(VLOOKUP(TablaPrecios[[#This Row],[Producto]],'[1]Costo Materia Prima'!A$3:K$424,5,FALSE),"") -> 60.08 | I41: =IFERROR(TablaPrecios[[#This Row],[Precio]]/TablaPrecios[[#This Row],[Cantidad]],0) -> 60.08 | J41: =_xlfn.IFNA(VLOOKUP(TablaPrecios[[#This Row],[Producto]],'[1]Costo Materia Prima'!A$3:K$424,8,FALSE),"") -> KG | K41: =_xlfn.IFNA(VLOOKUP(TablaPrecios[[#This Row],[Producto]],'[1]Costo Materia Prima'!A$3:K$424,9,FALSE),"-") -> Verificado | L41: =_xlfn.IFNA(VLOOKUP(TablaPrecios[[#This Row],[Producto]],'[1]Costo Materia Prima'!A$3:K$424,11,FALSE),"") -> 46024
A42: Conservas La Costeña | B42: Costeña | C42: 7501017002399 | D42: Piña | E42: Piña en trocitos cada de 6/3 KG | F42: =_xlfn.IFNA(VLOOKUP(TablaPrecios[[#This Row],[Producto]],'[1]Costo Materia Prima'!A$3:K$424,3,FALSE),"") -> 33 | G42: =_xlfn.IFNA(VLOOKUP(TablaPrecios[[#This Row],[Producto]],'[1]Costo Materia Prima'!A$3:K$424,4,FALSE),"") -> KG | H42: =_xlfn.IFNA(VLOOKUP(TablaPrecios[[#This Row],[Producto]],'[1]Costo Materia Prima'!A$3:K$424,5,FALSE),"") -> 2230 | I42: =IFERROR(TablaPrecios[[#This Row],[Precio]]/TablaPrecios[[#This Row],[Cantidad]],0) -> 67.575758 | J42: =_xlfn.IFNA(VLOOKUP(TablaPrecios[[#This Row],[Producto]],'[1]Costo Materia Prima'!A$3:K$424,8,FALSE),"") -> KG | K42: =_xlfn.IFNA(VLOOKUP(TablaPrecios[[#This Row],[Producto]],'[1]Costo Materia Prima'!A$3:K$424,9,FALSE),"-") -> Verificado | L42: =_xlfn.IFNA(VLOOKUP(TablaPrecios[[#This Row],[Producto]],'[1]Costo Materia Prima'!A$3:K$424,11,FALSE),"") -> 46024
A43: Conservas La Costeña | B43: Costeña | C43: 7501017003532 | D43: Guayaba | E43: Guayabas enteras en almibar cj de 12/800 Gr | F43: =_xlfn.IFNA(VLOOKUP(TablaPrecios[[#This Row],[Producto]],'[1]Costo Materia Prima'!A$3:K$424,3,FALSE),"") -> 13.6 | G43: =_xlfn.IFNA(VLOOKUP(TablaPrecios[[#This Row],[Producto]],'[1]Costo Materia Prima'!A$3:K$424,4,FALSE),"") -> KG | H43: =_xlfn.IFNA(VLOOKUP(TablaPrecios[[#This Row],[Producto]],'[1]Costo Materia Prima'!A$3:K$424,5,FALSE),"") -> 1037 | I43: =IFERROR(TablaPrecios[[#This Row],[Precio]]/TablaPrecios[[#This Row],[Cantidad]],0) -> 76.25 | J43: =_xlfn.IFNA(VLOOKUP(TablaPrecios[[#This Row],[Producto]],'[1]Costo Materia Prima'!A$3:K$424,8,FALSE),"") -> KG | K43: =_xlfn.IFNA(VLOOKUP(TablaPrecios[[#This Row],[Producto]],'[1]Costo Materia Prima'!A$3:K$424,9,FALSE),"-") -> Verificado | L43: =_xlfn.IFNA(VLOOKUP(TablaPrecios[[#This Row],[Producto]],'[1]Costo Materia Prima'!A$3:K$424,11,FALSE),"") -> 46042
A44: Conservas La Costeña | B44: Costeña | D44: Cocktail de Frutas | E44: Cocktel de Frutas 1/850 Gr (12 pzs) | F44: =_xlfn.IFNA(VLOOKUP(TablaPrecios[[#This Row],[Producto]],'[1]Costo Materia Prima'!A$3:K$424,3,FALSE),"") -> 20.4 | G44: =_xlfn.IFNA(VLOOKUP(TablaPrecios[[#This Row],[Producto]],'[1]Costo Materia Prima'!A$3:K$424,4,FALSE),"") -> KG | H44: =_xlfn.IFNA(VLOOKUP(TablaPrecios[[#This Row],[Producto]],'[1]Costo Materia Prima'!A$3:K$424,5,FALSE),"") -> 1371.88 | I44: =IFERROR(TablaPrecios[[#This Row],[Precio]]/TablaPrecios[[#This Row],[Cantidad]],0) -> 67.24902 | J44: =_xlfn.IFNA(VLOOKUP(TablaPrecios[[#This Row],[Producto]],'[1]Costo Materia Prima'!A$3:K$424,8,FALSE),"") -> KG | K44: =_xlfn.IFNA(VLOOKUP(TablaPrecios[[#This Row],[Producto]],'[1]Costo Materia Prima'!A$3:K$424,9,FALSE),"-") -> Verificado | L44: =_xlfn.IFNA(VLOOKUP(TablaPrecios[[#This Row],[Producto]],'[1]Costo Materia Prima'!A$3:K$424,11,FALSE),"") -> 46024
A45: Corrufacil | B45: Corrufacil | D45: Porta Vasos | E45: Porta Vasos 4 cavidades | F45: =_xlfn.IFNA(VLOOKUP(TablaPrecios[[#This Row],[Producto]],'[1]Costo Materia Prima'!A$3:K$424,3,FALSE),"") -> 600 | G45: =_xlfn.IFNA(VLOOKUP(TablaPrecios[[#This Row],[Producto]],'[1]Costo Materia Prima'!A$3:K$424,4,FALSE),"") -> PZ | H45: =_xlfn.IFNA(VLOOKUP(TablaPrecios[[#This Row],[Producto]],'[1]Costo Materia Prima'!A$3:K$424,5,FALSE),"") -> 3375.42 | I45: =IFERROR(TablaPrecios[[#This Row],[Precio]]/TablaPrecios[[#This Row],[Cantidad]],0) -> 5.6257 | J45: =_xlfn.IFNA(VLOOKUP(TablaPrecios[[#This Row],[Producto]],'[1]Costo Materia Prima'!A$3:K$424,8,FALSE),"") -> PZ | K45: =_xlfn.IFNA(VLOOKUP(TablaPrecios[[#This Row],[Producto]],'[1]Costo Materia Prima'!A$3:K$424,9,FALSE),"-") -> Verificado | L45: =_xlfn.IFNA(VLOOKUP(TablaPrecios[[#This Row],[Producto]],'[1]Costo Materia Prima'!A$3:K$424,11,FALSE),"") -> 46042
A46: Corrufacil | B46: Corrufacil | D46: Capacillo Mini #72 | E46: Capacillo #72 Rosa C/10,000 pzs | F46: =_xlfn.IFNA(VLOOKUP(TablaPrecios[[#This Row],[Producto]],'[1]Costo Materia Prima'!A$3:K$424,3,FALSE),"") -> 11500 | G46: =_xlfn.IFNA(VLOOKUP(TablaPrecios[[#This Row],[Producto]],'[1]Costo Materia Prima'!A$3:K$424,4,FALSE),"") -> PZ | H46: =_xlfn.IFNA(VLOOKUP(TablaPrecios[[#This Row],[Producto]],'[1]Costo Materia Prima'!A$3:K$424,5,FALSE),"") -> 4140 | I46: =IFERROR(TablaPrecios[[#This Row],[Precio]]/TablaPrecios[[#This Row],[Cantidad]],0) -> 0.36 | J46: =_xlfn.IFNA(VLOOKUP(TablaPrecios[[#This Row],[Producto]],'[1]Costo Materia Prima'!A$3:K$424,8,FALSE),"") -> PZ | K46: =_xlfn.IFNA(VLOOKUP(TablaPrecios[[#This Row],[Producto]],'[1]Costo Materia Prima'!A$3:K$424,9,FALSE),"-") -> Verificado | L46: =_xlfn.IFNA(VLOOKUP(TablaPrecios[[#This Row],[Producto]],'[1]Costo Materia Prima'!A$3:K$424,11,FALSE),"") -> 46024
A47: Corrufacil | B47: Corrufacil | C47: T-CP047-74 | D47: Capacillo | E47: Capacillo #74 Rosa C/10,000 pzs | F47: =_xlfn.IFNA(VLOOKUP(TablaPrecios[[#This Row],[Producto]],'[1]Costo Materia Prima'!A$3:K$424,3,FALSE),"") -> 20000 | G47: =_xlfn.IFNA(VLOOKUP(TablaPrecios[[#This Row],[Producto]],'[1]Costo Materia Prima'!A$3:K$424,4,FALSE),"") -> PZ | H47: =_xlfn.IFNA(VLOOKUP(TablaPrecios[[#This Row],[Producto]],'[1]Costo Materia Prima'!A$3:K$424,5,FALSE),"") -> 8005.88 | I47: =IFERROR(TablaPrecios[[#This Row],[Precio]]/TablaPrecios[[#This Row],[Cantidad]],0) -> 0.400294 | J47: =_xlfn.IFNA(VLOOKUP(TablaPrecios[[#This Row],[Producto]],'[1]Costo Materia Prima'!A$3:K$424,8,FALSE),"") -> PZ | K47: =_xlfn.IFNA(VLOOKUP(TablaPrecios[[#This Row],[Producto]],'[1]Costo Materia Prima'!A$3:K$424,9,FALSE),"-") -> Verificado | L47: =_xlfn.IFNA(VLOOKUP(TablaPrecios[[#This Row],[Producto]],'[1]Costo Materia Prima'!A$3:K$424,11,FALSE),"") -> 46042
A48: Corrufacil | B48: Corrufacil | D48: 1PZcupcake | E48: 1PZcupcake | F48: =_xlfn.IFNA(VLOOKUP(TablaPrecios[[#This Row],[Producto]],'[1]Costo Materia Prima'!A$3:K$424,3,FALSE),"") -> 74 | G48: =_xlfn.IFNA(VLOOKUP(TablaPrecios[[#This Row],[Producto]],'[1]Costo Materia Prima'!A$3:K$424,4,FALSE),"") -> PZ | H48: =_xlfn.IFNA(VLOOKUP(TablaPrecios[[#This Row],[Producto]],'[1]Costo Materia Prima'!A$3:K$424,5,FALSE),"") -> 537.98 | I48: =IFERROR(TablaPrecios[[#This Row],[Precio]]/TablaPrecios[[#This Row],[Cantidad]],0) -> 7.27 | J48: =_xlfn.IFNA(VLOOKUP(TablaPrecios[[#This Row],[Producto]],'[1]Costo Materia Prima'!A$3:K$424,8,FALSE),"") -> PZ | K48: =_xlfn.IFNA(VLOOKUP(TablaPrecios[[#This Row],[Producto]],'[1]Costo Materia Prima'!A$3:K$424,9,FALSE),"-") -> Verificado | L48: =_xlfn.IFNA(VLOOKUP(TablaPrecios[[#This Row],[Producto]],'[1]Costo Materia Prima'!A$3:K$424,11,FALSE),"") -> 45862
A49: Corrufacil | B49: Corrufacil | D49: 2PZ cupcake | E49: 2PZ cupcake | F49: =_xlfn.IFNA(VLOOKUP(TablaPrecios[[#This Row],[Producto]],'[1]Costo Materia Prima'!A$3:K$424,3,FALSE),"") -> 189 | G49: =_xlfn.IFNA(VLOOKUP(TablaPrecios[[#This Row],[Producto]],'[1]Costo Materia Prima'!A$3:K$424,4,FALSE),"") -> PZ | H49: =_xlfn.IFNA(VLOOKUP(TablaPrecios[[#This Row],[Producto]],'[1]Costo Materia Prima'!A$3:K$424,5,FALSE),"") -> 1563.03 | I49: =IFERROR(TablaPrecios[[#This Row],[Precio]]/TablaPrecios[[#This Row],[Cantidad]],0) -> 8.27 | J49: =_xlfn.IFNA(VLOOKUP(TablaPrecios[[#This Row],[Producto]],'[1]Costo Materia Prima'!A$3:K$424,8,FALSE),"") -> PZ | K49: =_xlfn.IFNA(VLOOKUP(TablaPrecios[[#This Row],[Producto]],'[1]Costo Materia Prima'!A$3:K$424,9,FALSE),"-") -> Verificado | L49: =_xlfn.IFNA(VLOOKUP(TablaPrecios[[#This Row],[Producto]],'[1]Costo Materia Prima'!A$3:K$424,11,FALSE),"") -> 45862
A50: Corrufacil | B50: Corrufacil | D50: 4PZCupcake | E50: 4PZCupcake | F50: =_xlfn.IFNA(VLOOKUP(TablaPrecios[[#This Row],[Producto]],'[1]Costo Materia Prima'!A$3:K$424,3,FALSE),"") -> 122 | G50: =_xlfn.IFNA(VLOOKUP(TablaPrecios[[#This Row],[Producto]],'[1]Costo Materia Prima'!A$3:K$424,4,FALSE),"") -> PZ | H50: =_xlfn.IFNA(VLOOKUP(TablaPrecios[[#This Row],[Producto]],'[1]Costo Materia Prima'!A$3:K$424,5,FALSE),"") -> 1277.34 | I50: =IFERROR(TablaPrecios[[#This Row],[Precio]]/TablaPrecios[[#This Row],[Cantidad]],0) -> 10.47 | J50: =_xlfn.IFNA(VLOOKUP(TablaPrecios[[#This Row],[Producto]],'[1]Costo Materia Prima'!A$3:K$424,8,FALSE),"") -> PZ | K50: =_xlfn.IFNA(VLOOKUP(TablaPrecios[[#This Row],[Producto]],'[1]Costo Materia Prima'!A$3:K$424,9,FALSE),"-") -> Verificado | L50: =_xlfn.IFNA(VLOOKUP(TablaPrecios[[#This Row],[Producto]],'[1]Costo Materia Prima'!A$3:K$424,11,FALSE),"") -> 45862
A51: Corrufacil | B51: Corrufacil | D51: 6PZ cupcake | E51: 6PZ cupcake | F51: =_xlfn.IFNA(VLOOKUP(TablaPrecios[[#This Row],[Producto]],'[1]Costo Materia Prima'!A$3:K$424,3,FALSE),"") -> 0 | G51: =_xlfn.IFNA(VLOOKUP(TablaPrecios[[#This Row],[Producto]],'[1]Costo Materia Prima'!A$3:K$424,4,FALSE),"") -> PZ | H51: =_xlfn.IFNA(VLOOKUP(TablaPrecios[[#This Row],[Producto]],'[1]Costo Materia Prima'!A$3:K$424,5,FALSE),"") -> 0 | I51: =IFERROR(TablaPrecios[[#This Row],[Precio]]/TablaPrecios[[#This Row],[Cantidad]],0) -> 0 | J51: =_xlfn.IFNA(VLOOKUP(TablaPrecios[[#This Row],[Producto]],'[1]Costo Materia Prima'!A$3:K$424,8,FALSE),"") -> PZ | K51: =_xlfn.IFNA(VLOOKUP(TablaPrecios[[#This Row],[Producto]],'[1]Costo Materia Prima'!A$3:K$424,9,FALSE),"-") -> Verificado | L51: =_xlfn.IFNA(VLOOKUP(TablaPrecios[[#This Row],[Producto]],'[1]Costo Materia Prima'!A$3:K$424,11,FALSE),"") -> 45862
A52: Corrufacil | B52: Corrufacil | D52: 12PZ cupcake | E52: 12PZ cupcake | F52: =_xlfn.IFNA(VLOOKUP(TablaPrecios[[#This Row],[Producto]],'[1]Costo Materia Prima'!A$3:K$424,3,FALSE),"") -> 0 | G52: =_xlfn.IFNA(VLOOKUP(TablaPrecios[[#This Row],[Producto]],'[1]Costo Materia Prima'!A$3:K$424,4,FALSE),"") -> PZ | H52: =_xlfn.IFNA(VLOOKUP(TablaPrecios[[#This Row],[Producto]],'[1]Costo Materia Prima'!A$3:K$424,5,FALSE),"") -> 0 | I52: =IFERROR(TablaPrecios[[#This Row],[Precio]]/TablaPrecios[[#This Row],[Cantidad]],0) -> 0 | J52: =_xlfn.IFNA(VLOOKUP(TablaPrecios[[#This Row],[Producto]],'[1]Costo Materia Prima'!A$3:K$424,8,FALSE),"") -> PZ | K52: =_xlfn.IFNA(VLOOKUP(TablaPrecios[[#This Row],[Producto]],'[1]Costo Materia Prima'!A$3:K$424,9,FALSE),"-") -> Verificado | L52: =_xlfn.IFNA(VLOOKUP(TablaPrecios[[#This Row],[Producto]],'[1]Costo Materia Prima'!A$3:K$424,11,FALSE),"") -> 45862
A53: COSTCO | B53: Costco | D53: Crunch Barra | E53: Crunch en barra paquete de 16 pz | F53: =_xlfn.IFNA(VLOOKUP(TablaPrecios[[#This Row],[Producto]],'[1]Costo Materia Prima'!A$3:K$424,3,FALSE),"") -> 0 | G53: =_xlfn.IFNA(VLOOKUP(TablaPrecios[[#This Row],[Producto]],'[1]Costo Materia Prima'!A$3:K$424,4,FALSE),"") -> PZ | H53: =_xlfn.IFNA(VLOOKUP(TablaPrecios[[#This Row],[Producto]],'[1]Costo Materia Prima'!A$3:K$424,5,FALSE),"") -> 0 | I53: =IFERROR(TablaPrecios[[#This Row],[Precio]]/TablaPrecios[[#This Row],[Cantidad]],0) -> 0 | J53: =_xlfn.IFNA(VLOOKUP(TablaPrecios[[#This Row],[Producto]],'[1]Costo Materia Prima'!A$3:K$424,8,FALSE),"") -> PZ | K53: =_xlfn.IFNA(VLOOKUP(TablaPrecios[[#This Row],[Producto]],'[1]Costo Materia Prima'!A$3:K$424,9,FALSE),"-") -> Verificado | L53: =_xlfn.IFNA(VLOOKUP(TablaPrecios[[#This Row],[Producto]],'[1]Costo Materia Prima'!A$3:K$424,11,FALSE),"") -> 46024
A54: COSTCO | B54: Costco | D54: Azucar Mascabado | E54: Azucar Mascabado | F54: =_xlfn.IFNA(VLOOKUP(TablaPrecios[[#This Row],[Producto]],'[1]Costo Materia Prima'!A$3:K$424,3,FALSE),"") -> 30 | G54: =_xlfn.IFNA(VLOOKUP(TablaPrecios[[#This Row],[Producto]],'[1]Costo Materia Prima'!A$3:K$424,4,FALSE),"") -> KG | H54: =_xlfn.IFNA(VLOOKUP(TablaPrecios[[#This Row],[Producto]],'[1]Costo Materia Prima'!A$3:K$424,5,FALSE),"") -> 1554 | I54: =IFERROR(TablaPrecios[[#This Row],[Precio]]/TablaPrecios[[#This Row],[Cantidad]],0) -> 51.8 | J54: =_xlfn.IFNA(VLOOKUP(TablaPrecios[[#This Row],[Producto]],'[1]Costo Materia Prima'!A$3:K$424,8,FALSE),"") -> KG | K54: =_xlfn.IFNA(VLOOKUP(TablaPrecios[[#This Row],[Producto]],'[1]Costo Materia Prima'!A$3:K$424,9,FALSE),"-") -> Verificado | L54: =_xlfn.IFNA(VLOOKUP(TablaPrecios[[#This Row],[Producto]],'[1]Costo Materia Prima'!A$3:K$424,11,FALSE),"") -> 46042
A55: COSTCO | B55: Costco | C55: Sin Clave | D55: Harina Brownie | E55: Caja de harina para brownies (2.26 kg empaque con 4 costales) | F55: =_xlfn.IFNA(VLOOKUP(TablaPrecios[[#This Row],[Producto]],'[1]Costo Materia Prima'!A$3:K$424,3,FALSE),"") -> 3.06 | G55: =_xlfn.IFNA(VLOOKUP(TablaPrecios[[#This Row],[Producto]],'[1]Costo Materia Prima'!A$3:K$424,4,FALSE),"") -> KG | H55: =_xlfn.IFNA(VLOOKUP(TablaPrecios[[#This Row],[Producto]],'[1]Costo Materia Prima'!A$3:K$424,5,FALSE),"") -> 414 | I55: =IFERROR(TablaPrecios[[#This Row],[Precio]]/TablaPrecios[[#This Row],[Cantidad]],0) -> 135.29412 | J55: =_xlfn.IFNA(VLOOKUP(TablaPrecios[[#This Row],[Producto]],'[1]Costo Materia Prima'!A$3:K$424,8,FALSE),"") -> KG | K55: =_xlfn.IFNA(VLOOKUP(TablaPrecios[[#This Row],[Producto]],'[1]Costo Materia Prima'!A$3:K$424,9,FALSE),"-") -> Verificado | L55: =_xlfn.IFNA(VLOOKUP(TablaPrecios[[#This Row],[Producto]],'[1]Costo Materia Prima'!A$3:K$424,11,FALSE),"") -> 46024
A56: COSTCO | B56: Costco | D56: Almendra | E56: Almendra fileteada 0.906 KG | F56: =_xlfn.IFNA(VLOOKUP(TablaPrecios[[#This Row],[Producto]],'[1]Costo Materia Prima'!A$3:K$424,3,FALSE),"") -> 10 | G56: =_xlfn.IFNA(VLOOKUP(TablaPrecios[[#This Row],[Producto]],'[1]Costo Materia Prima'!A$3:K$424,4,FALSE),"") -> KG | H56: =_xlfn.IFNA(VLOOKUP(TablaPrecios[[#This Row],[Producto]],'[1]Costo Materia Prima'!A$3:K$424,5,FALSE),"") -> 2560 | I56: =IFERROR(TablaPrecios[[#This Row],[Precio]]/TablaPrecios[[#This Row],[Cantidad]],0) -> 256 | J56: =_xlfn.IFNA(VLOOKUP(TablaPrecios[[#This Row],[Producto]],'[1]Costo Materia Prima'!A$3:K$424,8,FALSE),"") -> KG | K56: =_xlfn.IFNA(VLOOKUP(TablaPrecios[[#This Row],[Producto]],'[1]Costo Materia Prima'!A$3:K$424,9,FALSE),"-") -> Verificado | L56: =_xlfn.IFNA(VLOOKUP(TablaPrecios[[#This Row],[Producto]],'[1]Costo Materia Prima'!A$3:K$424,11,FALSE),"") -> 46042
A57: Cremería Junior | B57: Cremería Junior | D57: Huevo | E57: Cartera Huevo | F57: =_xlfn.IFNA(VLOOKUP(TablaPrecios[[#This Row],[Producto]],'[1]Costo Materia Prima'!A$3:K$424,3,FALSE),"") -> 2160 | G57: =_xlfn.IFNA(VLOOKUP(TablaPrecios[[#This Row],[Producto]],'[1]Costo Materia Prima'!A$3:K$424,4,FALSE),"") -> PZ/CART | H57: =_xlfn.IFNA(VLOOKUP(TablaPrecios[[#This Row],[Producto]],'[1]Costo Materia Prima'!A$3:K$424,5,FALSE),"") -> 3900.24 | I57: =IFERROR(TablaPrecios[[#This Row],[Precio]]/TablaPrecios[[#This Row],[Cantidad]],0) -> 1.8056667 | J57: =_xlfn.IFNA(VLOOKUP(TablaPrecios[[#This Row],[Producto]],'[1]Costo Materia Prima'!A$3:K$424,8,FALSE),"") -> PZ | K57: =_xlfn.IFNA(VLOOKUP(TablaPrecios[[#This Row],[Producto]],'[1]Costo Materia Prima'!A$3:K$424,9,FALSE),"-") -> Verificado | L57: =_xlfn.IFNA(VLOOKUP(TablaPrecios[[#This Row],[Producto]],'[1]Costo Materia Prima'!A$3:K$424,11,FALSE),"") -> 46042
A58: Dawn | B58: Dawn | C58: 29519092450 | D58: Especial Devils | E58: PST BS DELUXE DEVILS FOO (saco de 22.68kg) | F58: =_xlfn.IFNA(VLOOKUP(TablaPrecios[[#This Row],[Producto]],'[1]Costo Materia Prima'!A$3:K$424,3,FALSE),"") -> 0 | G58: =_xlfn.IFNA(VLOOKUP(TablaPrecios[[#This Row],[Producto]],'[1]Costo Materia Prima'!A$3:K$424,4,FALSE),"") -> KG | H58: =_xlfn.IFNA(VLOOKUP(TablaPrecios[[#This Row],[Producto]],'[1]Costo Materia Prima'!A$3:K$424,5,FALSE),"") -> 0 | I58: =IFERROR(TablaPrecios[[#This Row],[Precio]]/TablaPrecios[[#This Row],[Cantidad]],0) -> 0 | J58: =_xlfn.IFNA(VLOOKUP(TablaPrecios[[#This Row],[Producto]],'[1]Costo Materia Prima'!A$3:K$424,8,FALSE),"") -> KG | K58: =_xlfn.IFNA(VLOOKUP(TablaPrecios[[#This Row],[Producto]],'[1]Costo Materia Prima'!A$3:K$424,9,FALSE),"-") -> Verificado | L58: =_xlfn.IFNA(VLOOKUP(TablaPrecios[[#This Row],[Producto]],'[1]Costo Materia Prima'!A$3:K$424,11,FALSE),"") -> 46024
A59: Dawn | B59: Dawn | D59: Deleite Chocolate | E59: LINEA DELEITE CHOCOLATE CREME CAKE | F59: =_xlfn.IFNA(VLOOKUP(TablaPrecios[[#This Row],[Producto]],'[1]Costo Materia Prima'!A$3:K$424,3,FALSE),"") -> 720 | G59: =_xlfn.IFNA(VLOOKUP(TablaPrecios[[#This Row],[Producto]],'[1]Costo Materia Prima'!A$3:K$424,4,FALSE),"") -> KG | H59: =_xlfn.IFNA(VLOOKUP(TablaPrecios[[#This Row],[Producto]],'[1]Costo Materia Prima'!A$3:K$424,5,FALSE),"") -> 38896 | I59: =IFERROR(TablaPrecios[[#This Row],[Precio]]/TablaPrecios[[#This Row],[Cantidad]],0) -> 54.022222 | J59: =_xlfn.IFNA(VLOOKUP(TablaPrecios[[#This Row],[Producto]],'[1]Costo Materia Prima'!A$3:K$424,8,FALSE),"") -> KG | K59: =_xlfn.IFNA(VLOOKUP(TablaPrecios[[#This Row],[Producto]],'[1]Costo Materia Prima'!A$3:K$424,9,FALSE),"-") -> Verificado | L59: =_xlfn.IFNA(VLOOKUP(TablaPrecios[[#This Row],[Producto]],'[1]Costo Materia Prima'!A$3:K$424,11,FALSE),"") -> 46042
A60: Dawn | B60: Dawn | C60: 29519079936 | D60: Devils Chocolate | E60: RICHCRM CHOC CK BS (saco de 22.68 kg) | F60: =_xlfn.IFNA(VLOOKUP(TablaPrecios[[#This Row],[Producto]],'[1]Costo Materia Prima'!A$3:K$424,3,FALSE),"") -> 0 | G60: =_xlfn.IFNA(VLOOKUP(TablaPrecios[[#This Row],[Producto]],'[1]Costo Materia Prima'!A$3:K$424,4,FALSE),"") -> KG | H60: =_xlfn.IFNA(VLOOKUP(TablaPrecios[[#This Row],[Producto]],'[1]Costo Materia Prima'!A$3:K$424,5,FALSE),"") -> 0 | I60: =IFERROR(TablaPrecios[[#This Row],[Precio]]/TablaPrecios[[#This Row],[Cantidad]],0) -> 0 | J60: =_xlfn.IFNA(VLOOKUP(TablaPrecios[[#This Row],[Producto]],'[1]Costo Materia Prima'!A$3:K$424,8,FALSE),"") -> KG | K60: =_xlfn.IFNA(VLOOKUP(TablaPrecios[[#This Row],[Producto]],'[1]Costo Materia Prima'!A$3:K$424,9,FALSE),"-") -> Verificado | L60: =_xlfn.IFNA(VLOOKUP(TablaPrecios[[#This Row],[Producto]],'[1]Costo Materia Prima'!A$3:K$424,11,FALSE),"") -> 46024
A61: Dawn | B61: Dawn | D61: Vainilla Dawn | E61: DAWN Cake BS Cream Spec | F61: =_xlfn.IFNA(VLOOKUP(TablaPrecios[[#This Row],[Producto]],'[1]Costo Materia Prima'!A$3:K$424,3,FALSE),"") -> 1632.96 | G61: =_xlfn.IFNA(VLOOKUP(TablaPrecios[[#This Row],[Producto]],'[1]Costo Materia Prima'!A$3:K$424,4,FALSE),"") -> KG | H61: =_xlfn.IFNA(VLOOKUP(TablaPrecios[[#This Row],[Producto]],'[1]Costo Materia Prima'!A$3:K$424,5,FALSE),"") -> 72841.6 | I61: =IFERROR(TablaPrecios[[#This Row],[Precio]]/TablaPrecios[[#This Row],[Cantidad]],0) -> 44.607094 | J61: =_xlfn.IFNA(VLOOKUP(TablaPrecios[[#This Row],[Producto]],'[1]Costo Materia Prima'!A$3:K$424,8,FALSE),"") -> KG | K61: =_xlfn.IFNA(VLOOKUP(TablaPrecios[[#This Row],[Producto]],'[1]Costo Materia Prima'!A$3:K$424,9,FALSE),"-") -> Verificado | L61: =_xlfn.IFNA(VLOOKUP(TablaPrecios[[#This Row],[Producto]],'[1]Costo Materia Prima'!A$3:K$424,11,FALSE),"") -> 46042
A62: Dawn | B62: Dawn | D62: Dona Dawn | E62: Dona Dawn | F62: =_xlfn.IFNA(VLOOKUP(TablaPrecios[[#This Row],[Producto]],'[1]Costo Materia Prima'!A$3:K$424,3,FALSE),"") -> 720 | G62: =_xlfn.IFNA(VLOOKUP(TablaPrecios[[#This Row],[Producto]],'[1]Costo Materia Prima'!A$3:K$424,4,FALSE),"") -> PZ | H62: =_xlfn.IFNA(VLOOKUP(TablaPrecios[[#This Row],[Producto]],'[1]Costo Materia Prima'!A$3:K$424,5,FALSE),"") -> 3921.51 | I62: =IFERROR(TablaPrecios[[#This Row],[Precio]]/TablaPrecios[[#This Row],[Cantidad]],0) -> 5.4465417 | J62: =_xlfn.IFNA(VLOOKUP(TablaPrecios[[#This Row],[Producto]],'[1]Costo Materia Prima'!A$3:K$424,8,FALSE),"") -> PZ | K62: =_xlfn.IFNA(VLOOKUP(TablaPrecios[[#This Row],[Producto]],'[1]Costo Materia Prima'!A$3:K$424,9,FALSE),"-") -> Verificado | L62: =_xlfn.IFNA(VLOOKUP(TablaPrecios[[#This Row],[Producto]],'[1]Costo Materia Prima'!A$3:K$424,11,FALSE),"") -> 46024
D63: Glaseado | E63: Glaseado | F63: =_xlfn.IFNA(VLOOKUP(TablaPrecios[[#This Row],[Producto]],'[1]Costo Materia Prima'!A$3:K$424,3,FALSE),"") | G63: =_xlfn.IFNA(VLOOKUP(TablaPrecios[[#This Row],[Producto]],'[1]Costo Materia Prima'!A$3:K$424,4,FALSE),"") | H63: =_xlfn.IFNA(VLOOKUP(TablaPrecios[[#This Row],[Producto]],'[1]Costo Materia Prima'!A$3:K$424,5,FALSE),"") | I63: =IFERROR(TablaPrecios[[#This Row],[Precio]]/TablaPrecios[[#This Row],[Cantidad]],0) -> 0 | J63: =_xlfn.IFNA(VLOOKUP(TablaPrecios[[#This Row],[Producto]],'[1]Costo Materia Prima'!A$3:K$424,8,FALSE),"") | K63: =_xlfn.IFNA(VLOOKUP(TablaPrecios[[#This Row],[Producto]],'[1]Costo Materia Prima'!A$3:K$424,9,FALSE),"-") -> - | L63: =_xlfn.IFNA(VLOOKUP(TablaPrecios[[#This Row],[Producto]],'[1]Costo Materia Prima'!A$3:K$424,11,FALSE),"")
A64: Distribuciones Santa Cruz | D64: Mantequilla Flex | E64: Mantequilla Flex | F64: =_xlfn.IFNA(VLOOKUP(TablaPrecios[[#This Row],[Producto]],'[1]Costo Materia Prima'!A$3:K$424,3,FALSE),"") -> 20 | G64: =_xlfn.IFNA(VLOOKUP(TablaPrecios[[#This Row],[Producto]],'[1]Costo Materia Prima'!A$3:K$424,4,FALSE),"") -> KG | H64: =_xlfn.IFNA(VLOOKUP(TablaPrecios[[#This Row],[Producto]],'[1]Costo Materia Prima'!A$3:K$424,5,FALSE),"") -> 1160 | I64: =IFERROR(TablaPrecios[[#This Row],[Precio]]/TablaPrecios[[#This Row],[Cantidad]],0) -> 58 | J64: =_xlfn.IFNA(VLOOKUP(TablaPrecios[[#This Row],[Producto]],'[1]Costo Materia Prima'!A$3:K$424,8,FALSE),"") -> KG | K64: =_xlfn.IFNA(VLOOKUP(TablaPrecios[[#This Row],[Producto]],'[1]Costo Materia Prima'!A$3:K$424,9,FALSE),"-") -> Verificado | L64: =_xlfn.IFNA(VLOOKUP(TablaPrecios[[#This Row],[Producto]],'[1]Costo Materia Prima'!A$3:K$424,11,FALSE),"") -> 46042
A65: Distribuciones Santa Cruz | B65: Santa Cruz | D65: Relleno Manzana | E65: Relleno de manzana F. Fillinf Cub/37 LBX | F65: =_xlfn.IFNA(VLOOKUP(TablaPrecios[[#This Row],[Producto]],'[1]Costo Materia Prima'!A$3:K$424,3,FALSE),"") -> 16.78 | G65: =_xlfn.IFNA(VLOOKUP(TablaPrecios[[#This Row],[Producto]],'[1]Costo Materia Prima'!A$3:K$424,4,FALSE),"") -> KG | H65: =_xlfn.IFNA(VLOOKUP(TablaPrecios[[#This Row],[Producto]],'[1]Costo Materia Prima'!A$3:K$424,5,FALSE),"") -> 1392.3 | I65: =IFERROR(TablaPrecios[[#This Row],[Precio]]/TablaPrecios[[#This Row],[Cantidad]],0) -> 82.973778 | J65: =_xlfn.IFNA(VLOOKUP(TablaPrecios[[#This Row],[Producto]],'[1]Costo Materia Prima'!A$3:K$424,8,FALSE),"") -> KG | K65: =_xlfn.IFNA(VLOOKUP(TablaPrecios[[#This Row],[Producto]],'[1]Costo Materia Prima'!A$3:K$424,9,FALSE),"-") -> Verificado | L65: =_xlfn.IFNA(VLOOKUP(TablaPrecios[[#This Row],[Producto]],'[1]Costo Materia Prima'!A$3:K$424,11,FALSE),"") -> 46042
A66: Dulceria Yoli | B66: Yoli | D66: Colorante Mermelada Rojo | E66: Colorante rojo | F66: =_xlfn.IFNA(VLOOKUP(TablaPrecios[[#This Row],[Producto]],'[1]Costo Materia Prima'!A$3:K$424,3,FALSE),"") -> 3 | G66: =_xlfn.IFNA(VLOOKUP(TablaPrecios[[#This Row],[Producto]],'[1]Costo Materia Prima'!A$3:K$424,4,FALSE),"") -> KG | H66: =_xlfn.IFNA(VLOOKUP(TablaPrecios[[#This Row],[Producto]],'[1]Costo Materia Prima'!A$3:K$424,5,FALSE),"") -> 1215 | I66: =IFERROR(TablaPrecios[[#This Row],[Precio]]/TablaPrecios[[#This Row],[Cantidad]],0) -> 405 | J66: =_xlfn.IFNA(VLOOKUP(TablaPrecios[[#This Row],[Producto]],'[1]Costo Materia Prima'!A$3:K$424,8,FALSE),"") -> KG | K66: =_xlfn.IFNA(VLOOKUP(TablaPrecios[[#This Row],[Producto]],'[1]Costo Materia Prima'!A$3:K$424,9,FALSE),"-") -> Verificado | L66: =_xlfn.IFNA(VLOOKUP(TablaPrecios[[#This Row],[Producto]],'[1]Costo Materia Prima'!A$3:K$424,11,FALSE),"") -> 46042
A67: Dulceria Yoli | B67: Yoli | D67: Ácido Cítrico | E67: Ácido cítrico | F67: =_xlfn.IFNA(VLOOKUP(TablaPrecios[[#This Row],[Producto]],'[1]Costo Materia Prima'!A$3:K$424,3,FALSE),"") -> 5 | G67: =_xlfn.IFNA(VLOOKUP(TablaPrecios[[#This Row],[Producto]],'[1]Costo Materia Prima'!A$3:K$424,4,FALSE),"") -> KG | H67: =_xlfn.IFNA(VLOOKUP(TablaPrecios[[#This Row],[Producto]],'[1]Costo Materia Prima'!A$3:K$424,5,FALSE),"") -> 195 | I67: =IFERROR(TablaPrecios[[#This Row],[Precio]]/TablaPrecios[[#This Row],[Cantidad]],0) -> 39 | J67: =_xlfn.IFNA(VLOOKUP(TablaPrecios[[#This Row],[Producto]],'[1]Costo Materia Prima'!A$3:K$424,8,FALSE),"") -> KG | K67: =_xlfn.IFNA(VLOOKUP(TablaPrecios[[#This Row],[Producto]],'[1]Costo Materia Prima'!A$3:K$424,9,FALSE),"-") -> Verificado | L67: =_xlfn.IFNA(VLOOKUP(TablaPrecios[[#This Row],[Producto]],'[1]Costo Materia Prima'!A$3:K$424,11,FALSE),"") -> 46042
A68: Dulceria Yoli | B68: Yoli | D68: Cuchara Rebanada | E68: Fantasy Cuchara Fantasy Chica | F68: =_xlfn.IFNA(VLOOKUP(TablaPrecios[[#This Row],[Producto]],'[1]Costo Materia Prima'!A$3:K$424,3,FALSE),"") -> 6000 | G68: =_xlfn.IFNA(VLOOKUP(TablaPrecios[[#This Row],[Producto]],'[1]Costo Materia Prima'!A$3:K$424,4,FALSE),"") -> Unidad | H68: =_xlfn.IFNA(VLOOKUP(TablaPrecios[[#This Row],[Producto]],'[1]Costo Materia Prima'!A$3:K$424,5,FALSE),"") -> 780 | I68: =IFERROR(TablaPrecios[[#This Row],[Precio]]/TablaPrecios[[#This Row],[Cantidad]],0) -> 0.13 | J68: =_xlfn.IFNA(VLOOKUP(TablaPrecios[[#This Row],[Producto]],'[1]Costo Materia Prima'!A$3:K$424,8,FALSE),"") -> UN | K68: =_xlfn.IFNA(VLOOKUP(TablaPrecios[[#This Row],[Producto]],'[1]Costo Materia Prima'!A$3:K$424,9,FALSE),"-") -> Verificado | L68: =_xlfn.IFNA(VLOOKUP(TablaPrecios[[#This Row],[Producto]],'[1]Costo Materia Prima'!A$3:K$424,11,FALSE),"") -> 46042
A69: Dulceria Yoli | D69: Cuchara Fresas | E69: Fantasy Cuchara Coctelera | F69: =_xlfn.IFNA(VLOOKUP(TablaPrecios[[#This Row],[Producto]],'[1]Costo Materia Prima'!A$3:K$424,3,FALSE),"") -> 3000 | G69: =_xlfn.IFNA(VLOOKUP(TablaPrecios[[#This Row],[Producto]],'[1]Costo Materia Prima'!A$3:K$424,4,FALSE),"") -> Unidad | H69: =_xlfn.IFNA(VLOOKUP(TablaPrecios[[#This Row],[Producto]],'[1]Costo Materia Prima'!A$3:K$424,5,FALSE),"") -> 1139.99 | I69: =IFERROR(TablaPrecios[[#This Row],[Precio]]/TablaPrecios[[#This Row],[Cantidad]],0) -> 0.37999667 | J69: =_xlfn.IFNA(VLOOKUP(TablaPrecios[[#This Row],[Producto]],'[1]Costo Materia Prima'!A$3:K$424,8,FALSE),"") -> UN | K69: =_xlfn.IFNA(VLOOKUP(TablaPrecios[[#This Row],[Producto]],'[1]Costo Materia Prima'!A$3:K$424,9,FALSE),"-") -> Verificado | L69: =_xlfn.IFNA(VLOOKUP(TablaPrecios[[#This Row],[Producto]],'[1]Costo Materia Prima'!A$3:K$424,11,FALSE),"") -> 46042
A70: Dulceria Yoli | D70: Tapa Vasos Domo | E70: Tapadera hueca para vasos con crema | F70: =_xlfn.IFNA(VLOOKUP(TablaPrecios[[#This Row],[Producto]],'[1]Costo Materia Prima'!A$3:K$424,3,FALSE),"") -> 1000 | G70: =_xlfn.IFNA(VLOOKUP(TablaPrecios[[#This Row],[Producto]],'[1]Costo Materia Prima'!A$3:K$424,4,FALSE),"") -> PZ | H70: =_xlfn.IFNA(VLOOKUP(TablaPrecios[[#This Row],[Producto]],'[1]Costo Materia Prima'!A$3:K$424,5,FALSE),"") -> 834.66 | I70: =IFERROR(TablaPrecios[[#This Row],[Precio]]/TablaPrecios[[#This Row],[Cantidad]],0) -> 0.83466 | J70: =_xlfn.IFNA(VLOOKUP(TablaPrecios[[#This Row],[Producto]],'[1]Costo Materia Prima'!A$3:K$424,8,FALSE),"") -> PZ | K70: =_xlfn.IFNA(VLOOKUP(TablaPrecios[[#This Row],[Producto]],'[1]Costo Materia Prima'!A$3:K$424,9,FALSE),"-") -> Verificado | L70: =_xlfn.IFNA(VLOOKUP(TablaPrecios[[#This Row],[Producto]],'[1]Costo Materia Prima'!A$3:K$424,11,FALSE),"") -> 46024
A71: Dulceria Yoli | B71: Yoli | D71: BolsaCamisetaReb | E71: Anguiano Bolsa Camiseta Chica | F71: =_xlfn.IFNA(VLOOKUP(TablaPrecios[[#This Row],[Producto]],'[1]Costo Materia Prima'!A$3:K$424,3,FALSE),"") -> 0 | G71: =_xlfn.IFNA(VLOOKUP(TablaPrecios[[#This Row],[Producto]],'[1]Costo Materia Prima'!A$3:K$424,4,FALSE),"") -> KG | H71: =_xlfn.IFNA(VLOOKUP(TablaPrecios[[#This Row],[Producto]],'[1]Costo Materia Prima'!A$3:K$424,5,FALSE),"") -> 0 | I71: =IFERROR(TablaPrecios[[#This Row],[Precio]]/TablaPrecios[[#This Row],[Cantidad]],0) -> 0 | J71: =_xlfn.IFNA(VLOOKUP(TablaPrecios[[#This Row],[Producto]],'[1]Costo Materia Prima'!A$3:K$424,8,FALSE),"") -> KG | K71: =_xlfn.IFNA(VLOOKUP(TablaPrecios[[#This Row],[Producto]],'[1]Costo Materia Prima'!A$3:K$424,9,FALSE),"-") -> Verificado | L71: =_xlfn.IFNA(VLOOKUP(TablaPrecios[[#This Row],[Producto]],'[1]Costo Materia Prima'!A$3:K$424,11,FALSE),"") -> 46024
A72: ENCO | B72: ENCO | D72: Polvo de Merengue | E72: Polvo de Merengue | F72: =_xlfn.IFNA(VLOOKUP(TablaPrecios[[#This Row],[Producto]],'[1]Costo Materia Prima'!A$3:K$424,3,FALSE),"") -> 84 | G72: =_xlfn.IFNA(VLOOKUP(TablaPrecios[[#This Row],[Producto]],'[1]Costo Materia Prima'!A$3:K$424,4,FALSE),"") -> KG | H72: =_xlfn.IFNA(VLOOKUP(TablaPrecios[[#This Row],[Producto]],'[1]Costo Materia Prima'!A$3:K$424,5,FALSE),"") -> 24182.06 | I72: =IFERROR(TablaPrecios[[#This Row],[Precio]]/TablaPrecios[[#This Row],[Cantidad]],0) -> 287.88167 | J72: =_xlfn.IFNA(VLOOKUP(TablaPrecios[[#This Row],[Producto]],'[1]Costo Materia Prima'!A$3:K$424,8,FALSE),"") -> KG | K72: =_xlfn.IFNA(VLOOKUP(TablaPrecios[[#This Row],[Producto]],'[1]Costo Materia Prima'!A$3:K$424,9,FALSE),"-") -> Verificado | L72: =_xlfn.IFNA(VLOOKUP(TablaPrecios[[#This Row],[Producto]],'[1]Costo Materia Prima'!A$3:K$424,11,FALSE),"") -> 46042
A73: Etiquetas Gráficas | B73: Etiquetas | D73: EtiquetaGrande | E73: Etiqueta Grande | F73: =_xlfn.IFNA(VLOOKUP(TablaPrecios[[#This Row],[Producto]],'[1]Costo Materia Prima'!A$3:K$424,3,FALSE),"") -> 5500 | G73: =_xlfn.IFNA(VLOOKUP(TablaPrecios[[#This Row],[Producto]],'[1]Costo Materia Prima'!A$3:K$424,4,FALSE),"") -> PZ | H73: =_xlfn.IFNA(VLOOKUP(TablaPrecios[[#This Row],[Producto]],'[1]Costo Materia Prima'!A$3:K$424,5,FALSE),"") -> 2360.6 | I73: =IFERROR(TablaPrecios[[#This Row],[Precio]]/TablaPrecios[[#This Row],[Cantidad]],0) -> 0.4292 | J73: =_xlfn.IFNA(VLOOKUP(TablaPrecios[[#This Row],[Producto]],'[1]Costo Materia Prima'!A$3:K$424,8,FALSE),"") -> PZ | K73: =_xlfn.IFNA(VLOOKUP(TablaPrecios[[#This Row],[Producto]],'[1]Costo Materia Prima'!A$3:K$424,9,FALSE),"-") -> Verificado | L73: =_xlfn.IFNA(VLOOKUP(TablaPrecios[[#This Row],[Producto]],'[1]Costo Materia Prima'!A$3:K$424,11,FALSE),"") -> 46042
A74: Etiquetas Gráficas | D74: Etiqueta Aviso | E74: Etiqueta Aviso | F74: =_xlfn.IFNA(VLOOKUP(TablaPrecios[[#This Row],[Producto]],'[1]Costo Materia Prima'!A$3:K$424,3,FALSE),"") -> 10000 | G74: =_xlfn.IFNA(VLOOKUP(TablaPrecios[[#This Row],[Producto]],'[1]Costo Materia Prima'!A$3:K$424,4,FALSE),"") -> PZ | H74: =_xlfn.IFNA(VLOOKUP(TablaPrecios[[#This Row],[Producto]],'[1]Costo Materia Prima'!A$3:K$424,5,FALSE),"") -> 5568 | I74: =IFERROR(TablaPrecios[[#This Row],[Precio]]/TablaPrecios[[#This Row],[Cantidad]],0) -> 0.5568 | J74: =_xlfn.IFNA(VLOOKUP(TablaPrecios[[#This Row],[Producto]],'[1]Costo Materia Prima'!A$3:K$424,8,FALSE),"") -> PZ | K74: =_xlfn.IFNA(VLOOKUP(TablaPrecios[[#This Row],[Producto]],'[1]Costo Materia Prima'!A$3:K$424,9,FALSE),"-") -> Verificado | L74: =_xlfn.IFNA(VLOOKUP(TablaPrecios[[#This Row],[Producto]],'[1]Costo Materia Prima'!A$3:K$424,11,FALSE),"") -> 46042
A75: Etiquetas Gráficas | B75: Etiquetas | D75: Etiqueta Cuadrada | E75: Etiqueta Cuadrada Celebrando Dulces Momentos | F75: =_xlfn.IFNA(VLOOKUP(TablaPrecios[[#This Row],[Producto]],'[1]Costo Materia Prima'!A$3:K$424,3,FALSE),"") -> 1 | G75: =_xlfn.IFNA(VLOOKUP(TablaPrecios[[#This Row],[Producto]],'[1]Costo Materia Prima'!A$3:K$424,4,FALSE),"") -> PZ | H75: =_xlfn.IFNA(VLOOKUP(TablaPrecios[[#This Row],[Producto]],'[1]Costo Materia Prima'!A$3:K$424,5,FALSE),"") -> 0.4988 | I75: =IFERROR(TablaPrecios[[#This Row],[Precio]]/TablaPrecios[[#This Row],[Cantidad]],0) -> 0.4988 | J75: =_xlfn.IFNA(VLOOKUP(TablaPrecios[[#This Row],[Producto]],'[1]Costo Materia Prima'!A$3:K$424,8,FALSE),"") -> PZ | K75: =_xlfn.IFNA(VLOOKUP(TablaPrecios[[#This Row],[Producto]],'[1]Costo Materia Prima'!A$3:K$424,9,FALSE),"-") -> Verificado | L75: =_xlfn.IFNA(VLOOKUP(TablaPrecios[[#This Row],[Producto]],'[1]Costo Materia Prima'!A$3:K$424,11,FALSE),"") -> 46024
